Workbook

Sheet GlobalContinent Population
A1: E | B1: A | C1: Global Population | D1: Global Population Growth | K1: E | L1: A | M1: Acrolan Population | N1: Acrolan Population Growth | O1: % of World | V1: E | W1: A | X1: Atirhan Population | Y1: Atirhan Population Growth | Z1: % of World | AG1: E | AH1: A | AI1: Ayuman Population | AJ1: Ayuma Population Growth | AK1: % of World | AR1: E | AS1: A | AT1: Mahean Population | AU1: Mahean Population Growth | AV1: % of World | BC1: E | BD1: A | BE1: Massiran Population | BF1: Massiran Population Growth | BG1: % of World | BN1: E | BO1: A | BP1: New Ayren Population | BQ1: New Ayren Population Growth | BR1: % of World | BY1: E | BZ1: A | CA1: Quian Population | CB1: Quian Population Growth | CC1: % of World
A2: =SUM(B2+250) -> 2015 | B2: 1765 | C2: =Acetoa!C2 + Acrana!C2 + Aetintio!C2 + Ahokini!C2 + Amcha!C2 + Andsaudare!C2 + Anymna!C2 + Aplasia!C2 + Arbiya!C2 + 'Areoix Lie'!C2 + Ashain!C2 + Astye!C2 + Baluyde!C2 + Byllu!C2 + 'Candenat'!C2 + 'Canldives'!C2 + 'Chaenia'!C2 + 'Cloja'!C2 + 'Crila Republic'!C2 + 'Cruthi Anoso'!C2 + 'Curata'!C2 + Dahe!C2 + Danocia!C2 + Darewa!C2 + Desaki!C2 + Deschon!C2 + 'Disal Nila'!C2 + 'Dual Cenryia'!C2 + Ealdorii!C2 + Easuhura!C2 + Eldavpir!C2 + Eldjo!C2 + 'Elja and Munusia'!C2 + Emara!C2 + Enina!C2 + Eparia!C2 + Erkizil!C2 + Estijan!C2 + Etirha!C2 + Etretes!C2 + Exilium!C2 + 'Far Lands'!C2 + 'Feio Lie'!C2 + Fermori!C2 + Finae!C2 + Fincen!C2 + 'Fire Coast'!C2 + Gaeiya!C2 + Galca!C2 + Genaire!C2 + Grazail!C2 + Guise!C2 + Haiza!C2 + Heiso!C2 + Hiwush!C2 + Hkuqo!C2 + Hyelen!C2 + Iainoa!C2 + Iareva!C2 + Ihner!C2 + Ikzen!C2 + Ilicuhe!C2 + Inania!C2 + Inrea!C2 + Iquir!C2 + Isari!C2 + Isnti!C2 + Isuibul!C2 + Jathua!C2 + Jau!C2 + Jshain!C2 + Kaastini!C2 + Koruch!C2 + Kusierna!C2 + Laselteh!C2 + Lasri!C2 + Letan!C2 + Lieri!C2 + Lycroa!C2 + Lydroa!C2 + Maalle!C2 + Mendereide!C2 + 'Merela Sta'!C2 + 'Mesjan Hyaa'!C2 + Metndria!C2 + Migoku!C2 + Myla!C2 + 'New Kizura'!C2 + 'New Misos'!C2 + 'Nheyes Si'!C2 + Nia!C2 + 'Niretui and Anulan'!C2 + 'Niul Spijan'!C2 + 'North Ayre'!C2 + Ocaun!C2 + Ohtina!C2 + Onphello!C2 + Oscairia!C2 + Othya!C2 + Otiiric!C2 + Oyreain!C2 + Ozinia!C2 + Palina!C2 + Peka!C2 + Pelan!C2 + Pelines!C2 + Pelugrotoa!C2 + 'Pha Hii'!C2 + Phuris!C2 + Praesyu!C2 + Prstreula!C2 + 'Pruim Fijan'!C2 + 'Prystr Hii'!C2 + Quidic!C2 + 'Raledria'!C2 + 'Reerica'!C2 + 'Rethern'!C2 + 'Rijan bu'!C2 + 'Rinew'!C2 + 'Rkmepuia'!C2 + 'Rtesania'!C2 + 'Ruylku'!C2 + Saa!C2 + Sadain!C2 + Sanagara!C2 + Sattle!C2 + Selaja!C2 + Seytinemas!C2 + Shinam!C2 + Shomjind!C2 + Siana!C2 + Sivoso!C2 + Slyiaduun!C2 + Stinebar!C2 + Suenan!C2 + Sunsokua!C2 + Taing!C2 + Taniduna!C2 + Taoisia!C2 + Taval!C2 + Terressin!C2 + Tomscilus!C2 + Tonder!C2 + Trevilla!C2 + Trian!C2 + Tvecoca!C2 + Ucrua!C2 + Ukhdari!C2 + Umarcia!C2 + Umendel!C2 + 'United Delet'!C2 + 'United Mihili'!C2 + Urbiqu!C2 + Uularin!C2 + Vayvele!C2 + Veelmit!C2 + Verste!C2 + Verusa!C2 + Vesozata!C2 + Viussi!C2 + Volver!C2 + Walporein!C2 + 'Welenu Fana'!C2 + 'Western Migoku'!C2 + Wundry!C2 + Yaxuto!C2 + Yihnurda!C2 + Yoprioq!C2 + Yutnitu!C2 + Zenashan!C2 + Zhanshe!C2 + Ztesh!C2 -> 6.8491801e+09 | D2: =((C2-C3)/C3) -> 0.0096461647 | K2: =SUM(L2+250) -> 2015 | L2: 1765 | M2: ='Areoix Lie'!C2 + Pelines!C2 + Terressin!C2 + Taniduna!C2 + Iquir!C2 + Deschon!C2 + Othya!C2 + Eldavpir!C2 + 'Candenat'!C2 + Jau!C2 + Viussi!C2 + Jathua!C2 + Jshain!C2 + Acetoa!C2 + Sattle!C2 + 'Reerica'!C2 + 'Feio Lie'!C2 + Umendel!C2 + 'Fire Coast'!C2 + Yoprioq!C2 + 'Rijan bu'!C2 + Saa!C2 + 'Rinew'!C2 + Enina!C2 + Trevilla!C2 -> 1.0700681e+09 | N2: =((M2-M3)/M3) -> 0.011979006 | O2: =SUM(M2/C2) -> 0.15623303 | V2: =SUM(W2+250) -> 2015 | W2: 1765 | X2: =Aetintio!C2 + Arbiya!C2 + 'Curata'!C2 + 'Disal Nila'!C2 + Etirha!C2 + Fincen!C2 + Gaeiya!C2 + Genaire!C2 + Grazail!C2 + Guise!C2 + Laselteh!C2 + Lasri!C2 + Metndria!C2 + 'New Misos'!C2 + Peka!C2 + Pelan!C2 + Phuris!C2 + 'Raledria'!C2 + Slyiaduun!C2 + Tomscilus!C2 -> 5.3743781e+08 | Y2: =((X2-X3)/X3) -> 0.011148887 | Z2: =SUM(X2/C2) -> 0.078467466 | AG2: =SUM(AH2+250) -> 2015 | AH2: 1765 | AI2: =Acrana!C2 + Danocia!C2 + Darewa!C2 + Ealdorii!C2 + Easuhura!C2 + Eldjo!C2 + Emara!C2 + Estijan!C2 + Fermori!C2 + Ikzen!C2 + Ilicuhe!C2 + Koruch!C2 + Lycroa!C2 + Lydroa!C2 + 'Merela Sta'!C2 + 'New Kizura'!C2 + 'Niul Spijan'!C2 + Palina!C2 + Praesyu!C2 + Siana!C2 + Tonder!C2 + Ukhdari!C2 + Urbiqu!C2 + Uularin!C2 + Verusa!C2 + Yaxuto!C2 + Zenashan!C2 + Hkuqo!C2 -> 9.9965908e+08 | AJ2: =((AI2-AI3)/AI3) -> 0.0066254716 | AK2: =SUM(AI2/C2) -> 0.1459531 | AR2: =SUM(AS2+250) -> 2015 | AS2: 1765 | AT2: =Amcha!C2 + Byllu!C2 + 'Chaenia'!C2 + 'Cruthi Anoso'!C2 + 'Dual Cenryia'!C2 + Exilium!C2 + Galca!C2 + Inania!C2 + Inrea!C2 + Isnti!C2 + Lieri!C2 + Ocaun!C2 + Otiiric!C2 + Ozinia!C2 + Pelugrotoa!C2 + 'Rtesania'!C2 + Sadain!C2 + Selaja!C2 + Seytinemas!C2 + Sivoso!C2 + Sunsokua!C2 + Taing!C2 + Taoisia!C2 + Trian!C2 + Vayvele!C2 -> 1.3873282e+09 | AU2: =((AT2-AT3)/AT3) -> 0.0097958061 | AV2: =SUM(AT2/C2) -> 0.2025539 | BC2: =SUM(BD2+250) -> 2015 | BD2: 1765 | BE2: ='Canldives'!C2 + 'Cloja'!C2 + Dahe!C2 + Eparia!C2 + Etretes!C2 + Haiza!C2 + Ihner!C2 + Kaastini!C2 + Kusierna!C2 + Migoku!C2 + 'North Ayre'!C2 + Oscairia!C2 + Oyreain!C2 + 'Pha Hii'!C2 + 'Pruim Fijan'!C2 + 'Prystr Hii'!C2 + 'Ruylku'!C2 + Sanagara!C2 + Shinam!C2 + Stinebar!C2 + Suenan!C2 + Taval!C2 + Ucrua!C2 + Vesozata!C2 + 'Welenu Fana'!C2 + 'Western Migoku'!C2 -> 1.3890988e+09 | BF2: =((BE2-BE3)/BE3) -> 0.0071160083 | BG2: =SUM(BE2/C2) -> 0.20281243 | BN2: =SUM(BO2+250) -> 2015 | BO2: 1765 | BP2: =Andsaudare!C2 + Aplasia!C2 + Astye!C2 + 'Crila Republic'!C2 + 'Elja and Munusia'!C2 + Hiwush!C2 + Iainoa!C2 + Isari!C2 + Isuibul!C2 + Maalle!C2 + Mendereide!C2 + Nia!C2 + 'Niretui and Anulan'!C2 + Ohtina!C2 + Prstreula!C2 + 'Rethern'!C2 + 'Rkmepuia'!C2 + Tvecoca!C2 + Umarcia!C2 + 'United Delet'!C2 + Veelmit!C2 + Walporein!C2 + Yutnitu!C2 -> 2.760672e+08 | BQ2: =((BP2-BP3)/BP3) -> 0.011087359 | BR2: =SUM(BP2/C2) -> 0.040306605 | BY2: =SUM(BZ2+250) -> 2015 | BZ2: 1765 | CA2: =Ahokini!C2 + Anymna!C2 + Ashain!C2 + Baluyde!C2 + Desaki!C2 + Erkizil!C2 + 'Far Lands'!C2 + Finae!C2 + Hyelen!C2 + Iareva!C2 + Letan!C2 + 'Mesjan Hyaa'!C2 + Myla!C2 + 'Nheyes Si'!C2 + Onphello!C2 + Quidic!C2 + Shomjind!C2 + 'United Mihili'!C2 + Verste!C2 + Volver!C2 + Wundry!C2 + Yihnurda!C2 + Zhanshe!C2 + Ztesh!C2 -> 1.1689143e+09 | CB2: =((CA2-CA3)/CA3) -> 0.011908833 | CC2: =SUM(CA2/C2) -> 0.17066484
A3: =SUM(B3+250) -> 2014 | B3: 1764 | C3: =Acetoa!C3 + Acrana!C3 + Aetintio!C3 + Ahokini!C3 + Amcha!C3 + Andsaudare!C3 + Anymna!C3 + Aplasia!C3 + Arbiya!C3 + 'Areoix Lie'!C3 + Ashain!C3 + Astye!C3 + Baluyde!C3 + Byllu!C3 + 'Candenat'!C3 + 'Canldives'!C3 + 'Chaenia'!C3 + 'Cloja'!C3 + 'Crila Republic'!C3 + 'Cruthi Anoso'!C3 + 'Curata'!C3 + Dahe!C3 + Danocia!C3 + Darewa!C3 + Desaki!C3 + Deschon!C3 + 'Disal Nila'!C3 + 'Dual Cenryia'!C3 + Ealdorii!C3 + Easuhura!C3 + Eldavpir!C3 + Eldjo!C3 + 'Elja and Munusia'!C3 + Emara!C3 + Enina!C3 + Eparia!C3 + Erkizil!C3 + Estijan!C3 + Etirha!C3 + Etretes!C3 + Exilium!C3 + 'Far Lands'!C3 + 'Feio Lie'!C3 + Fermori!C3 + Finae!C3 + Fincen!C3 + 'Fire Coast'!C3 + Gaeiya!C3 + Galca!C3 + Genaire!C3 + Grazail!C3 + Guise!C3 + Haiza!C3 + Heiso!C3 + Hiwush!C3 + Hkuqo!C3 + Hyelen!C3 + Iainoa!C3 + Iareva!C3 + Ihner!C3 + Ikzen!C3 + Ilicuhe!C3 + Inania!C3 + Inrea!C3 + Iquir!C3 + Isari!C3 + Isnti!C3 + Isuibul!C3 + Jathua!C3 + Jau!C3 + Jshain!C3 + Kaastini!C3 + Koruch!C3 + Kusierna!C3 + Laselteh!C3 + Lasri!C3 + Letan!C3 + Lieri!C3 + Lycroa!C3 + Lydroa!C3 + Maalle!C3 + Mendereide!C3 + 'Merela Sta'!C3 + 'Mesjan Hyaa'!C3 + Metndria!C3 + Migoku!C3 + Myla!C3 + 'New Kizura'!C3 + 'New Misos'!C3 + 'Nheyes Si'!C3 + Nia!C3 + 'Niretui and Anulan'!C3 + 'Niul Spijan'!C3 + 'North Ayre'!C3 + Ocaun!C3 + Ohtina!C3 + Onphello!C3 + Oscairia!C3 + Othya!C3 + Otiiric!C3 + Oyreain!C3 + Ozinia!C3 + Palina!C3 + Peka!C3 + Pelan!C3 + Pelines!C3 + Pelugrotoa!C3 + 'Pha Hii'!C3 + Phuris!C3 + Praesyu!C3 + Prstreula!C3 + 'Pruim Fijan'!C3 + 'Prystr Hii'!C3 + Quidic!C3 + 'Raledria'!C3 + 'Reerica'!C3 + 'Rethern'!C3 + 'Rijan bu'!C3 + 'Rinew'!C3 + 'Rkmepuia'!C3 + 'Rtesania'!C3 + 'Ruylku'!C3 + Saa!C3 + Sadain!C3 + Sanagara!C3 + Sattle!C3 + Selaja!C3 + Seytinemas!C3 + Shinam!C3 + Shomjind!C3 + Siana!C3 + Sivoso!C3 + Slyiaduun!C3 + Stinebar!C3 + Suenan!C3 + Sunsokua!C3 + Taing!C3 + Taniduna!C3 + Taoisia!C3 + Taval!C3 + Terressin!C3 + Tomscilus!C3 + Tonder!C3 + Trevilla!C3 + Trian!C3 + Tvecoca!C3 + Ucrua!C3 + Ukhdari!C3 + Umarcia!C3 + Umendel!C3 + 'United Delet'!C3 + 'United Mihili'!C3 + Urbiqu!C3 + Uularin!C3 + Vayvele!C3 + Veelmit!C3 + Verste!C3 + Verusa!C3 + Vesozata!C3 + Viussi!C3 + Volver!C3 + Walporein!C3 + 'Welenu Fana'!C3 + 'Western Migoku'!C3 + Wundry!C3 + Yaxuto!C3 + Yihnurda!C3 + Yoprioq!C3 + Yutnitu!C3 + Zenashan!C3 + Zhanshe!C3 + Ztesh!C3 -> 6.783743e+09 | D3: =((C3-C4)/C4) -> 0.0098200828 | K3: =SUM(L3+250) -> 2014 | L3: 1764 | M3: ='Areoix Lie'!C3 + Pelines!C3 + Terressin!C3 + Taniduna!C3 + Iquir!C3 + Deschon!C3 + Othya!C3 + Eldavpir!C3 + 'Candenat'!C3 + Jau!C3 + Viussi!C3 + Jathua!C3 + Jshain!C3 + Acetoa!C3 + Sattle!C3 + 'Reerica'!C3 + 'Feio Lie'!C3 + Umendel!C3 + 'Fire Coast'!C3 + Yoprioq!C3 + 'Rijan bu'!C3 + Saa!C3 + 'Rinew'!C3 + Enina!C3 + Trevilla!C3 -> 1.0574015e+09 | N3: =((M3-M4)/M4) -> 0.012193103 | O3: =SUM(M3/C3) -> 0.15587287 | V3: =SUM(W3+250) -> 2014 | W3: 1764 | X3: =Aetintio!C3 + Arbiya!C3 + 'Curata'!C3 + 'Disal Nila'!C3 + Etirha!C3 + Fincen!C3 + Gaeiya!C3 + Genaire!C3 + Grazail!C3 + Guise!C3 + Laselteh!C3 + Lasri!C3 + Metndria!C3 + 'New Misos'!C3 + Peka!C3 + Pelan!C3 + Phuris!C3 + 'Raledria'!C3 + Slyiaduun!C3 + Tomscilus!C3 -> 5.3151204e+08 | Y3: =((X3-X4)/X4) -> 0.011528272 | Z3: =SUM(X3/C3) -> 0.078350852 | AG3: =SUM(AH3+250) -> 2014 | AH3: 1764 | AI3: =Acrana!C3 + Danocia!C3 + Darewa!C3 + Ealdorii!C3 + Easuhura!C3 + Eldjo!C3 + Emara!C3 + Estijan!C3 + Fermori!C3 + Ikzen!C3 + Ilicuhe!C3 + Koruch!C3 + Lycroa!C3 + Lydroa!C3 + 'Merela Sta'!C3 + 'New Kizura'!C3 + 'Niul Spijan'!C3 + Palina!C3 + Praesyu!C3 + Siana!C3 + Tonder!C3 + Ukhdari!C3 + Urbiqu!C3 + Uularin!C3 + Verusa!C3 + Yaxuto!C3 + Zenashan!C3 + Hkuqo!C3 -> 9.9307946e+08 | AJ3: =((AI3-AI4)/AI4) -> 0.0065056736 | AK3: =SUM(AI3/C3) -> 0.14639108 | AR3: =SUM(AS3+250) -> 2014 | AS3: 1764 | AT3: =Amcha!C3 + Byllu!C3 + 'Chaenia'!C3 + 'Cruthi Anoso'!C3 + 'Dual Cenryia'!C3 + Exilium!C3 + Galca!C3 + Inania!C3 + Inrea!C3 + Isnti!C3 + Lieri!C3 + Ocaun!C3 + Otiiric!C3 + Ozinia!C3 + Pelugrotoa!C3 + 'Rtesania'!C3 + Sadain!C3 + Selaja!C3 + Seytinemas!C3 + Sivoso!C3 + Sunsokua!C3 + Taing!C3 + Taoisia!C3 + Trian!C3 + Vayvele!C3 -> 1.37387e+09 | AU3: =((AT3-AT4)/AT4) -> 0.0099515274 | AV3: =SUM(AT3/C3) -> 0.20252389 | BC3: =SUM(BD3+250) -> 2014 | BD3: 1764 | BE3: ='Canldives'!C3 + 'Cloja'!C3 + Dahe!C3 + Eparia!C3 + Etretes!C3 + Haiza!C3 + Ihner!C3 + Kaastini!C3 + Kusierna!C3 + Migoku!C3 + 'North Ayre'!C3 + Oscairia!C3 + Oyreain!C3 + 'Pha Hii'!C3 + 'Pruim Fijan'!C3 + 'Prystr Hii'!C3 + 'Ruylku'!C3 + Sanagara!C3 + Shinam!C3 + Stinebar!C3 + Suenan!C3 + Taval!C3 + Ucrua!C3 + Vesozata!C3 + 'Welenu Fana'!C3 + 'Western Migoku'!C3 -> 1.3792838e+09 | BF3: =((BE3-BE4)/BE4) -> 0.007000883 | BG3: =SUM(BE3/C3) -> 0.20332195 | BN3: =SUM(BO3+250) -> 2014 | BO3: 1764 | BP3: =Andsaudare!C3 + Aplasia!C3 + Astye!C3 + 'Crila Republic'!C3 + 'Elja and Munusia'!C3 + Hiwush!C3 + Iainoa!C3 + Isari!C3 + Isuibul!C3 + Maalle!C3 + Mendereide!C3 + Nia!C3 + 'Niretui and Anulan'!C3 + Ohtina!C3 + Prstreula!C3 + 'Rethern'!C3 + 'Rkmepuia'!C3 + Tvecoca!C3 + Umarcia!C3 + 'United Delet'!C3 + Veelmit!C3 + Walporein!C3 + Yutnitu!C3 -> 2.7303991e+08 | BQ3: =((BP3-BP4)/BP4) -> 0.011549713 | BR3: =SUM(BP3/C3) -> 0.040249152 | BY3: =SUM(BZ3+250) -> 2014 | BZ3: 1764 | CA3: =Ahokini!C3 + Anymna!C3 + Ashain!C3 + Baluyde!C3 + Desaki!C3 + Erkizil!C3 + 'Far Lands'!C3 + Finae!C3 + Hyelen!C3 + Iareva!C3 + Letan!C3 + 'Mesjan Hyaa'!C3 + Myla!C3 + 'Nheyes Si'!C3 + Onphello!C3 + Quidic!C3 + Shomjind!C3 + 'United Mihili'!C3 + Verste!C3 + Volver!C3 + Wundry!C3 + Yihnurda!C3 + Zhanshe!C3 + Ztesh!C3 -> 1.1551577e+09 | CB3: =((CA3-CA4)/CA4) -> 0.012526438 | CC3: =SUM(CA3/C3) -> 0.17028323
A4: =SUM(B4+250) -> 2013 | B4: 1763 | C4: =Acetoa!C4 + Acrana!C4 + Aetintio!C4 + Ahokini!C4 + Amcha!C4 + Andsaudare!C4 + Anymna!C4 + Aplasia!C4 + Arbiya!C4 + 'Areoix Lie'!C4 + Ashain!C4 + Astye!C4 + Baluyde!C4 + Byllu!C4 + 'Candenat'!C4 + 'Canldives'!C4 + 'Chaenia'!C4 + 'Cloja'!C4 + 'Crila Republic'!C4 + 'Cruthi Anoso'!C4 + 'Curata'!C4 + Dahe!C4 + Danocia!C4 + Darewa!C4 + Desaki!C4 + Deschon!C4 + 'Disal Nila'!C4 + 'Dual Cenryia'!C4 + Ealdorii!C4 + Easuhura!C4 + Eldavpir!C4 + Eldjo!C4 + 'Elja and Munusia'!C4 + Emara!C4 + Enina!C4 + Eparia!C4 + Erkizil!C4 + Estijan!C4 + Etirha!C4 + Etretes!C4 + Exilium!C4 + 'Far Lands'!C4 + 'Feio Lie'!C4 + Fermori!C4 + Finae!C4 + Fincen!C4 + 'Fire Coast'!C4 + Gaeiya!C4 + Galca!C4 + Genaire!C4 + Grazail!C4 + Guise!C4 + Haiza!C4 + Heiso!C4 + Hiwush!C4 + Hkuqo!C4 + Hyelen!C4 + Iainoa!C4 + Iareva!C4 + Ihner!C4 + Ikzen!C4 + Ilicuhe!C4 + Inania!C4 + Inrea!C4 + Iquir!C4 + Isari!C4 + Isnti!C4 + Isuibul!C4 + Jathua!C4 + Jau!C4 + Jshain!C4 + Kaastini!C4 + Koruch!C4 + Kusierna!C4 + Laselteh!C4 + Lasri!C4 + Letan!C4 + Lieri!C4 + Lycroa!C4 + Lydroa!C4 + Maalle!C4 + Mendereide!C4 + 'Merela Sta'!C4 + 'Mesjan Hyaa'!C4 + Metndria!C4 + Migoku!C4 + Myla!C4 + 'New Kizura'!C4 + 'New Misos'!C4 + 'Nheyes Si'!C4 + Nia!C4 + 'Niretui and Anulan'!C4 + 'Niul Spijan'!C4 + 'North Ayre'!C4 + Ocaun!C4 + Ohtina!C4 + Onphello!C4 + Oscairia!C4 + Othya!C4 + Otiiric!C4 + Oyreain!C4 + Ozinia!C4 + Palina!C4 + Peka!C4 + Pelan!C4 + Pelines!C4 + Pelugrotoa!C4 + 'Pha Hii'!C4 + Phuris!C4 + Praesyu!C4 + Prstreula!C4 + 'Pruim Fijan'!C4 + 'Prystr Hii'!C4 + Quidic!C4 + 'Raledria'!C4 + 'Reerica'!C4 + 'Rethern'!C4 + 'Rijan bu'!C4 + 'Rinew'!C4 + 'Rkmepuia'!C4 + 'Rtesania'!C4 + 'Ruylku'!C4 + Saa!C4 + Sadain!C4 + Sanagara!C4 + Sattle!C4 + Selaja!C4 + Seytinemas!C4 + Shinam!C4 + Shomjind!C4 + Siana!C4 + Sivoso!C4 + Slyiaduun!C4 + Stinebar!C4 + Suenan!C4 + Sunsokua!C4 + Taing!C4 + Taniduna!C4 + Taoisia!C4 + Taval!C4 + Terressin!C4 + Tomscilus!C4 + Tonder!C4 + Trevilla!C4 + Trian!C4 + Tvecoca!C4 + Ucrua!C4 + Ukhdari!C4 + Umarcia!C4 + Umendel!C4 + 'United Delet'!C4 + 'United Mihili'!C4 + Urbiqu!C4 + Uularin!C4 + Vayvele!C4 + Veelmit!C4 + Verste!C4 + Verusa!C4 + Vesozata!C4 + Viussi!C4 + Volver!C4 + Walporein!C4 + 'Welenu Fana'!C4 + 'Western Migoku'!C4 + Wundry!C4 + Yaxuto!C4 + Yihnurda!C4 + Yoprioq!C4 + Yutnitu!C4 + Zenashan!C4 + Zhanshe!C4 + Ztesh!C4 -> 6.7177739e+09 | D4: =((C4-C5)/C5) -> 0.0098609584 | K4: =SUM(L4+250) -> 2013 | L4: 1763 | M4: ='Areoix Lie'!C4 + Pelines!C4 + Terressin!C4 + Taniduna!C4 + Iquir!C4 + Deschon!C4 + Othya!C4 + Eldavpir!C4 + 'Candenat'!C4 + Jau!C4 + Viussi!C4 + Jathua!C4 + Jshain!C4 + Acetoa!C4 + Sattle!C4 + 'Reerica'!C4 + 'Feio Lie'!C4 + Umendel!C4 + 'Fire Coast'!C4 + Yoprioq!C4 + 'Rijan bu'!C4 + Saa!C4 + 'Rinew'!C4 + Enina!C4 + Trevilla!C4 -> 1.0446638e+09 | N4: =((M4-M5)/M5) -> 0.011587611 | O4: =SUM(M4/C4) -> 0.15550744 | V4: =SUM(W4+250) -> 2013 | W4: 1763 | X4: =Aetintio!C4 + Arbiya!C4 + 'Curata'!C4 + 'Disal Nila'!C4 + Etirha!C4 + Fincen!C4 + Gaeiya!C4 + Genaire!C4 + Grazail!C4 + Guise!C4 + Laselteh!C4 + Lasri!C4 + Metndria!C4 + 'New Misos'!C4 + Peka!C4 + Pelan!C4 + Phuris!C4 + 'Raledria'!C4 + Slyiaduun!C4 + Tomscilus!C4 -> 5.2545446e+08 | Y4: =((X4-X5)/X5) -> 0.012712502 | Z4: =SUM(X4/C4) -> 0.078218539 | AG4: =SUM(AH4+250) -> 2013 | AH4: 1763 | AI4: =Acrana!C4 + Danocia!C4 + Darewa!C4 + Ealdorii!C4 + Easuhura!C4 + Eldjo!C4 + Emara!C4 + Estijan!C4 + Fermori!C4 + Ikzen!C4 + Ilicuhe!C4 + Koruch!C4 + Lycroa!C4 + Lydroa!C4 + 'Merela Sta'!C4 + 'New Kizura'!C4 + 'Niul Spijan'!C4 + Palina!C4 + Praesyu!C4 + Siana!C4 + Tonder!C4 + Ukhdari!C4 + Urbiqu!C4 + Uularin!C4 + Verusa!C4 + Yaxuto!C4 + Zenashan!C4 + Hkuqo!C4 -> 9.8666057e+08 | AJ4: =((AI4-AI5)/AI5) -> 0.006512277 | AK4: =SUM(AI4/C4) -> 0.14687314 | AR4: =SUM(AS4+250) -> 2013 | AS4: 1763 | AT4: =Amcha!C4 + Byllu!C4 + 'Chaenia'!C4 + 'Cruthi Anoso'!C4 + 'Dual Cenryia'!C4 + Exilium!C4 + Galca!C4 + Inania!C4 + Inrea!C4 + Isnti!C4 + Lieri!C4 + Ocaun!C4 + Otiiric!C4 + Ozinia!C4 + Pelugrotoa!C4 + 'Rtesania'!C4 + Sadain!C4 + Selaja!C4 + Seytinemas!C4 + Sivoso!C4 + Sunsokua!C4 + Taing!C4 + Taoisia!C4 + Trian!C4 + Vayvele!C4 -> 1.3603326e+09 | AU4: =((AT4-AT5)/AT5) -> 0.0099131221 | AV4: =SUM(AT4/C4) -> 0.20249753 | BC4: =SUM(BD4+250) -> 2013 | BD4: 1763 | BE4: ='Canldives'!C4 + 'Cloja'!C4 + Dahe!C4 + Eparia!C4 + Etretes!C4 + Haiza!C4 + Ihner!C4 + Kaastini!C4 + Kusierna!C4 + Migoku!C4 + 'North Ayre'!C4 + Oscairia!C4 + Oyreain!C4 + 'Pha Hii'!C4 + 'Pruim Fijan'!C4 + 'Prystr Hii'!C4 + 'Ruylku'!C4 + Sanagara!C4 + Shinam!C4 + Stinebar!C4 + Suenan!C4 + Taval!C4 + Ucrua!C4 + Vesozata!C4 + 'Welenu Fana'!C4 + 'Western Migoku'!C4 -> 1.3696948e+09 | BF4: =((BE4-BE5)/BE5) -> 0.0067701805 | BG4: =SUM(BE4/C4) -> 0.20389117 | BN4: =SUM(BO4+250) -> 2013 | BO4: 1763 | BP4: =Andsaudare!C4 + Aplasia!C4 + Astye!C4 + 'Crila Republic'!C4 + 'Elja and Munusia'!C4 + Hiwush!C4 + Iainoa!C4 + Isari!C4 + Isuibul!C4 + Maalle!C4 + Mendereide!C4 + Nia!C4 + 'Niretui and Anulan'!C4 + Ohtina!C4 + Prstreula!C4 + 'Rethern'!C4 + 'Rkmepuia'!C4 + Tvecoca!C4 + Umarcia!C4 + 'United Delet'!C4 + Veelmit!C4 + Walporein!C4 + Yutnitu!C4 -> 2.6992238e+08 | BQ4: =((BP4-BP5)/BP5) -> 0.01183094 | BR4: =SUM(BP4/C4) -> 0.040180331 | BY4: =SUM(BZ4+250) -> 2013 | BZ4: 1763 | CA4: =Ahokini!C4 + Anymna!C4 + Ashain!C4 + Baluyde!C4 + Desaki!C4 + Erkizil!C4 + 'Far Lands'!C4 + Finae!C4 + Hyelen!C4 + Iareva!C4 + Letan!C4 + 'Mesjan Hyaa'!C4 + Myla!C4 + 'Nheyes Si'!C4 + Onphello!C4 + Quidic!C4 + Shomjind!C4 + 'United Mihili'!C4 + Verste!C4 + Volver!C4 + Wundry!C4 + Yihnurda!C4 + Zhanshe!C4 + Ztesh!C4 -> 1.1408667e+09 | CB4: =((CA4-CA5)/CA5) -> 0.013054492 | CC4: =SUM(CA4/C4) -> 0.16982809
A5: =SUM(B5+250) -> 2012 | B5: 1762 | C5: =Acetoa!C5 + Acrana!C5 + Aetintio!C5 + Ahokini!C5 + Amcha!C5 + Andsaudare!C5 + Anymna!C5 + Aplasia!C5 + Arbiya!C5 + 'Areoix Lie'!C5 + Ashain!C5 + Astye!C5 + Baluyde!C5 + Byllu!C5 + 'Candenat'!C5 + 'Canldives'!C5 + 'Chaenia'!C5 + 'Cloja'!C5 + 'Crila Republic'!C5 + 'Cruthi Anoso'!C5 + 'Curata'!C5 + Dahe!C5 + Danocia!C5 + Darewa!C5 + Desaki!C5 + Deschon!C5 + 'Disal Nila'!C5 + 'Dual Cenryia'!C5 + Ealdorii!C5 + Easuhura!C5 + Eldavpir!C5 + Eldjo!C5 + 'Elja and Munusia'!C5 + Emara!C5 + Enina!C5 + Eparia!C5 + Erkizil!C5 + Estijan!C5 + Etirha!C5 + Etretes!C5 + Exilium!C5 + 'Far Lands'!C5 + 'Feio Lie'!C5 + Fermori!C5 + Finae!C5 + Fincen!C5 + 'Fire Coast'!C5 + Gaeiya!C5 + Galca!C5 + Genaire!C5 + Grazail!C5 + Guise!C5 + Haiza!C5 + Heiso!C5 + Hiwush!C5 + Hkuqo!C5 + Hyelen!C5 + Iainoa!C5 + Iareva!C5 + Ihner!C5 + Ikzen!C5 + Ilicuhe!C5 + Inania!C5 + Inrea!C5 + Iquir!C5 + Isari!C5 + Isnti!C5 + Isuibul!C5 + Jathua!C5 + Jau!C5 + Jshain!C5 + Kaastini!C5 + Koruch!C5 + Kusierna!C5 + Laselteh!C5 + Lasri!C5 + Letan!C5 + Lieri!C5 + Lycroa!C5 + Lydroa!C5 + Maalle!C5 + Mendereide!C5 + 'Merela Sta'!C5 + 'Mesjan Hyaa'!C5 + Metndria!C5 + Migoku!C5 + Myla!C5 + 'New Kizura'!C5 + 'New Misos'!C5 + 'Nheyes Si'!C5 + Nia!C5 + 'Niretui and Anulan'!C5 + 'Niul Spijan'!C5 + 'North Ayre'!C5 + Ocaun!C5 + Ohtina!C5 + Onphello!C5 + Oscairia!C5 + Othya!C5 + Otiiric!C5 + Oyreain!C5 + Ozinia!C5 + Palina!C5 + Peka!C5 + Pelan!C5 + Pelines!C5 + Pelugrotoa!C5 + 'Pha Hii'!C5 + Phuris!C5 + Praesyu!C5 + Prstreula!C5 + 'Pruim Fijan'!C5 + 'Prystr Hii'!C5 + Quidic!C5 + 'Raledria'!C5 + 'Reerica'!C5 + 'Rethern'!C5 + 'Rijan bu'!C5 + 'Rinew'!C5 + 'Rkmepuia'!C5 + 'Rtesania'!C5 + 'Ruylku'!C5 + Saa!C5 + Sadain!C5 + Sanagara!C5 + Sattle!C5 + Selaja!C5 + Seytinemas!C5 + Shinam!C5 + Shomjind!C5 + Siana!C5 + Sivoso!C5 + Slyiaduun!C5 + Stinebar!C5 + Suenan!C5 + Sunsokua!C5 + Taing!C5 + Taniduna!C5 + Taoisia!C5 + Taval!C5 + Terressin!C5 + Tomscilus!C5 + Tonder!C5 + Trevilla!C5 + Trian!C5 + Tvecoca!C5 + Ucrua!C5 + Ukhdari!C5 + Umarcia!C5 + Umendel!C5 + 'United Delet'!C5 + 'United Mihili'!C5 + Urbiqu!C5 + Uularin!C5 + Vayvele!C5 + Veelmit!C5 + Verste!C5 + Verusa!C5 + Vesozata!C5 + Viussi!C5 + Volver!C5 + Walporein!C5 + 'Welenu Fana'!C5 + 'Western Migoku'!C5 + Wundry!C5 + Yaxuto!C5 + Yihnurda!C5 + Yoprioq!C5 + Yutnitu!C5 + Zenashan!C5 + Zhanshe!C5 + Ztesh!C5 -> 6.6521771e+09 | D5: =((C5-C6)/C6) -> 0.01007584 | K5: =SUM(L5+250) -> 2012 | L5: 1762 | M5: ='Areoix Lie'!C5 + Pelines!C5 + Terressin!C5 + Taniduna!C5 + Iquir!C5 + Deschon!C5 + Othya!C5 + Eldavpir!C5 + 'Candenat'!C5 + Jau!C5 + Viussi!C5 + Jathua!C5 + Jshain!C5 + Acetoa!C5 + Sattle!C5 + 'Reerica'!C5 + 'Feio Lie'!C5 + Umendel!C5 + 'Fire Coast'!C5 + Yoprioq!C5 + 'Rijan bu'!C5 + Saa!C5 + 'Rinew'!C5 + Enina!C5 + Trevilla!C5 -> 1.0326973e+09 | N5: =((M5-M6)/M6) -> 0.011045252 | O5: =SUM(M5/C5) -> 0.15524201 | V5: =SUM(W5+250) -> 2012 | W5: 1762 | X5: =Aetintio!C5 + Arbiya!C5 + 'Curata'!C5 + 'Disal Nila'!C5 + Etirha!C5 + Fincen!C5 + Gaeiya!C5 + Genaire!C5 + Grazail!C5 + Guise!C5 + Laselteh!C5 + Lasri!C5 + Metndria!C5 + 'New Misos'!C5 + Peka!C5 + Pelan!C5 + Phuris!C5 + 'Raledria'!C5 + Slyiaduun!C5 + Tomscilus!C5 -> 5.1885847e+08 | Y5: =((X5-X6)/X6) -> 0.013080513 | Z5: =SUM(X5/C5) -> 0.077998295 | AG5: =SUM(AH5+250) -> 2012 | AH5: 1762 | AI5: =Acrana!C5 + Danocia!C5 + Darewa!C5 + Ealdorii!C5 + Easuhura!C5 + Eldjo!C5 + Emara!C5 + Estijan!C5 + Fermori!C5 + Ikzen!C5 + Ilicuhe!C5 + Koruch!C5 + Lycroa!C5 + Lydroa!C5 + 'Merela Sta'!C5 + 'New Kizura'!C5 + 'Niul Spijan'!C5 + Palina!C5 + Praesyu!C5 + Siana!C5 + Tonder!C5 + Ukhdari!C5 + Urbiqu!C5 + Uularin!C5 + Verusa!C5 + Yaxuto!C5 + Zenashan!C5 + Hkuqo!C5 -> 9.8027674e+08 | AJ5: =((AI5-AI6)/AI6) -> 0.006759365 | AK5: =SUM(AI5/C5) -> 0.14736179 | AR5: =SUM(AS5+250) -> 2012 | AS5: 1762 | AT5: =Amcha!C5 + Byllu!C5 + 'Chaenia'!C5 + 'Cruthi Anoso'!C5 + 'Dual Cenryia'!C5 + Exilium!C5 + Galca!C5 + Inania!C5 + Inrea!C5 + Isnti!C5 + Lieri!C5 + Ocaun!C5 + Otiiric!C5 + Ozinia!C5 + Pelugrotoa!C5 + 'Rtesania'!C5 + Sadain!C5 + Selaja!C5 + Seytinemas!C5 + Sivoso!C5 + Sunsokua!C5 + Taing!C5 + Taoisia!C5 + Trian!C5 + Vayvele!C5 -> 1.3469798e+09 | AU5: =((AT5-AT6)/AT6) -> 0.010133468 | AV5: =SUM(AT5/C5) -> 0.20248707 | BC5: =SUM(BD5+250) -> 2012 | BD5: 1762 | BE5: ='Canldives'!C5 + 'Cloja'!C5 + Dahe!C5 + Eparia!C5 + Etretes!C5 + Haiza!C5 + Ihner!C5 + Kaastini!C5 + Kusierna!C5 + Migoku!C5 + 'North Ayre'!C5 + Oscairia!C5 + Oyreain!C5 + 'Pha Hii'!C5 + 'Pruim Fijan'!C5 + 'Prystr Hii'!C5 + 'Ruylku'!C5 + Sanagara!C5 + Shinam!C5 + Stinebar!C5 + Suenan!C5 + Taval!C5 + Ucrua!C5 + Vesozata!C5 + 'Welenu Fana'!C5 + 'Western Migoku'!C5 -> 1.360484e+09 | BF5: =((BE5-BE6)/BE6) -> 0.0071313151 | BG5: =SUM(BE5/C5) -> 0.20451711 | BN5: =SUM(BO5+250) -> 2012 | BO5: 1762 | BP5: =Andsaudare!C5 + Aplasia!C5 + Astye!C5 + 'Crila Republic'!C5 + 'Elja and Munusia'!C5 + Hiwush!C5 + Iainoa!C5 + Isari!C5 + Isuibul!C5 + Maalle!C5 + Mendereide!C5 + Nia!C5 + 'Niretui and Anulan'!C5 + Ohtina!C5 + Prstreula!C5 + 'Rethern'!C5 + 'Rkmepuia'!C5 + Tvecoca!C5 + Umarcia!C5 + 'United Delet'!C5 + Veelmit!C5 + Walporein!C5 + Yutnitu!C5 -> 2.6676628e+08 | BQ5: =((BP5-BP6)/BP6) -> 0.012526868 | BR5: =SUM(BP5/C5) -> 0.040102102 | BY5: =SUM(BZ5+250) -> 2012 | BZ5: 1762 | CA5: =Ahokini!C5 + Anymna!C5 + Ashain!C5 + Baluyde!C5 + Desaki!C5 + Erkizil!C5 + 'Far Lands'!C5 + Finae!C5 + Hyelen!C5 + Iareva!C5 + Letan!C5 + 'Mesjan Hyaa'!C5 + Myla!C5 + 'Nheyes Si'!C5 + Onphello!C5 + Quidic!C5 + Shomjind!C5 + 'United Mihili'!C5 + Verste!C5 + Volver!C5 + Wundry!C5 + Yihnurda!C5 + Zhanshe!C5 + Ztesh!C5 -> 1.1261652e+09 | CB5: =((CA5-CA6)/CA6) -> 0.013596237 | CC5: =SUM(CA5/C5) -> 0.16929272
A6: =SUM(B6+250) -> 2011 | B6: 1761 | C6: =Acetoa!C6 + Acrana!C6 + Aetintio!C6 + Ahokini!C6 + Amcha!C6 + Andsaudare!C6 + Anymna!C6 + Aplasia!C6 + Arbiya!C6 + 'Areoix Lie'!C6 + Ashain!C6 + Astye!C6 + Baluyde!C6 + Byllu!C6 + 'Candenat'!C6 + 'Canldives'!C6 + 'Chaenia'!C6 + 'Cloja'!C6 + 'Crila Republic'!C6 + 'Cruthi Anoso'!C6 + 'Curata'!C6 + Dahe!C6 + Danocia!C6 + Darewa!C6 + Desaki!C6 + Deschon!C6 + 'Disal Nila'!C6 + 'Dual Cenryia'!C6 + Ealdorii!C6 + Easuhura!C6 + Eldavpir!C6 + Eldjo!C6 + 'Elja and Munusia'!C6 + Emara!C6 + Enina!C6 + Eparia!C6 + Erkizil!C6 + Estijan!C6 + Etirha!C6 + Etretes!C6 + Exilium!C6 + 'Far Lands'!C6 + 'Feio Lie'!C6 + Fermori!C6 + Finae!C6 + Fincen!C6 + 'Fire Coast'!C6 + Gaeiya!C6 + Galca!C6 + Genaire!C6 + Grazail!C6 + Guise!C6 + Haiza!C6 + Heiso!C6 + Hiwush!C6 + Hkuqo!C6 + Hyelen!C6 + Iainoa!C6 + Iareva!C6 + Ihner!C6 + Ikzen!C6 + Ilicuhe!C6 + Inania!C6 + Inrea!C6 + Iquir!C6 + Isari!C6 + Isnti!C6 + Isuibul!C6 + Jathua!C6 + Jau!C6 + Jshain!C6 + Kaastini!C6 + Koruch!C6 + Kusierna!C6 + Laselteh!C6 + Lasri!C6 + Letan!C6 + Lieri!C6 + Lycroa!C6 + Lydroa!C6 + Maalle!C6 + Mendereide!C6 + 'Merela Sta'!C6 + 'Mesjan Hyaa'!C6 + Metndria!C6 + Migoku!C6 + Myla!C6 + 'New Kizura'!C6 + 'New Misos'!C6 + 'Nheyes Si'!C6 + Nia!C6 + 'Niretui and Anulan'!C6 + 'Niul Spijan'!C6 + 'North Ayre'!C6 + Ocaun!C6 + Ohtina!C6 + Onphello!C6 + Oscairia!C6 + Othya!C6 + Otiiric!C6 + Oyreain!C6 + Ozinia!C6 + Palina!C6 + Peka!C6 + Pelan!C6 + Pelines!C6 + Pelugrotoa!C6 + 'Pha Hii'!C6 + Phuris!C6 + Praesyu!C6 + Prstreula!C6 + 'Pruim Fijan'!C6 + 'Prystr Hii'!C6 + Quidic!C6 + 'Raledria'!C6 + 'Reerica'!C6 + 'Rethern'!C6 + 'Rijan bu'!C6 + 'Rinew'!C6 + 'Rkmepuia'!C6 + 'Rtesania'!C6 + 'Ruylku'!C6 + Saa!C6 + Sadain!C6 + Sanagara!C6 + Sattle!C6 + Selaja!C6 + Seytinemas!C6 + Shinam!C6 + Shomjind!C6 + Siana!C6 + Sivoso!C6 + Slyiaduun!C6 + Stinebar!C6 + Suenan!C6 + Sunsokua!C6 + Taing!C6 + Taniduna!C6 + Taoisia!C6 + Taval!C6 + Terressin!C6 + Tomscilus!C6 + Tonder!C6 + Trevilla!C6 + Trian!C6 + Tvecoca!C6 + Ucrua!C6 + Ukhdari!C6 + Umarcia!C6 + Umendel!C6 + 'United Delet'!C6 + 'United Mihili'!C6 + Urbiqu!C6 + Uularin!C6 + Vayvele!C6 + Veelmit!C6 + Verste!C6 + Verusa!C6 + Vesozata!C6 + Viussi!C6 + Volver!C6 + Walporein!C6 + 'Welenu Fana'!C6 + 'Western Migoku'!C6 + Wundry!C6 + Yaxuto!C6 + Yihnurda!C6 + Yoprioq!C6 + Yutnitu!C6 + Zenashan!C6 + Zhanshe!C6 + Ztesh!C6 -> 6.5858194e+09 | D6: =((C6-C7)/C7) -> 0.010086267 | K6: =SUM(L6+250) -> 2011 | L6: 1761 | M6: ='Areoix Lie'!C6 + Pelines!C6 + Terressin!C6 + Taniduna!C6 + Iquir!C6 + Deschon!C6 + Othya!C6 + Eldavpir!C6 + 'Candenat'!C6 + Jau!C6 + Viussi!C6 + Jathua!C6 + Jshain!C6 + Acetoa!C6 + Sattle!C6 + 'Reerica'!C6 + 'Feio Lie'!C6 + Umendel!C6 + 'Fire Coast'!C6 + Yoprioq!C6 + 'Rijan bu'!C6 + Saa!C6 + 'Rinew'!C6 + Enina!C6 + Trevilla!C6 -> 1.0214155e+09 | N6: =((M6-M7)/M7) -> 0.01188251 | O6: =SUM(M6/C6) -> 0.15509316 | V6: =SUM(W6+250) -> 2011 | W6: 1761 | X6: =Aetintio!C6 + Arbiya!C6 + 'Curata'!C6 + 'Disal Nila'!C6 + Etirha!C6 + Fincen!C6 + Gaeiya!C6 + Genaire!C6 + Grazail!C6 + Guise!C6 + Laselteh!C6 + Lasri!C6 + Metndria!C6 + 'New Misos'!C6 + Peka!C6 + Pelan!C6 + Phuris!C6 + 'Raledria'!C6 + Slyiaduun!C6 + Tomscilus!C6 -> 5.1215917e+08 | Y6: =((X6-X7)/X7) -> 0.011055656 | Z6: =SUM(X6/C6) -> 0.077766962 | AG6: =SUM(AH6+250) -> 2011 | AH6: 1761 | AI6: =Acrana!C6 + Danocia!C6 + Darewa!C6 + Ealdorii!C6 + Easuhura!C6 + Eldjo!C6 + Emara!C6 + Estijan!C6 + Fermori!C6 + Ikzen!C6 + Ilicuhe!C6 + Koruch!C6 + Lycroa!C6 + Lydroa!C6 + 'Merela Sta'!C6 + 'New Kizura'!C6 + 'Niul Spijan'!C6 + Palina!C6 + Praesyu!C6 + Siana!C6 + Tonder!C6 + Ukhdari!C6 + Urbiqu!C6 + Uularin!C6 + Verusa!C6 + Yaxuto!C6 + Zenashan!C6 + Hkuqo!C6 -> 9.7369518e+08 | AJ6: =((AI6-AI7)/AI7) -> 0.0067869546 | AK6: =SUM(AI6/C6) -> 0.14784723 | AR6: =SUM(AS6+250) -> 2011 | AS6: 1761 | AT6: =Amcha!C6 + Byllu!C6 + 'Chaenia'!C6 + 'Cruthi Anoso'!C6 + 'Dual Cenryia'!C6 + Exilium!C6 + Galca!C6 + Inania!C6 + Inrea!C6 + Isnti!C6 + Lieri!C6 + Ocaun!C6 + Otiiric!C6 + Ozinia!C6 + Pelugrotoa!C6 + 'Rtesania'!C6 + Sadain!C6 + Selaja!C6 + Seytinemas!C6 + Sivoso!C6 + Sunsokua!C6 + Taing!C6 + Taoisia!C6 + Trian!C6 + Vayvele!C6 -> 1.3334672e+09 | AU6: =((AT6-AT7)/AT7) -> 0.0098042195 | AV6: =SUM(AT6/C6) -> 0.20247552 | BC6: =SUM(BD6+250) -> 2011 | BD6: 1761 | BE6: ='Canldives'!C6 + 'Cloja'!C6 + Dahe!C6 + Eparia!C6 + Etretes!C6 + Haiza!C6 + Ihner!C6 + Kaastini!C6 + Kusierna!C6 + Migoku!C6 + 'North Ayre'!C6 + Oscairia!C6 + Oyreain!C6 + 'Pha Hii'!C6 + 'Pruim Fijan'!C6 + 'Prystr Hii'!C6 + 'Ruylku'!C6 + Sanagara!C6 + Shinam!C6 + Stinebar!C6 + Suenan!C6 + Taval!C6 + Ucrua!C6 + Vesozata!C6 + 'Welenu Fana'!C6 + 'Western Migoku'!C6 -> 1.3508507e+09 | BF6: =((BE6-BE7)/BE7) -> 0.0070703532 | BG6: =SUM(BE6/C6) -> 0.20511505 | BN6: =SUM(BO6+250) -> 2011 | BO6: 1761 | BP6: =Andsaudare!C6 + Aplasia!C6 + Astye!C6 + 'Crila Republic'!C6 + 'Elja and Munusia'!C6 + Hiwush!C6 + Iainoa!C6 + Isari!C6 + Isuibul!C6 + Maalle!C6 + Mendereide!C6 + Nia!C6 + 'Niretui and Anulan'!C6 + Ohtina!C6 + Prstreula!C6 + 'Rethern'!C6 + 'Rkmepuia'!C6 + Tvecoca!C6 + Umarcia!C6 + 'United Delet'!C6 + Veelmit!C6 + Walporein!C6 + Yutnitu!C6 -> 2.6346588e+08 | BQ6: =((BP6-BP7)/BP7) -> 0.013633237 | BR6: =SUM(BP6/C6) -> 0.040005027 | BY6: =SUM(BZ6+250) -> 2011 | BZ6: 1761 | CA6: =Ahokini!C6 + Anymna!C6 + Ashain!C6 + Baluyde!C6 + Desaki!C6 + Erkizil!C6 + 'Far Lands'!C6 + Finae!C6 + Hyelen!C6 + Iareva!C6 + Letan!C6 + 'Mesjan Hyaa'!C6 + Myla!C6 + 'Nheyes Si'!C6 + Onphello!C6 + Quidic!C6 + Shomjind!C6 + 'United Mihili'!C6 + Verste!C6 + Volver!C6 + Wundry!C6 + Yihnurda!C6 + Zhanshe!C6 + Ztesh!C6 -> 1.111059e+09 | CB6: =((CA6-CA7)/CA7) -> 0.014004264 | CC6: =SUM(CA6/C6) -> 0.16870474
A7: =SUM(B7+250) -> 2010 | B7: 1760 | C7: =Acetoa!C7 + Acrana!C7 + Aetintio!C7 + Ahokini!C7 + Amcha!C7 + Andsaudare!C7 + Anymna!C7 + Aplasia!C7 + Arbiya!C7 + 'Areoix Lie'!C7 + Ashain!C7 + Astye!C7 + Baluyde!C7 + Byllu!C7 + 'Candenat'!C7 + 'Canldives'!C7 + 'Chaenia'!C7 + 'Cloja'!C7 + 'Crila Republic'!C7 + 'Cruthi Anoso'!C7 + 'Curata'!C7 + Dahe!C7 + Danocia!C7 + Darewa!C7 + Desaki!C7 + Deschon!C7 + 'Disal Nila'!C7 + 'Dual Cenryia'!C7 + Ealdorii!C7 + Easuhura!C7 + Eldavpir!C7 + Eldjo!C7 + 'Elja and Munusia'!C7 + Emara!C7 + Enina!C7 + Eparia!C7 + Erkizil!C7 + Estijan!C7 + Etirha!C7 + Etretes!C7 + Exilium!C7 + 'Far Lands'!C7 + 'Feio Lie'!C7 + Fermori!C7 + Finae!C7 + Fincen!C7 + 'Fire Coast'!C7 + Gaeiya!C7 + Galca!C7 + Genaire!C7 + Grazail!C7 + Guise!C7 + Haiza!C7 + Heiso!C7 + Hiwush!C7 + Hkuqo!C7 + Hyelen!C7 + Iainoa!C7 + Iareva!C7 + Ihner!C7 + Ikzen!C7 + Ilicuhe!C7 + Inania!C7 + Inrea!C7 + Iquir!C7 + Isari!C7 + Isnti!C7 + Isuibul!C7 + Jathua!C7 + Jau!C7 + Jshain!C7 + Kaastini!C7 + Koruch!C7 + Kusierna!C7 + Laselteh!C7 + Lasri!C7 + Letan!C7 + Lieri!C7 + Lycroa!C7 + Lydroa!C7 + Maalle!C7 + Mendereide!C7 + 'Merela Sta'!C7 + 'Mesjan Hyaa'!C7 + Metndria!C7 + Migoku!C7 + Myla!C7 + 'New Kizura'!C7 + 'New Misos'!C7 + 'Nheyes Si'!C7 + Nia!C7 + 'Niretui and Anulan'!C7 + 'Niul Spijan'!C7 + 'North Ayre'!C7 + Ocaun!C7 + Ohtina!C7 + Onphello!C7 + Oscairia!C7 + Othya!C7 + Otiiric!C7 + Oyreain!C7 + Ozinia!C7 + Palina!C7 + Peka!C7 + Pelan!C7 + Pelines!C7 + Pelugrotoa!C7 + 'Pha Hii'!C7 + Phuris!C7 + Praesyu!C7 + Prstreula!C7 + 'Pruim Fijan'!C7 + 'Prystr Hii'!C7 + Quidic!C7 + 'Raledria'!C7 + 'Reerica'!C7 + 'Rethern'!C7 + 'Rijan bu'!C7 + 'Rinew'!C7 + 'Rkmepuia'!C7 + 'Rtesania'!C7 + 'Ruylku'!C7 + Saa!C7 + Sadain!C7 + Sanagara!C7 + Sattle!C7 + Selaja!C7 + Seytinemas!C7 + Shinam!C7 + Shomjind!C7 + Siana!C7 + Sivoso!C7 + Slyiaduun!C7 + Stinebar!C7 + Suenan!C7 + Sunsokua!C7 + Taing!C7 + Taniduna!C7 + Taoisia!C7 + Taval!C7 + Terressin!C7 + Tomscilus!C7 + Tonder!C7 + Trevilla!C7 + Trian!C7 + Tvecoca!C7 + Ucrua!C7 + Ukhdari!C7 + Umarcia!C7 + Umendel!C7 + 'United Delet'!C7 + 'United Mihili'!C7 + Urbiqu!C7 + Uularin!C7 + Vayvele!C7 + Veelmit!C7 + Verste!C7 + Verusa!C7 + Vesozata!C7 + Viussi!C7 + Volver!C7 + Walporein!C7 + 'Welenu Fana'!C7 + 'Western Migoku'!C7 + Wundry!C7 + Yaxuto!C7 + Yihnurda!C7 + Yoprioq!C7 + Yutnitu!C7 + Zenashan!C7 + Zhanshe!C7 + Ztesh!C7 -> 6.5200564e+09 | D7: =((C7-C8)/C8) -> 0.01041509 | K7: =SUM(L7+250) -> 2010 | L7: 1760 | M7: ='Areoix Lie'!C7 + Pelines!C7 + Terressin!C7 + Taniduna!C7 + Iquir!C7 + Deschon!C7 + Othya!C7 + Eldavpir!C7 + 'Candenat'!C7 + Jau!C7 + Viussi!C7 + Jathua!C7 + Jshain!C7 + Acetoa!C7 + Sattle!C7 + 'Reerica'!C7 + 'Feio Lie'!C7 + Umendel!C7 + 'Fire Coast'!C7 + Yoprioq!C7 + 'Rijan bu'!C7 + Saa!C7 + 'Rinew'!C7 + Enina!C7 + Trevilla!C7 -> 1.0094211e+09 | N7: =((M7-M8)/M8) -> 0.012584589 | O7: =SUM(M7/C7) -> 0.15481785 | V7: =SUM(W7+250) -> 2010 | W7: 1760 | X7: =Aetintio!C7 + Arbiya!C7 + 'Curata'!C7 + 'Disal Nila'!C7 + Etirha!C7 + Fincen!C7 + Gaeiya!C7 + Genaire!C7 + Grazail!C7 + Guise!C7 + Laselteh!C7 + Lasri!C7 + Metndria!C7 + 'New Misos'!C7 + Peka!C7 + Pelan!C7 + Phuris!C7 + 'Raledria'!C7 + Slyiaduun!C7 + Tomscilus!C7 -> 5.0655883e+08 | Y7: =((X7-X8)/X8) -> 0.012333086 | Z7: =SUM(X7/C7) -> 0.0776924 | AG7: =SUM(AH7+250) -> 2010 | AH7: 1760 | AI7: =Acrana!C7 + Danocia!C7 + Darewa!C7 + Ealdorii!C7 + Easuhura!C7 + Eldjo!C7 + Emara!C7 + Estijan!C7 + Fermori!C7 + Ikzen!C7 + Ilicuhe!C7 + Koruch!C7 + Lycroa!C7 + Lydroa!C7 + 'Merela Sta'!C7 + 'New Kizura'!C7 + 'Niul Spijan'!C7 + Palina!C7 + Praesyu!C7 + Siana!C7 + Tonder!C7 + Ukhdari!C7 + Urbiqu!C7 + Uularin!C7 + Verusa!C7 + Yaxuto!C7 + Zenashan!C7 + Hkuqo!C7 -> 9.671313e+08 | AJ7: =((AI7-AI8)/AI8) -> 0.006808056 | AK7: =SUM(AI7/C7) -> 0.14833174 | AR7: =SUM(AS7+250) -> 2010 | AS7: 1760 | AT7: =Amcha!C7 + Byllu!C7 + 'Chaenia'!C7 + 'Cruthi Anoso'!C7 + 'Dual Cenryia'!C7 + Exilium!C7 + Galca!C7 + Inania!C7 + Inrea!C7 + Isnti!C7 + Lieri!C7 + Ocaun!C7 + Otiiric!C7 + Ozinia!C7 + Pelugrotoa!C7 + 'Rtesania'!C7 + Sadain!C7 + Selaja!C7 + Seytinemas!C7 + Sivoso!C7 + Sunsokua!C7 + Taing!C7 + Taoisia!C7 + Trian!C7 + Vayvele!C7 -> 1.3205205e+09 | AU7: =((AT7-AT8)/AT8) -> 0.0095812558 | AV7: =SUM(AT7/C7) -> 0.20253207 | BC7: =SUM(BD7+250) -> 2010 | BD7: 1760 | BE7: ='Canldives'!C7 + 'Cloja'!C7 + Dahe!C7 + Eparia!C7 + Etretes!C7 + Haiza!C7 + Ihner!C7 + Kaastini!C7 + Kusierna!C7 + Migoku!C7 + 'North Ayre'!C7 + Oscairia!C7 + Oyreain!C7 + 'Pha Hii'!C7 + 'Pruim Fijan'!C7 + 'Prystr Hii'!C7 + 'Ruylku'!C7 + Sanagara!C7 + Shinam!C7 + Stinebar!C7 + Suenan!C7 + Taval!C7 + Ucrua!C7 + Vesozata!C7 + 'Welenu Fana'!C7 + 'Western Migoku'!C7 -> 1.3413668e+09 | BF7: =((BE7-BE8)/BE8) -> 0.0072034456 | BG7: =SUM(BE7/C7) -> 0.20572932 | BN7: =SUM(BO7+250) -> 2010 | BO7: 1760 | BP7: =Andsaudare!C7 + Aplasia!C7 + Astye!C7 + 'Crila Republic'!C7 + 'Elja and Munusia'!C7 + Hiwush!C7 + Iainoa!C7 + Isari!C7 + Isuibul!C7 + Maalle!C7 + Mendereide!C7 + Nia!C7 + 'Niretui and Anulan'!C7 + Ohtina!C7 + Prstreula!C7 + 'Rethern'!C7 + 'Rkmepuia'!C7 + Tvecoca!C7 + Umarcia!C7 + 'United Delet'!C7 + Veelmit!C7 + Walporein!C7 + Yutnitu!C7 -> 2.599223e+08 | BQ7: =((BP7-BP8)/BP8) -> 0.014983889 | BR7: =SUM(BP7/C7) -> 0.039865039 | BY7: =SUM(BZ7+250) -> 2010 | BZ7: 1760 | CA7: =Ahokini!C7 + Anymna!C7 + Ashain!C7 + Baluyde!C7 + Desaki!C7 + Erkizil!C7 + 'Far Lands'!C7 + Finae!C7 + Hyelen!C7 + Iareva!C7 + Letan!C7 + 'Mesjan Hyaa'!C7 + Myla!C7 + 'Nheyes Si'!C7 + Onphello!C7 + Quidic!C7 + Shomjind!C7 + 'United Mihili'!C7 + Verste!C7 + Volver!C7 + Wundry!C7 + Yihnurda!C7 + Zhanshe!C7 + Ztesh!C7 -> 1.0957143e+09 | CB7: =((CA7-CA8)/CA8) -> 0.014481258 | CC7: =SUM(CA7/C7) -> 0.16805288
A8: =SUM(B8+250) -> 2009 | B8: 1759 | C8: =Acetoa!C8 + Acrana!C8 + Aetintio!C8 + Ahokini!C8 + Amcha!C8 + Andsaudare!C8 + Anymna!C8 + Aplasia!C8 + Arbiya!C8 + 'Areoix Lie'!C8 + Ashain!C8 + Astye!C8 + Baluyde!C8 + Byllu!C8 + 'Candenat'!C8 + 'Canldives'!C8 + 'Chaenia'!C8 + 'Cloja'!C8 + 'Crila Republic'!C8 + 'Cruthi Anoso'!C8 + 'Curata'!C8 + Dahe!C8 + Danocia!C8 + Darewa!C8 + Desaki!C8 + Deschon!C8 + 'Disal Nila'!C8 + 'Dual Cenryia'!C8 + Ealdorii!C8 + Easuhura!C8 + Eldavpir!C8 + Eldjo!C8 + 'Elja and Munusia'!C8 + Emara!C8 + Enina!C8 + Eparia!C8 + Erkizil!C8 + Estijan!C8 + Etirha!C8 + Etretes!C8 + Exilium!C8 + 'Far Lands'!C8 + 'Feio Lie'!C8 + Fermori!C8 + Finae!C8 + Fincen!C8 + 'Fire Coast'!C8 + Gaeiya!C8 + Galca!C8 + Genaire!C8 + Grazail!C8 + Guise!C8 + Haiza!C8 + Heiso!C8 + Hiwush!C8 + Hkuqo!C8 + Hyelen!C8 + Iainoa!C8 + Iareva!C8 + Ihner!C8 + Ikzen!C8 + Ilicuhe!C8 + Inania!C8 + Inrea!C8 + Iquir!C8 + Isari!C8 + Isnti!C8 + Isuibul!C8 + Jathua!C8 + Jau!C8 + Jshain!C8 + Kaastini!C8 + Koruch!C8 + Kusierna!C8 + Laselteh!C8 + Lasri!C8 + Letan!C8 + Lieri!C8 + Lycroa!C8 + Lydroa!C8 + Maalle!C8 + Mendereide!C8 + 'Merela Sta'!C8 + 'Mesjan Hyaa'!C8 + Metndria!C8 + Migoku!C8 + Myla!C8 + 'New Kizura'!C8 + 'New Misos'!C8 + 'Nheyes Si'!C8 + Nia!C8 + 'Niretui and Anulan'!C8 + 'Niul Spijan'!C8 + 'North Ayre'!C8 + Ocaun!C8 + Ohtina!C8 + Onphello!C8 + Oscairia!C8 + Othya!C8 + Otiiric!C8 + Oyreain!C8 + Ozinia!C8 + Palina!C8 + Peka!C8 + Pelan!C8 + Pelines!C8 + Pelugrotoa!C8 + 'Pha Hii'!C8 + Phuris!C8 + Praesyu!C8 + Prstreula!C8 + 'Pruim Fijan'!C8 + 'Prystr Hii'!C8 + Quidic!C8 + 'Raledria'!C8 + 'Reerica'!C8 + 'Rethern'!C8 + 'Rijan bu'!C8 + 'Rinew'!C8 + 'Rkmepuia'!C8 + 'Rtesania'!C8 + 'Ruylku'!C8 + Saa!C8 + Sadain!C8 + Sanagara!C8 + Sattle!C8 + Selaja!C8 + Seytinemas!C8 + Shinam!C8 + Shomjind!C8 + Siana!C8 + Sivoso!C8 + Slyiaduun!C8 + Stinebar!C8 + Suenan!C8 + Sunsokua!C8 + Taing!C8 + Taniduna!C8 + Taoisia!C8 + Taval!C8 + Terressin!C8 + Tomscilus!C8 + Tonder!C8 + Trevilla!C8 + Trian!C8 + Tvecoca!C8 + Ucrua!C8 + Ukhdari!C8 + Umarcia!C8 + Umendel!C8 + 'United Delet'!C8 + 'United Mihili'!C8 + Urbiqu!C8 + Uularin!C8 + Vayvele!C8 + Veelmit!C8 + Verste!C8 + Verusa!C8 + Vesozata!C8 + Viussi!C8 + Volver!C8 + Walporein!C8 + 'Welenu Fana'!C8 + 'Western Migoku'!C8 + Wundry!C8 + Yaxuto!C8 + Yihnurda!C8 + Yoprioq!C8 + Yutnitu!C8 + Zenashan!C8 + Zhanshe!C8 + Ztesh!C8 -> 6.4528494e+09 | D8: =((C8-C9)/C9) -> 0.010869919 | K8: =SUM(L8+250) -> 2009 | L8: 1759 | M8: ='Areoix Lie'!C8 + Pelines!C8 + Terressin!C8 + Taniduna!C8 + Iquir!C8 + Deschon!C8 + Othya!C8 + Eldavpir!C8 + 'Candenat'!C8 + Jau!C8 + Viussi!C8 + Jathua!C8 + Jshain!C8 + Acetoa!C8 + Sattle!C8 + 'Reerica'!C8 + 'Feio Lie'!C8 + Umendel!C8 + 'Fire Coast'!C8 + Yoprioq!C8 + 'Rijan bu'!C8 + Saa!C8 + 'Rinew'!C8 + Enina!C8 + Trevilla!C8 -> 9.9687581e+08 | N8: =((M8-M9)/M9) -> 0.012520331 | O8: =SUM(M8/C8) -> 0.15448614 | V8: =SUM(W8+250) -> 2009 | W8: 1759 | X8: =Aetintio!C8 + Arbiya!C8 + 'Curata'!C8 + 'Disal Nila'!C8 + Etirha!C8 + Fincen!C8 + Gaeiya!C8 + Genaire!C8 + Grazail!C8 + Guise!C8 + Laselteh!C8 + Lasri!C8 + Metndria!C8 + 'New Misos'!C8 + Peka!C8 + Pelan!C8 + Phuris!C8 + 'Raledria'!C8 + Slyiaduun!C8 + Tomscilus!C8 -> 5.0038751e+08 | Y8: =((X8-X9)/X9) -> 0.014921104 | Z8: =SUM(X8/C8) -> 0.077545202 | AG8: =SUM(AH8+250) -> 2009 | AH8: 1759 | AI8: =Acrana!C8 + Danocia!C8 + Darewa!C8 + Ealdorii!C8 + Easuhura!C8 + Eldjo!C8 + Emara!C8 + Estijan!C8 + Fermori!C8 + Ikzen!C8 + Ilicuhe!C8 + Koruch!C8 + Lycroa!C8 + Lydroa!C8 + 'Merela Sta'!C8 + 'New Kizura'!C8 + 'Niul Spijan'!C8 + Palina!C8 + Praesyu!C8 + Siana!C8 + Tonder!C8 + Ukhdari!C8 + Urbiqu!C8 + Uularin!C8 + Verusa!C8 + Yaxuto!C8 + Zenashan!C8 + Hkuqo!C8 -> 9.6059154e+08 | AJ8: =((AI8-AI9)/AI9) -> 0.0066885485 | AK8: =SUM(AI8/C8) -> 0.14886316 | AR8: =SUM(AS8+250) -> 2009 | AS8: 1759 | AT8: =Amcha!C8 + Byllu!C8 + 'Chaenia'!C8 + 'Cruthi Anoso'!C8 + 'Dual Cenryia'!C8 + Exilium!C8 + Galca!C8 + Inania!C8 + Inrea!C8 + Isnti!C8 + Lieri!C8 + Ocaun!C8 + Otiiric!C8 + Ozinia!C8 + Pelugrotoa!C8 + 'Rtesania'!C8 + Sadain!C8 + Selaja!C8 + Seytinemas!C8 + Sivoso!C8 + Sunsokua!C8 + Taing!C8 + Taoisia!C8 + Trian!C8 + Vayvele!C8 -> 1.3079884e+09 | AU8: =((AT8-AT9)/AT9) -> 0.010107633 | AV8: =SUM(AT8/C8) -> 0.20269935 | BC8: =SUM(BD8+250) -> 2009 | BD8: 1759 | BE8: ='Canldives'!C8 + 'Cloja'!C8 + Dahe!C8 + Eparia!C8 + Etretes!C8 + Haiza!C8 + Ihner!C8 + Kaastini!C8 + Kusierna!C8 + Migoku!C8 + 'North Ayre'!C8 + Oscairia!C8 + Oyreain!C8 + 'Pha Hii'!C8 + 'Pruim Fijan'!C8 + 'Prystr Hii'!C8 + 'Ruylku'!C8 + Sanagara!C8 + Shinam!C8 + Stinebar!C8 + Suenan!C8 + Taval!C8 + Ucrua!C8 + Vesozata!C8 + 'Welenu Fana'!C8 + 'Western Migoku'!C8 -> 1.3317734e+09 | BF8: =((BE8-BE9)/BE9) -> 0.0074987698 | BG8: =SUM(BE8/C8) -> 0.20638532 | BN8: =SUM(BO8+250) -> 2009 | BO8: 1759 | BP8: =Andsaudare!C8 + Aplasia!C8 + Astye!C8 + 'Crila Republic'!C8 + 'Elja and Munusia'!C8 + Hiwush!C8 + Iainoa!C8 + Isari!C8 + Isuibul!C8 + Maalle!C8 + Mendereide!C8 + Nia!C8 + 'Niretui and Anulan'!C8 + Ohtina!C8 + Prstreula!C8 + 'Rethern'!C8 + 'Rkmepuia'!C8 + Tvecoca!C8 + Umarcia!C8 + 'United Delet'!C8 + Veelmit!C8 + Walporein!C8 + Yutnitu!C8 -> 2.5608515e+08 | BQ8: =((BP8-BP9)/BP9) -> 0.015525571 | BR8: =SUM(BP8/C8) -> 0.039685592 | BY8: =SUM(BZ8+250) -> 2009 | BZ8: 1759 | CA8: =Ahokini!C8 + Anymna!C8 + Ashain!C8 + Baluyde!C8 + Desaki!C8 + Erkizil!C8 + 'Far Lands'!C8 + Finae!C8 + Hyelen!C8 + Iareva!C8 + Letan!C8 + 'Mesjan Hyaa'!C8 + Myla!C8 + 'Nheyes Si'!C8 + Onphello!C8 + Quidic!C8 + Shomjind!C8 + 'United Mihili'!C8 + Verste!C8 + Volver!C8 + Wundry!C8 + Yihnurda!C8 + Zhanshe!C8 + Ztesh!C8 -> 1.0800735e+09 | CB8: =((CA8-CA9)/CA9) -> 0.015097057 | CC8: =SUM(CA8/C8) -> 0.16737931
A9: =SUM(B9+250) -> 2008 | B9: 1758 | C9: =Acetoa!C9 + Acrana!C9 + Aetintio!C9 + Ahokini!C9 + Amcha!C9 + Andsaudare!C9 + Anymna!C9 + Aplasia!C9 + Arbiya!C9 + 'Areoix Lie'!C9 + Ashain!C9 + Astye!C9 + Baluyde!C9 + Byllu!C9 + 'Candenat'!C9 + 'Canldives'!C9 + 'Chaenia'!C9 + 'Cloja'!C9 + 'Crila Republic'!C9 + 'Cruthi Anoso'!C9 + 'Curata'!C9 + Dahe!C9 + Danocia!C9 + Darewa!C9 + Desaki!C9 + Deschon!C9 + 'Disal Nila'!C9 + 'Dual Cenryia'!C9 + Ealdorii!C9 + Easuhura!C9 + Eldavpir!C9 + Eldjo!C9 + 'Elja and Munusia'!C9 + Emara!C9 + Enina!C9 + Eparia!C9 + Erkizil!C9 + Estijan!C9 + Etirha!C9 + Etretes!C9 + Exilium!C9 + 'Far Lands'!C9 + 'Feio Lie'!C9 + Fermori!C9 + Finae!C9 + Fincen!C9 + 'Fire Coast'!C9 + Gaeiya!C9 + Galca!C9 + Genaire!C9 + Grazail!C9 + Guise!C9 + Haiza!C9 + Heiso!C9 + Hiwush!C9 + Hkuqo!C9 + Hyelen!C9 + Iainoa!C9 + Iareva!C9 + Ihner!C9 + Ikzen!C9 + Ilicuhe!C9 + Inania!C9 + Inrea!C9 + Iquir!C9 + Isari!C9 + Isnti!C9 + Isuibul!C9 + Jathua!C9 + Jau!C9 + Jshain!C9 + Kaastini!C9 + Koruch!C9 + Kusierna!C9 + Laselteh!C9 + Lasri!C9 + Letan!C9 + Lieri!C9 + Lycroa!C9 + Lydroa!C9 + Maalle!C9 + Mendereide!C9 + 'Merela Sta'!C9 + 'Mesjan Hyaa'!C9 + Metndria!C9 + Migoku!C9 + Myla!C9 + 'New Kizura'!C9 + 'New Misos'!C9 + 'Nheyes Si'!C9 + Nia!C9 + 'Niretui and Anulan'!C9 + 'Niul Spijan'!C9 + 'North Ayre'!C9 + Ocaun!C9 + Ohtina!C9 + Onphello!C9 + Oscairia!C9 + Othya!C9 + Otiiric!C9 + Oyreain!C9 + Ozinia!C9 + Palina!C9 + Peka!C9 + Pelan!C9 + Pelines!C9 + Pelugrotoa!C9 + 'Pha Hii'!C9 + Phuris!C9 + Praesyu!C9 + Prstreula!C9 + 'Pruim Fijan'!C9 + 'Prystr Hii'!C9 + Quidic!C9 + 'Raledria'!C9 + 'Reerica'!C9 + 'Rethern'!C9 + 'Rijan bu'!C9 + 'Rinew'!C9 + 'Rkmepuia'!C9 + 'Rtesania'!C9 + 'Ruylku'!C9 + Saa!C9 + Sadain!C9 + Sanagara!C9 + Sattle!C9 + Selaja!C9 + Seytinemas!C9 + Shinam!C9 + Shomjind!C9 + Siana!C9 + Sivoso!C9 + Slyiaduun!C9 + Stinebar!C9 + Suenan!C9 + Sunsokua!C9 + Taing!C9 + Taniduna!C9 + Taoisia!C9 + Taval!C9 + Terressin!C9 + Tomscilus!C9 + Tonder!C9 + Trevilla!C9 + Trian!C9 + Tvecoca!C9 + Ucrua!C9 + Ukhdari!C9 + Umarcia!C9 + Umendel!C9 + 'United Delet'!C9 + 'United Mihili'!C9 + Urbiqu!C9 + Uularin!C9 + Vayvele!C9 + Veelmit!C9 + Verste!C9 + Verusa!C9 + Vesozata!C9 + Viussi!C9 + Volver!C9 + Walporein!C9 + 'Welenu Fana'!C9 + 'Western Migoku'!C9 + Wundry!C9 + Yaxuto!C9 + Yihnurda!C9 + Yoprioq!C9 + Yutnitu!C9 + Zenashan!C9 + Zhanshe!C9 + Ztesh!C9 -> 6.3834617e+09 | D9: =((C9-C10)/C10) -> 0.011523894 | K9: =SUM(L9+250) -> 2008 | L9: 1758 | M9: ='Areoix Lie'!C9 + Pelines!C9 + Terressin!C9 + Taniduna!C9 + Iquir!C9 + Deschon!C9 + Othya!C9 + Eldavpir!C9 + 'Candenat'!C9 + Jau!C9 + Viussi!C9 + Jathua!C9 + Jshain!C9 + Acetoa!C9 + Sattle!C9 + 'Reerica'!C9 + 'Feio Lie'!C9 + Umendel!C9 + 'Fire Coast'!C9 + Yoprioq!C9 + 'Rijan bu'!C9 + Saa!C9 + 'Rinew'!C9 + Enina!C9 + Trevilla!C9 -> 9.8454893e+08 | N9: =((M9-M10)/M10) -> 0.015966821 | O9: =SUM(M9/C9) -> 0.15423433 | V9: =SUM(W9+250) -> 2008 | W9: 1758 | X9: =Aetintio!C9 + Arbiya!C9 + 'Curata'!C9 + 'Disal Nila'!C9 + Etirha!C9 + Fincen!C9 + Gaeiya!C9 + Genaire!C9 + Grazail!C9 + Guise!C9 + Laselteh!C9 + Lasri!C9 + Metndria!C9 + 'New Misos'!C9 + Peka!C9 + Pelan!C9 + Phuris!C9 + 'Raledria'!C9 + Slyiaduun!C9 + Tomscilus!C9 -> 4.9303094e+08 | Y9: =((X9-X10)/X10) -> 0.014651217 | Z9: =SUM(X9/C9) -> 0.07723567 | AG9: =SUM(AH9+250) -> 2008 | AH9: 1758 | AI9: =Acrana!C9 + Danocia!C9 + Darewa!C9 + Ealdorii!C9 + Easuhura!C9 + Eldjo!C9 + Emara!C9 + Estijan!C9 + Fermori!C9 + Ikzen!C9 + Ilicuhe!C9 + Koruch!C9 + Lycroa!C9 + Lydroa!C9 + 'Merela Sta'!C9 + 'New Kizura'!C9 + 'Niul Spijan'!C9 + Palina!C9 + Praesyu!C9 + Siana!C9 + Tonder!C9 + Ukhdari!C9 + Urbiqu!C9 + Uularin!C9 + Verusa!C9 + Yaxuto!C9 + Zenashan!C9 + Hkuqo!C9 -> 9.5420927e+08 | AJ9: =((AI9-AI10)/AI10) -> 0.0068699768 | AK9: =SUM(AI9/C9) -> 0.14948147 | AR9: =SUM(AS9+250) -> 2008 | AS9: 1758 | AT9: =Amcha!C9 + Byllu!C9 + 'Chaenia'!C9 + 'Cruthi Anoso'!C9 + 'Dual Cenryia'!C9 + Exilium!C9 + Galca!C9 + Inania!C9 + Inrea!C9 + Isnti!C9 + Lieri!C9 + Ocaun!C9 + Otiiric!C9 + Ozinia!C9 + Pelugrotoa!C9 + 'Rtesania'!C9 + Sadain!C9 + Selaja!C9 + Seytinemas!C9 + Sivoso!C9 + Sunsokua!C9 + Taing!C9 + Taoisia!C9 + Trian!C9 + Vayvele!C9 -> 1.2949e+09 | AU9: =((AT9-AT10)/AT10) -> 0.010108017 | AV9: =SUM(AT9/C9) -> 0.20285232 | BC9: =SUM(BD9+250) -> 2008 | BD9: 1758 | BE9: ='Canldives'!C9 + 'Cloja'!C9 + Dahe!C9 + Eparia!C9 + Etretes!C9 + Haiza!C9 + Ihner!C9 + Kaastini!C9 + Kusierna!C9 + Migoku!C9 + 'North Ayre'!C9 + Oscairia!C9 + Oyreain!C9 + 'Pha Hii'!C9 + 'Pruim Fijan'!C9 + 'Prystr Hii'!C9 + 'Ruylku'!C9 + Sanagara!C9 + Shinam!C9 + Stinebar!C9 + Suenan!C9 + Taval!C9 + Ucrua!C9 + Vesozata!C9 + 'Welenu Fana'!C9 + 'Western Migoku'!C9 -> 1.3218611e+09 | BF9: =((BE9-BE10)/BE10) -> 0.0077894278 | BG9: =SUM(BE9/C9) -> 0.2070759 | BN9: =SUM(BO9+250) -> 2008 | BO9: 1758 | BP9: =Andsaudare!C9 + Aplasia!C9 + Astye!C9 + 'Crila Republic'!C9 + 'Elja and Munusia'!C9 + Hiwush!C9 + Iainoa!C9 + Isari!C9 + Isuibul!C9 + Maalle!C9 + Mendereide!C9 + Nia!C9 + 'Niretui and Anulan'!C9 + Ohtina!C9 + Prstreula!C9 + 'Rethern'!C9 + 'Rkmepuia'!C9 + Tvecoca!C9 + Umarcia!C9 + 'United Delet'!C9 + Veelmit!C9 + Walporein!C9 + Yutnitu!C9 -> 2.5217006e+08 | BQ9: =((BP9-BP10)/BP10) -> 0.015220552 | BR9: =SUM(BP9/C9) -> 0.039503654 | BY9: =SUM(BZ9+250) -> 2008 | BZ9: 1758 | CA9: =Ahokini!C9 + Anymna!C9 + Ashain!C9 + Baluyde!C9 + Desaki!C9 + Erkizil!C9 + 'Far Lands'!C9 + Finae!C9 + Hyelen!C9 + Iareva!C9 + Letan!C9 + 'Mesjan Hyaa'!C9 + Myla!C9 + 'Nheyes Si'!C9 + Onphello!C9 + Quidic!C9 + Shomjind!C9 + 'United Mihili'!C9 + Verste!C9 + Volver!C9 + Wundry!C9 + Yihnurda!C9 + Zhanshe!C9 + Ztesh!C9 -> 1.06401e+09 | CB9: =((CA9-CA10)/CA10) -> 0.015587842 | CC9: =SUM(CA9/C9) -> 0.16668229
A10: =SUM(B10+250) -> 2007 | B10: 1757 | C10: =Acetoa!C10 + Acrana!C10 + Aetintio!C10 + Ahokini!C10 + Amcha!C10 + Andsaudare!C10 + Anymna!C10 + Aplasia!C10 + Arbiya!C10 + 'Areoix Lie'!C10 + Ashain!C10 + Astye!C10 + Baluyde!C10 + Byllu!C10 + 'Candenat'!C10 + 'Canldives'!C10 + 'Chaenia'!C10 + 'Cloja'!C10 + 'Crila Republic'!C10 + 'Cruthi Anoso'!C10 + 'Curata'!C10 + Dahe!C10 + Danocia!C10 + Darewa!C10 + Desaki!C10 + Deschon!C10 + 'Disal Nila'!C10 + 'Dual Cenryia'!C10 + Ealdorii!C10 + Easuhura!C10 + Eldavpir!C10 + Eldjo!C10 + 'Elja and Munusia'!C10 + Emara!C10 + Enina!C10 + Eparia!C10 + Erkizil!C10 + Estijan!C10 + Etirha!C10 + Etretes!C10 + Exilium!C10 + 'Far Lands'!C10 + 'Feio Lie'!C10 + Fermori!C10 + Finae!C10 + Fincen!C10 + 'Fire Coast'!C10 + Gaeiya!C10 + Galca!C10 + Genaire!C10 + Grazail!C10 + Guise!C10 + Haiza!C10 + Heiso!C10 + Hiwush!C10 + Hkuqo!C10 + Hyelen!C10 + Iainoa!C10 + Iareva!C10 + Ihner!C10 + Ikzen!C10 + Ilicuhe!C10 + Inania!C10 + Inrea!C10 + Iquir!C10 + Isari!C10 + Isnti!C10 + Isuibul!C10 + Jathua!C10 + Jau!C10 + Jshain!C10 + Kaastini!C10 + Koruch!C10 + Kusierna!C10 + Laselteh!C10 + Lasri!C10 + Letan!C10 + Lieri!C10 + Lycroa!C10 + Lydroa!C10 + Maalle!C10 + Mendereide!C10 + 'Merela Sta'!C10 + 'Mesjan Hyaa'!C10 + Metndria!C10 + Migoku!C10 + Myla!C10 + 'New Kizura'!C10 + 'New Misos'!C10 + 'Nheyes Si'!C10 + Nia!C10 + 'Niretui and Anulan'!C10 + 'Niul Spijan'!C10 + 'North Ayre'!C10 + Ocaun!C10 + Ohtina!C10 + Onphello!C10 + Oscairia!C10 + Othya!C10 + Otiiric!C10 + Oyreain!C10 + Ozinia!C10 + Palina!C10 + Peka!C10 + Pelan!C10 + Pelines!C10 + Pelugrotoa!C10 + 'Pha Hii'!C10 + Phuris!C10 + Praesyu!C10 + Prstreula!C10 + 'Pruim Fijan'!C10 + 'Prystr Hii'!C10 + Quidic!C10 + 'Raledria'!C10 + 'Reerica'!C10 + 'Rethern'!C10 + 'Rijan bu'!C10 + 'Rinew'!C10 + 'Rkmepuia'!C10 + 'Rtesania'!C10 + 'Ruylku'!C10 + Saa!C10 + Sadain!C10 + Sanagara!C10 + Sattle!C10 + Selaja!C10 + Seytinemas!C10 + Shinam!C10 + Shomjind!C10 + Siana!C10 + Sivoso!C10 + Slyiaduun!C10 + Stinebar!C10 + Suenan!C10 + Sunsokua!C10 + Taing!C10 + Taniduna!C10 + Taoisia!C10 + Taval!C10 + Terressin!C10 + Tomscilus!C10 + Tonder!C10 + Trevilla!C10 + Trian!C10 + Tvecoca!C10 + Ucrua!C10 + Ukhdari!C10 + Umarcia!C10 + Umendel!C10 + 'United Delet'!C10 + 'United Mihili'!C10 + Urbiqu!C10 + Uularin!C10 + Vayvele!C10 + Veelmit!C10 + Verste!C10 + Verusa!C10 + Vesozata!C10 + Viussi!C10 + Volver!C10 + Walporein!C10 + 'Welenu Fana'!C10 + 'Western Migoku'!C10 + Wundry!C10 + Yaxuto!C10 + Yihnurda!C10 + Yoprioq!C10 + Yutnitu!C10 + Zenashan!C10 + Zhanshe!C10 + Ztesh!C10 -> 6.3107374e+09 | D10: =((C10-C11)/C11) -> 0.011187138 | K10: =SUM(L10+250) -> 2007 | L10: 1757 | M10: ='Areoix Lie'!C10 + Pelines!C10 + Terressin!C10 + Taniduna!C10 + Iquir!C10 + Deschon!C10 + Othya!C10 + Eldavpir!C10 + 'Candenat'!C10 + Jau!C10 + Viussi!C10 + Jathua!C10 + Jshain!C10 + Acetoa!C10 + Sattle!C10 + 'Reerica'!C10 + 'Feio Lie'!C10 + Umendel!C10 + 'Fire Coast'!C10 + Yoprioq!C10 + 'Rijan bu'!C10 + Saa!C10 + 'Rinew'!C10 + Enina!C10 + Trevilla!C10 -> 9.6907587e+08 | N10: =((M10-M11)/M11) -> 0.013427115 | O10: =SUM(M10/C10) -> 0.15355985 | V10: =SUM(W10+250) -> 2007 | W10: 1757 | X10: =Aetintio!C10 + Arbiya!C10 + 'Curata'!C10 + 'Disal Nila'!C10 + Etirha!C10 + Fincen!C10 + Gaeiya!C10 + Genaire!C10 + Grazail!C10 + Guise!C10 + Laselteh!C10 + Lasri!C10 + Metndria!C10 + 'New Misos'!C10 + Peka!C10 + Pelan!C10 + Phuris!C10 + 'Raledria'!C10 + Slyiaduun!C10 + Tomscilus!C10 -> 4.8591174e+08 | Y10: =((X10-X11)/X11) -> 0.013756286 | Z10: =SUM(X10/C10) -> 0.076997617 | AG10: =SUM(AH10+250) -> 2007 | AH10: 1757 | AI10: =Acrana!C10 + Danocia!C10 + Darewa!C10 + Ealdorii!C10 + Easuhura!C10 + Eldjo!C10 + Emara!C10 + Estijan!C10 + Fermori!C10 + Ikzen!C10 + Ilicuhe!C10 + Koruch!C10 + Lycroa!C10 + Lydroa!C10 + 'Merela Sta'!C10 + 'New Kizura'!C10 + 'Niul Spijan'!C10 + Palina!C10 + Praesyu!C10 + Siana!C10 + Tonder!C10 + Ukhdari!C10 + Urbiqu!C10 + Uularin!C10 + Verusa!C10 + Yaxuto!C10 + Zenashan!C10 + Hkuqo!C10 -> 9.476986e+08 | AJ10: =((AI10-AI11)/AI11) -> 0.0066946751 | AK10: =SUM(AI10/C10) -> 0.1501724 | AR10: =SUM(AS10+250) -> 2007 | AS10: 1757 | AT10: =Amcha!C10 + Byllu!C10 + 'Chaenia'!C10 + 'Cruthi Anoso'!C10 + 'Dual Cenryia'!C10 + Exilium!C10 + Galca!C10 + Inania!C10 + Inrea!C10 + Isnti!C10 + Lieri!C10 + Ocaun!C10 + Otiiric!C10 + Ozinia!C10 + Pelugrotoa!C10 + 'Rtesania'!C10 + Sadain!C10 + Selaja!C10 + Seytinemas!C10 + Sivoso!C10 + Sunsokua!C10 + Taing!C10 + Taoisia!C10 + Trian!C10 + Vayvele!C10 -> 1.2819421e+09 | AU10: =((AT10-AT11)/AT11) -> 0.010144304 | AV10: =SUM(AT10/C10) -> 0.20313666 | BC10: =SUM(BD10+250) -> 2007 | BD10: 1757 | BE10: ='Canldives'!C10 + 'Cloja'!C10 + Dahe!C10 + Eparia!C10 + Etretes!C10 + Haiza!C10 + Ihner!C10 + Kaastini!C10 + Kusierna!C10 + Migoku!C10 + 'North Ayre'!C10 + Oscairia!C10 + Oyreain!C10 + 'Pha Hii'!C10 + 'Pruim Fijan'!C10 + 'Prystr Hii'!C10 + 'Ruylku'!C10 + Sanagara!C10 + Shinam!C10 + Stinebar!C10 + Suenan!C10 + Taval!C10 + Ucrua!C10 + Vesozata!C10 + 'Welenu Fana'!C10 + 'Western Migoku'!C10 -> 1.3116441e+09 | BF10: =((BE10-BE11)/BE11) -> 0.0081378018 | BG10: =SUM(BE10/C10) -> 0.20784324 | BN10: =SUM(BO10+250) -> 2007 | BO10: 1757 | BP10: =Andsaudare!C10 + Aplasia!C10 + Astye!C10 + 'Crila Republic'!C10 + 'Elja and Munusia'!C10 + Hiwush!C10 + Iainoa!C10 + Isari!C10 + Isuibul!C10 + Maalle!C10 + Mendereide!C10 + Nia!C10 + 'Niretui and Anulan'!C10 + Ohtina!C10 + Prstreula!C10 + 'Rethern'!C10 + 'Rkmepuia'!C10 + Tvecoca!C10 + Umarcia!C10 + 'United Delet'!C10 + Veelmit!C10 + Walporein!C10 + Yutnitu!C10 -> 2.4838944e+08 | BQ10: =((BP10-BP11)/BP11) -> 0.015184271 | BR10: =SUM(BP10/C10) -> 0.039359812 | BY10: =SUM(BZ10+250) -> 2007 | BZ10: 1757 | CA10: =Ahokini!C10 + Anymna!C10 + Ashain!C10 + Baluyde!C10 + Desaki!C10 + Erkizil!C10 + 'Far Lands'!C10 + Finae!C10 + Hyelen!C10 + Iareva!C10 + Letan!C10 + 'Mesjan Hyaa'!C10 + Myla!C10 + 'Nheyes Si'!C10 + Onphello!C10 + Quidic!C10 + Shomjind!C10 + 'United Mihili'!C10 + Verste!C10 + Volver!C10 + Wundry!C10 + Yihnurda!C10 + Zhanshe!C10 + Ztesh!C10 -> 1.047679e+09 | CB10: =((CA10-CA11)/CA11) -> 0.016082189 | CC10: =SUM(CA10/C10) -> 0.1660153
A11: =SUM(B11+250) -> 2006 | B11: 1756 | C11: =Acetoa!C11 + Acrana!C11 + Aetintio!C11 + Ahokini!C11 + Amcha!C11 + Andsaudare!C11 + Anymna!C11 + Aplasia!C11 + Arbiya!C11 + 'Areoix Lie'!C11 + Ashain!C11 + Astye!C11 + Baluyde!C11 + Byllu!C11 + 'Candenat'!C11 + 'Canldives'!C11 + 'Chaenia'!C11 + 'Cloja'!C11 + 'Crila Republic'!C11 + 'Cruthi Anoso'!C11 + 'Curata'!C11 + Dahe!C11 + Danocia!C11 + Darewa!C11 + Desaki!C11 + Deschon!C11 + 'Disal Nila'!C11 + 'Dual Cenryia'!C11 + Ealdorii!C11 + Easuhura!C11 + Eldavpir!C11 + Eldjo!C11 + 'Elja and Munusia'!C11 + Emara!C11 + Enina!C11 + Eparia!C11 + Erkizil!C11 + Estijan!C11 + Etirha!C11 + Etretes!C11 + Exilium!C11 + 'Far Lands'!C11 + 'Feio Lie'!C11 + Fermori!C11 + Finae!C11 + Fincen!C11 + 'Fire Coast'!C11 + Gaeiya!C11 + Galca!C11 + Genaire!C11 + Grazail!C11 + Guise!C11 + Haiza!C11 + Heiso!C11 + Hiwush!C11 + Hkuqo!C11 + Hyelen!C11 + Iainoa!C11 + Iareva!C11 + Ihner!C11 + Ikzen!C11 + Ilicuhe!C11 + Inania!C11 + Inrea!C11 + Iquir!C11 + Isari!C11 + Isnti!C11 + Isuibul!C11 + Jathua!C11 + Jau!C11 + Jshain!C11 + Kaastini!C11 + Koruch!C11 + Kusierna!C11 + Laselteh!C11 + Lasri!C11 + Letan!C11 + Lieri!C11 + Lycroa!C11 + Lydroa!C11 + Maalle!C11 + Mendereide!C11 + 'Merela Sta'!C11 + 'Mesjan Hyaa'!C11 + Metndria!C11 + Migoku!C11 + Myla!C11 + 'New Kizura'!C11 + 'New Misos'!C11 + 'Nheyes Si'!C11 + Nia!C11 + 'Niretui and Anulan'!C11 + 'Niul Spijan'!C11 + 'North Ayre'!C11 + Ocaun!C11 + Ohtina!C11 + Onphello!C11 + Oscairia!C11 + Othya!C11 + Otiiric!C11 + Oyreain!C11 + Ozinia!C11 + Palina!C11 + Peka!C11 + Pelan!C11 + Pelines!C11 + Pelugrotoa!C11 + 'Pha Hii'!C11 + Phuris!C11 + Praesyu!C11 + Prstreula!C11 + 'Pruim Fijan'!C11 + 'Prystr Hii'!C11 + Quidic!C11 + 'Raledria'!C11 + 'Reerica'!C11 + 'Rethern'!C11 + 'Rijan bu'!C11 + 'Rinew'!C11 + 'Rkmepuia'!C11 + 'Rtesania'!C11 + 'Ruylku'!C11 + Saa!C11 + Sadain!C11 + Sanagara!C11 + Sattle!C11 + Selaja!C11 + Seytinemas!C11 + Shinam!C11 + Shomjind!C11 + Siana!C11 + Sivoso!C11 + Slyiaduun!C11 + Stinebar!C11 + Suenan!C11 + Sunsokua!C11 + Taing!C11 + Taniduna!C11 + Taoisia!C11 + Taval!C11 + Terressin!C11 + Tomscilus!C11 + Tonder!C11 + Trevilla!C11 + Trian!C11 + Tvecoca!C11 + Ucrua!C11 + Ukhdari!C11 + Umarcia!C11 + Umendel!C11 + 'United Delet'!C11 + 'United Mihili'!C11 + Urbiqu!C11 + Uularin!C11 + Vayvele!C11 + Veelmit!C11 + Verste!C11 + Verusa!C11 + Vesozata!C11 + Viussi!C11 + Volver!C11 + Walporein!C11 + 'Welenu Fana'!C11 + 'Western Migoku'!C11 + Wundry!C11 + Yaxuto!C11 + Yihnurda!C11 + Yoprioq!C11 + Yutnitu!C11 + Zenashan!C11 + Zhanshe!C11 + Ztesh!C11 -> 6.2409194e+09 | D11: =((C11-C12)/C12) -> 0.011344612 | K11: =SUM(L11+250) -> 2006 | L11: 1756 | M11: ='Areoix Lie'!C11 + Pelines!C11 + Terressin!C11 + Taniduna!C11 + Iquir!C11 + Deschon!C11 + Othya!C11 + Eldavpir!C11 + 'Candenat'!C11 + Jau!C11 + Viussi!C11 + Jathua!C11 + Jshain!C11 + Acetoa!C11 + Sattle!C11 + 'Reerica'!C11 + 'Feio Lie'!C11 + Umendel!C11 + 'Fire Coast'!C11 + Yoprioq!C11 + 'Rijan bu'!C11 + Saa!C11 + 'Rinew'!C11 + Enina!C11 + Trevilla!C11 -> 9.5623637e+08 | N11: =((M11-M12)/M12) -> 0.014195436 | O11: =SUM(M11/C11) -> 0.15322043 | V11: =SUM(W11+250) -> 2006 | W11: 1756 | X11: =Aetintio!C11 + Arbiya!C11 + 'Curata'!C11 + 'Disal Nila'!C11 + Etirha!C11 + Fincen!C11 + Gaeiya!C11 + Genaire!C11 + Grazail!C11 + Guise!C11 + Laselteh!C11 + Lasri!C11 + Metndria!C11 + 'New Misos'!C11 + Peka!C11 + Pelan!C11 + Phuris!C11 + 'Raledria'!C11 + Slyiaduun!C11 + Tomscilus!C11 -> 4.7931811e+08 | Y11: =((X11-X12)/X12) -> 0.011184981 | Z11: =SUM(X11/C11) -> 0.076802483 | AG11: =SUM(AH11+250) -> 2006 | AH11: 1756 | AI11: =Acrana!C11 + Danocia!C11 + Darewa!C11 + Ealdorii!C11 + Easuhura!C11 + Eldjo!C11 + Emara!C11 + Estijan!C11 + Fermori!C11 + Ikzen!C11 + Ilicuhe!C11 + Koruch!C11 + Lycroa!C11 + Lydroa!C11 + 'Merela Sta'!C11 + 'New Kizura'!C11 + 'Niul Spijan'!C11 + Palina!C11 + Praesyu!C11 + Siana!C11 + Tonder!C11 + Ukhdari!C11 + Urbiqu!C11 + Uularin!C11 + Verusa!C11 + Yaxuto!C11 + Zenashan!C11 + Hkuqo!C11 -> 9.4139626e+08 | AJ11: =((AI11-AI12)/AI12) -> 0.0070115451 | AK11: =SUM(AI11/C11) -> 0.15084256 | AR11: =SUM(AS11+250) -> 2006 | AS11: 1756 | AT11: =Amcha!C11 + Byllu!C11 + 'Chaenia'!C11 + 'Cruthi Anoso'!C11 + 'Dual Cenryia'!C11 + Exilium!C11 + Galca!C11 + Inania!C11 + Inrea!C11 + Isnti!C11 + Lieri!C11 + Ocaun!C11 + Otiiric!C11 + Ozinia!C11 + Pelugrotoa!C11 + 'Rtesania'!C11 + Sadain!C11 + Selaja!C11 + Seytinemas!C11 + Sivoso!C11 + Sunsokua!C11 + Taing!C11 + Taoisia!C11 + Trian!C11 + Vayvele!C11 -> 1.2690683e+09 | AU11: =((AT11-AT12)/AT12) -> 0.010942699 | AV11: =SUM(AT11/C11) -> 0.20334637 | BC11: =SUM(BD11+250) -> 2006 | BD11: 1756 | BE11: ='Canldives'!C11 + 'Cloja'!C11 + Dahe!C11 + Eparia!C11 + Etretes!C11 + Haiza!C11 + Ihner!C11 + Kaastini!C11 + Kusierna!C11 + Migoku!C11 + 'North Ayre'!C11 + Oscairia!C11 + Oyreain!C11 + 'Pha Hii'!C11 + 'Pruim Fijan'!C11 + 'Prystr Hii'!C11 + 'Ruylku'!C11 + Sanagara!C11 + Shinam!C11 + Stinebar!C11 + Suenan!C11 + Taval!C11 + Ucrua!C11 + Vesozata!C11 + 'Welenu Fana'!C11 + 'Western Migoku'!C11 -> 1.3010564e+09 | BF11: =((BE11-BE12)/BE12) -> 0.0082471155 | BG11: =SUM(BE11/C11) -> 0.20847191 | BN11: =SUM(BO11+250) -> 2006 | BO11: 1756 | BP11: =Andsaudare!C11 + Aplasia!C11 + Astye!C11 + 'Crila Republic'!C11 + 'Elja and Munusia'!C11 + Hiwush!C11 + Iainoa!C11 + Isari!C11 + Isuibul!C11 + Maalle!C11 + Mendereide!C11 + Nia!C11 + 'Niretui and Anulan'!C11 + Ohtina!C11 + Prstreula!C11 + 'Rethern'!C11 + 'Rkmepuia'!C11 + Tvecoca!C11 + Umarcia!C11 + 'United Delet'!C11 + Veelmit!C11 + Walporein!C11 + Yutnitu!C11 -> 2.4467424e+08 | BQ11: =((BP11-BP12)/BP12) -> 0.015075399 | BR11: =SUM(BP11/C11) -> 0.039204839 | BY11: =SUM(BZ11+250) -> 2006 | BZ11: 1756 | CA11: =Ahokini!C11 + Anymna!C11 + Ashain!C11 + Baluyde!C11 + Desaki!C11 + Erkizil!C11 + 'Far Lands'!C11 + Finae!C11 + Hyelen!C11 + Iareva!C11 + Letan!C11 + 'Mesjan Hyaa'!C11 + Myla!C11 + 'Nheyes Si'!C11 + Onphello!C11 + Quidic!C11 + Shomjind!C11 + 'United Mihili'!C11 + Verste!C11 + Volver!C11 + Wundry!C11 + Yihnurda!C11 + Zhanshe!C11 + Ztesh!C11 -> 1.0310967e+09 | CB11: =((CA11-CA12)/CA12) -> 0.016204865 | CC11: =SUM(CA11/C11) -> 0.16521551
A12: =SUM(B12+250) -> 2005 | B12: 1755 | C12: =Acetoa!C12 + Acrana!C12 + Aetintio!C12 + Ahokini!C12 + Amcha!C12 + Andsaudare!C12 + Anymna!C12 + Aplasia!C12 + Arbiya!C12 + 'Areoix Lie'!C12 + Ashain!C12 + Astye!C12 + Baluyde!C12 + Byllu!C12 + 'Candenat'!C12 + 'Canldives'!C12 + 'Chaenia'!C12 + 'Cloja'!C12 + 'Crila Republic'!C12 + 'Cruthi Anoso'!C12 + 'Curata'!C12 + Dahe!C12 + Danocia!C12 + Darewa!C12 + Desaki!C12 + Deschon!C12 + 'Disal Nila'!C12 + 'Dual Cenryia'!C12 + Ealdorii!C12 + Easuhura!C12 + Eldavpir!C12 + Eldjo!C12 + 'Elja and Munusia'!C12 + Emara!C12 + Enina!C12 + Eparia!C12 + Erkizil!C12 + Estijan!C12 + Etirha!C12 + Etretes!C12 + Exilium!C12 + 'Far Lands'!C12 + 'Feio Lie'!C12 + Fermori!C12 + Finae!C12 + Fincen!C12 + 'Fire Coast'!C12 + Gaeiya!C12 + Galca!C12 + Genaire!C12 + Grazail!C12 + Guise!C12 + Haiza!C12 + Heiso!C12 + Hiwush!C12 + Hkuqo!C12 + Hyelen!C12 + Iainoa!C12 + Iareva!C12 + Ihner!C12 + Ikzen!C12 + Ilicuhe!C12 + Inania!C12 + Inrea!C12 + Iquir!C12 + Isari!C12 + Isnti!C12 + Isuibul!C12 + Jathua!C12 + Jau!C12 + Jshain!C12 + Kaastini!C12 + Koruch!C12 + Kusierna!C12 + Laselteh!C12 + Lasri!C12 + Letan!C12 + Lieri!C12 + Lycroa!C12 + Lydroa!C12 + Maalle!C12 + Mendereide!C12 + 'Merela Sta'!C12 + 'Mesjan Hyaa'!C12 + Metndria!C12 + Migoku!C12 + Myla!C12 + 'New Kizura'!C12 + 'New Misos'!C12 + 'Nheyes Si'!C12 + Nia!C12 + 'Niretui and Anulan'!C12 + 'Niul Spijan'!C12 + 'North Ayre'!C12 + Ocaun!C12 + Ohtina!C12 + Onphello!C12 + Oscairia!C12 + Othya!C12 + Otiiric!C12 + Oyreain!C12 + Ozinia!C12 + Palina!C12 + Peka!C12 + Pelan!C12 + Pelines!C12 + Pelugrotoa!C12 + 'Pha Hii'!C12 + Phuris!C12 + Praesyu!C12 + Prstreula!C12 + 'Pruim Fijan'!C12 + 'Prystr Hii'!C12 + Quidic!C12 + 'Raledria'!C12 + 'Reerica'!C12 + 'Rethern'!C12 + 'Rijan bu'!C12 + 'Rinew'!C12 + 'Rkmepuia'!C12 + 'Rtesania'!C12 + 'Ruylku'!C12 + Saa!C12 + Sadain!C12 + Sanagara!C12 + Sattle!C12 + Selaja!C12 + Seytinemas!C12 + Shinam!C12 + Shomjind!C12 + Siana!C12 + Sivoso!C12 + Slyiaduun!C12 + Stinebar!C12 + Suenan!C12 + Sunsokua!C12 + Taing!C12 + Taniduna!C12 + Taoisia!C12 + Taval!C12 + Terressin!C12 + Tomscilus!C12 + Tonder!C12 + Trevilla!C12 + Trian!C12 + Tvecoca!C12 + Ucrua!C12 + Ukhdari!C12 + Umarcia!C12 + Umendel!C12 + 'United Delet'!C12 + 'United Mihili'!C12 + Urbiqu!C12 + Uularin!C12 + Vayvele!C12 + Veelmit!C12 + Verste!C12 + Verusa!C12 + Vesozata!C12 + Viussi!C12 + Volver!C12 + Walporein!C12 + 'Welenu Fana'!C12 + 'Western Migoku'!C12 + Wundry!C12 + Yaxuto!C12 + Yihnurda!C12 + Yoprioq!C12 + Yutnitu!C12 + Zenashan!C12 + Zhanshe!C12 + Ztesh!C12 -> 6.1709128e+09 | D12: =((C12-C13)/C13) -> 0.011302747 | K12: =SUM(L12+250) -> 2005 | L12: 1755 | M12: ='Areoix Lie'!C12 + Pelines!C12 + Terressin!C12 + Taniduna!C12 + Iquir!C12 + Deschon!C12 + Othya!C12 + Eldavpir!C12 + 'Candenat'!C12 + Jau!C12 + Viussi!C12 + Jathua!C12 + Jshain!C12 + Acetoa!C12 + Sattle!C12 + 'Reerica'!C12 + 'Feio Lie'!C12 + Umendel!C12 + 'Fire Coast'!C12 + Yoprioq!C12 + 'Rijan bu'!C12 + Saa!C12 + 'Rinew'!C12 + Enina!C12 + Trevilla!C12 -> 9.4285218e+08 | N12: =((M12-M13)/M13) -> 0.014084455 | O12: =SUM(M12/C12) -> 0.15278974 | V12: =SUM(W12+250) -> 2005 | W12: 1755 | X12: =Aetintio!C12 + Arbiya!C12 + 'Curata'!C12 + 'Disal Nila'!C12 + Etirha!C12 + Fincen!C12 + Gaeiya!C12 + Genaire!C12 + Grazail!C12 + Guise!C12 + Laselteh!C12 + Lasri!C12 + Metndria!C12 + 'New Misos'!C12 + Peka!C12 + Pelan!C12 + Phuris!C12 + 'Raledria'!C12 + Slyiaduun!C12 + Tomscilus!C12 -> 4.7401624e+08 | Y12: =((X12-X13)/X13) -> 0.010851903 | Z12: =SUM(X12/C12) -> 0.076814608 | AG12: =SUM(AH12+250) -> 2005 | AH12: 1755 | AI12: =Acrana!C12 + Danocia!C12 + Darewa!C12 + Ealdorii!C12 + Easuhura!C12 + Eldjo!C12 + Emara!C12 + Estijan!C12 + Fermori!C12 + Ikzen!C12 + Ilicuhe!C12 + Koruch!C12 + Lycroa!C12 + Lydroa!C12 + 'Merela Sta'!C12 + 'New Kizura'!C12 + 'Niul Spijan'!C12 + Palina!C12 + Praesyu!C12 + Siana!C12 + Tonder!C12 + Ukhdari!C12 + Urbiqu!C12 + Uularin!C12 + Verusa!C12 + Yaxuto!C12 + Zenashan!C12 + Hkuqo!C12 -> 9.3484157e+08 | AJ12: =((AI12-AI13)/AI13) -> 0.0069644122 | AK12: =SUM(AI12/C12) -> 0.15149162 | AR12: =SUM(AS12+250) -> 2005 | AS12: 1755 | AT12: =Amcha!C12 + Byllu!C12 + 'Chaenia'!C12 + 'Cruthi Anoso'!C12 + 'Dual Cenryia'!C12 + Exilium!C12 + Galca!C12 + Inania!C12 + Inrea!C12 + Isnti!C12 + Lieri!C12 + Ocaun!C12 + Otiiric!C12 + Ozinia!C12 + Pelugrotoa!C12 + 'Rtesania'!C12 + Sadain!C12 + Selaja!C12 + Seytinemas!C12 + Sivoso!C12 + Sunsokua!C12 + Taing!C12 + Taoisia!C12 + Trian!C12 + Vayvele!C12 -> 1.2553316e+09 | AU12: =((AT12-AT13)/AT13) -> 0.010774153 | AV12: =SUM(AT12/C12) -> 0.20342721 | BC12: =SUM(BD12+250) -> 2005 | BD12: 1755 | BE12: ='Canldives'!C12 + 'Cloja'!C12 + Dahe!C12 + Eparia!C12 + Etretes!C12 + Haiza!C12 + Ihner!C12 + Kaastini!C12 + Kusierna!C12 + Migoku!C12 + 'North Ayre'!C12 + Oscairia!C12 + Oyreain!C12 + 'Pha Hii'!C12 + 'Pruim Fijan'!C12 + 'Prystr Hii'!C12 + 'Ruylku'!C12 + Sanagara!C12 + Shinam!C12 + Stinebar!C12 + Suenan!C12 + Taval!C12 + Ucrua!C12 + Vesozata!C12 + 'Welenu Fana'!C12 + 'Western Migoku'!C12 -> 1.2904142e+09 | BF12: =((BE12-BE13)/BE13) -> 0.0083821366 | BG12: =SUM(BE12/C12) -> 0.20911237 | BN12: =SUM(BO12+250) -> 2005 | BO12: 1755 | BP12: =Andsaudare!C12 + Aplasia!C12 + Astye!C12 + 'Crila Republic'!C12 + 'Elja and Munusia'!C12 + Hiwush!C12 + Iainoa!C12 + Isari!C12 + Isuibul!C12 + Maalle!C12 + Mendereide!C12 + Nia!C12 + 'Niretui and Anulan'!C12 + Ohtina!C12 + Prstreula!C12 + 'Rethern'!C12 + 'Rkmepuia'!C12 + Tvecoca!C12 + Umarcia!C12 + 'United Delet'!C12 + Veelmit!C12 + Walporein!C12 + Yutnitu!C12 -> 2.4104046e+08 | BQ12: =((BP12-BP13)/BP13) -> 0.015183431 | BR12: =SUM(BP12/C12) -> 0.039060746 | BY12: =SUM(BZ12+250) -> 2005 | BZ12: 1755 | CA12: =Ahokini!C12 + Anymna!C12 + Ashain!C12 + Baluyde!C12 + Desaki!C12 + Erkizil!C12 + 'Far Lands'!C12 + Finae!C12 + Hyelen!C12 + Iareva!C12 + Letan!C12 + 'Mesjan Hyaa'!C12 + Myla!C12 + 'Nheyes Si'!C12 + Onphello!C12 + Quidic!C12 + Shomjind!C12 + 'United Mihili'!C12 + Verste!C12 + Volver!C12 + Wundry!C12 + Yihnurda!C12 + Zhanshe!C12 + Ztesh!C12 -> 1.0146544e+09 | CB12: =((CA12-CA13)/CA13) -> 0.016350825 | CC12: =SUM(CA12/C12) -> 0.16442533
A13: =SUM(B13+250) -> 2004 | B13: 1754 | C13: =Acetoa!C13 + Acrana!C13 + Aetintio!C13 + Ahokini!C13 + Amcha!C13 + Andsaudare!C13 + Anymna!C13 + Aplasia!C13 + Arbiya!C13 + 'Areoix Lie'!C13 + Ashain!C13 + Astye!C13 + Baluyde!C13 + Byllu!C13 + 'Candenat'!C13 + 'Canldives'!C13 + 'Chaenia'!C13 + 'Cloja'!C13 + 'Crila Republic'!C13 + 'Cruthi Anoso'!C13 + 'Curata'!C13 + Dahe!C13 + Danocia!C13 + Darewa!C13 + Desaki!C13 + Deschon!C13 + 'Disal Nila'!C13 + 'Dual Cenryia'!C13 + Ealdorii!C13 + Easuhura!C13 + Eldavpir!C13 + Eldjo!C13 + 'Elja and Munusia'!C13 + Emara!C13 + Enina!C13 + Eparia!C13 + Erkizil!C13 + Estijan!C13 + Etirha!C13 + Etretes!C13 + Exilium!C13 + 'Far Lands'!C13 + 'Feio Lie'!C13 + Fermori!C13 + Finae!C13 + Fincen!C13 + 'Fire Coast'!C13 + Gaeiya!C13 + Galca!C13 + Genaire!C13 + Grazail!C13 + Guise!C13 + Haiza!C13 + Heiso!C13 + Hiwush!C13 + Hkuqo!C13 + Hyelen!C13 + Iainoa!C13 + Iareva!C13 + Ihner!C13 + Ikzen!C13 + Ilicuhe!C13 + Inania!C13 + Inrea!C13 + Iquir!C13 + Isari!C13 + Isnti!C13 + Isuibul!C13 + Jathua!C13 + Jau!C13 + Jshain!C13 + Kaastini!C13 + Koruch!C13 + Kusierna!C13 + Laselteh!C13 + Lasri!C13 + Letan!C13 + Lieri!C13 + Lycroa!C13 + Lydroa!C13 + Maalle!C13 + Mendereide!C13 + 'Merela Sta'!C13 + 'Mesjan Hyaa'!C13 + Metndria!C13 + Migoku!C13 + Myla!C13 + 'New Kizura'!C13 + 'New Misos'!C13 + 'Nheyes Si'!C13 + Nia!C13 + 'Niretui and Anulan'!C13 + 'Niul Spijan'!C13 + 'North Ayre'!C13 + Ocaun!C13 + Ohtina!C13 + Onphello!C13 + Oscairia!C13 + Othya!C13 + Otiiric!C13 + Oyreain!C13 + Ozinia!C13 + Palina!C13 + Peka!C13 + Pelan!C13 + Pelines!C13 + Pelugrotoa!C13 + 'Pha Hii'!C13 + Phuris!C13 + Praesyu!C13 + Prstreula!C13 + 'Pruim Fijan'!C13 + 'Prystr Hii'!C13 + Quidic!C13 + 'Raledria'!C13 + 'Reerica'!C13 + 'Rethern'!C13 + 'Rijan bu'!C13 + 'Rinew'!C13 + 'Rkmepuia'!C13 + 'Rtesania'!C13 + 'Ruylku'!C13 + Saa!C13 + Sadain!C13 + Sanagara!C13 + Sattle!C13 + Selaja!C13 + Seytinemas!C13 + Shinam!C13 + Shomjind!C13 + Siana!C13 + Sivoso!C13 + Slyiaduun!C13 + Stinebar!C13 + Suenan!C13 + Sunsokua!C13 + Taing!C13 + Taniduna!C13 + Taoisia!C13 + Taval!C13 + Terressin!C13 + Tomscilus!C13 + Tonder!C13 + Trevilla!C13 + Trian!C13 + Tvecoca!C13 + Ucrua!C13 + Ukhdari!C13 + Umarcia!C13 + Umendel!C13 + 'United Delet'!C13 + 'United Mihili'!C13 + Urbiqu!C13 + Uularin!C13 + Vayvele!C13 + Veelmit!C13 + Verste!C13 + Verusa!C13 + Vesozata!C13 + Viussi!C13 + Volver!C13 + Walporein!C13 + 'Welenu Fana'!C13 + 'Western Migoku'!C13 + Wundry!C13 + Yaxuto!C13 + Yihnurda!C13 + Yoprioq!C13 + Yutnitu!C13 + Zenashan!C13 + Zhanshe!C13 + Ztesh!C13 -> 6.101944e+09 | D13: =((C13-C14)/C14) -> 0.011388603 | K13: =SUM(L13+250) -> 2004 | L13: 1754 | M13: ='Areoix Lie'!C13 + Pelines!C13 + Terressin!C13 + Taniduna!C13 + Iquir!C13 + Deschon!C13 + Othya!C13 + Eldavpir!C13 + 'Candenat'!C13 + Jau!C13 + Viussi!C13 + Jathua!C13 + Jshain!C13 + Acetoa!C13 + Sattle!C13 + 'Reerica'!C13 + 'Feio Lie'!C13 + Umendel!C13 + 'Fire Coast'!C13 + Yoprioq!C13 + 'Rijan bu'!C13 + Saa!C13 + 'Rinew'!C13 + Enina!C13 + Trevilla!C13 -> 9.2975705e+08 | N13: =((M13-M14)/M14) -> 0.014195686 | O13: =SUM(M13/C13) -> 0.15237063 | V13: =SUM(W13+250) -> 2004 | W13: 1754 | X13: =Aetintio!C13 + Arbiya!C13 + 'Curata'!C13 + 'Disal Nila'!C13 + Etirha!C13 + Fincen!C13 + Gaeiya!C13 + Genaire!C13 + Grazail!C13 + Guise!C13 + Laselteh!C13 + Lasri!C13 + Metndria!C13 + 'New Misos'!C13 + Peka!C13 + Pelan!C13 + Phuris!C13 + 'Raledria'!C13 + Slyiaduun!C13 + Tomscilus!C13 -> 4.6892749e+08 | Y13: =((X13-X14)/X14) -> 0.010314544 | Z13: =SUM(X13/C13) -> 0.076848867 | AG13: =SUM(AH13+250) -> 2004 | AH13: 1754 | AI13: =Acrana!C13 + Danocia!C13 + Darewa!C13 + Ealdorii!C13 + Easuhura!C13 + Eldjo!C13 + Emara!C13 + Estijan!C13 + Fermori!C13 + Ikzen!C13 + Ilicuhe!C13 + Koruch!C13 + Lycroa!C13 + Lydroa!C13 + 'Merela Sta'!C13 + 'New Kizura'!C13 + 'Niul Spijan'!C13 + Palina!C13 + Praesyu!C13 + Siana!C13 + Tonder!C13 + Ukhdari!C13 + Urbiqu!C13 + Uularin!C13 + Verusa!C13 + Yaxuto!C13 + Zenashan!C13 + Hkuqo!C13 -> 9.2837598e+08 | AJ13: =((AI13-AI14)/AI14) -> 0.007042764 | AK13: =SUM(AI13/C13) -> 0.1521443 | AR13: =SUM(AS13+250) -> 2004 | AS13: 1754 | AT13: =Amcha!C13 + Byllu!C13 + 'Chaenia'!C13 + 'Cruthi Anoso'!C13 + 'Dual Cenryia'!C13 + Exilium!C13 + Galca!C13 + Inania!C13 + Inrea!C13 + Isnti!C13 + Lieri!C13 + Ocaun!C13 + Otiiric!C13 + Ozinia!C13 + Pelugrotoa!C13 + 'Rtesania'!C13 + Sadain!C13 + Selaja!C13 + Seytinemas!C13 + Sivoso!C13 + Sunsokua!C13 + Taing!C13 + Taoisia!C13 + Trian!C13 + Vayvele!C13 -> 1.2419506e+09 | AU13: =((AT13-AT14)/AT14) -> 0.010821903 | AV13: =SUM(AT13/C13) -> 0.20353359 | BC13: =SUM(BD13+250) -> 2004 | BD13: 1754 | BE13: ='Canldives'!C13 + 'Cloja'!C13 + Dahe!C13 + Eparia!C13 + Etretes!C13 + Haiza!C13 + Ihner!C13 + Kaastini!C13 + Kusierna!C13 + Migoku!C13 + 'North Ayre'!C13 + Oscairia!C13 + Oyreain!C13 + 'Pha Hii'!C13 + 'Pruim Fijan'!C13 + 'Prystr Hii'!C13 + 'Ruylku'!C13 + Sanagara!C13 + Shinam!C13 + Stinebar!C13 + Suenan!C13 + Taval!C13 + Ucrua!C13 + Vesozata!C13 + 'Welenu Fana'!C13 + 'Western Migoku'!C13 -> 1.2796877e+09 | BF13: =((BE13-BE14)/BE14) -> 0.0085662981 | BG13: =SUM(BE13/C13) -> 0.20971803 | BN13: =SUM(BO13+250) -> 2004 | BO13: 1754 | BP13: =Andsaudare!C13 + Aplasia!C13 + Astye!C13 + 'Crila Republic'!C13 + 'Elja and Munusia'!C13 + Hiwush!C13 + Iainoa!C13 + Isari!C13 + Isuibul!C13 + Maalle!C13 + Mendereide!C13 + Nia!C13 + 'Niretui and Anulan'!C13 + Ohtina!C13 + Prstreula!C13 + 'Rethern'!C13 + 'Rkmepuia'!C13 + Tvecoca!C13 + Umarcia!C13 + 'United Delet'!C13 + Veelmit!C13 + Walporein!C13 + Yutnitu!C13 -> 2.3743538e+08 | BQ13: =((BP13-BP14)/BP14) -> 0.015600214 | BR13: =SUM(BP13/C13) -> 0.038911431 | BY13: =SUM(BZ13+250) -> 2004 | BZ13: 1754 | CA13: =Ahokini!C13 + Anymna!C13 + Ashain!C13 + Baluyde!C13 + Desaki!C13 + Erkizil!C13 + 'Far Lands'!C13 + Finae!C13 + Hyelen!C13 + Iareva!C13 + Letan!C13 + 'Mesjan Hyaa'!C13 + Myla!C13 + 'Nheyes Si'!C13 + Onphello!C13 + Quidic!C13 + Shomjind!C13 + 'United Mihili'!C13 + Verste!C13 + Volver!C13 + Wundry!C13 + Yihnurda!C13 + Zhanshe!C13 + Ztesh!C13 -> 9.9833082e+08 | CB13: =((CA13-CA14)/CA14) -> 0.016647007 | CC13: =SUM(CA13/C13) -> 0.16360865
... A65: =SUM(B65+250) -> 1952 | B65: 1702 | C65: =Acetoa!C65 + Acrana!C65 + Aetintio!C65 + Ahokini!C65 + Amcha!C65 + Andsaudare!C65 + Anymna!C65 + Aplasia!C65 + Arbiya!C65 + 'Areoix Lie'!C65 + Ashain!C65 + Astye!C65 + Baluyde!C65 + Byllu!C65 + 'Candenat'!C65 + 'Canldives'!C65 + 'Chaenia'!C65 + 'Cloja'!C65 + 'Crila Republic'!C65 + 'Cruthi Anoso'!C65 + 'Curata'!C65 + Dahe!C65 + Danocia!C65 + Darewa!C65 + Desaki!C65 + Deschon!C65 + 'Disal Nila'!C65 + 'Dual Cenryia'!C65 + Ealdorii!C65 + Easuhura!C65 + Eldavpir!C65 + Eldjo!C65 + 'Elja and Munusia'!C65 + Emara!C65 + Enina!C65 + Eparia!C65 + Erkizil!C65 + Estijan!C65 + Etirha!C65 + Etretes!C65 + Exilium!C65 + 'Far Lands'!C65 + 'Feio Lie'!C65 + Fermori!C65 + Finae!C65 + Fincen!C65 + 'Fire Coast'!C65 + Gaeiya!C65 + Galca!C65 + Genaire!C65 + Grazail!C65 + Guise!C65 + Haiza!C65 + Heiso!C65 + Hiwush!C65 + Hkuqo!C65 + Hyelen!C65 + Iainoa!C65 + Iareva!C65 + Ihner!C65 + Ikzen!C65 + Ilicuhe!C65 + Inania!C65 + Inrea!C65 + Iquir!C65 + Isari!C65 + Isnti!C65 + Isuibul!C65 + Jathua!C65 + Jau!C65 + Jshain!C65 + Kaastini!C65 + Koruch!C65 + Kusierna!C65 + Laselteh!C65 + Lasri!C65 + Letan!C65 + Lieri!C65 + Lycroa!C65 + Lydroa!C65 + Maalle!C65 + Mendereide!C65 + 'Merela Sta'!C65 + 'Mesjan Hyaa'!C65 + Metndria!C65 + Migoku!C65 + Myla!C65 + 'New Kizura'!C65 + 'New Misos'!C65 + 'Nheyes Si'!C65 + Nia!C65 + 'Niretui and Anulan'!C65 + 'Niul Spijan'!C65 + 'North Ayre'!C65 + Ocaun!C65 + Ohtina!C65 + Onphello!C65 + Oscairia!C65 + Othya!C65 + Otiiric!C65 + Oyreain!C65 + Ozinia!C65 + Palina!C65 + Peka!C65 + Pelan!C65 + Pelines!C65 + Pelugrotoa!C65 + 'Pha Hii'!C65 + Phuris!C65 + Praesyu!C65 + Prstreula!C65 + 'Pruim Fijan'!C65 + 'Prystr Hii'!C65 + Quidic!C65 + 'Raledria'!C65 + 'Reerica'!C65 + 'Rethern'!C65 + 'Rijan bu'!C65 + 'Rinew'!C65 + 'Rkmepuia'!C65 + 'Rtesania'!C65 + 'Ruylku'!C65 + Saa!C65 + Sadain!C65 + Sanagara!C65 + Sattle!C65 + Selaja!C65 + Seytinemas!C65 + Shinam!C65 + Shomjind!C65 + Siana!C65 + Sivoso!C65 + Slyiaduun!C65 + Stinebar!C65 + Suenan!C65 + Sunsokua!C65 + Taing!C65 + Taniduna!C65 + Taoisia!C65 + Taval!C65 + Terressin!C65 + Tomscilus!C65 + Tonder!C65 + Trevilla!C65 + Trian!C65 + Tvecoca!C65 + Ucrua!C65 + Ukhdari!C65 + Umarcia!C65 + Umendel!C65 + 'United Delet'!C65 + 'United Mihili'!C65 + Urbiqu!C65 + Uularin!C65 + Vayvele!C65 + Veelmit!C65 + Verste!C65 + Verusa!C65 + Vesozata!C65 + Viussi!C65 + Volver!C65 + Walporein!C65 + 'Welenu Fana'!C65 + 'Western Migoku'!C65 + Wundry!C65 + Yaxuto!C65 + Yihnurda!C65 + Yoprioq!C65 + Yutnitu!C65 + Zenashan!C65 + Zhanshe!C65 + Ztesh!C65 -> 2.6121848e+09 | D65: =((C65-C66)/C66) -> 0.019026534 | K65: =SUM(L65+250) -> 1952 | L65: 1702 | M65: ='Areoix Lie'!C65 + Pelines!C65 + Terressin!C65 + Taniduna!C65 + Iquir!C65 + Deschon!C65 + Othya!C65 + Eldavpir!C65 + 'Candenat'!C65 + Jau!C65 + Viussi!C65 + Jathua!C65 + Jshain!C65 + Acetoa!C65 + Sattle!C65 + 'Reerica'!C65 + 'Feio Lie'!C65 + Umendel!C65 + 'Fire Coast'!C65 + Yoprioq!C65 + 'Rijan bu'!C65 + Saa!C65 + 'Rinew'!C65 + Enina!C65 + Trevilla!C65 -> 3.4121689e+08 | N65: =((M65-M66)/M66) -> 0.024808578 | O65: =SUM(M65/C65) -> 0.13062509 | V65: =SUM(W65+250) -> 1952 | W65: 1702 | X65: =Aetintio!C65 + Arbiya!C65 + 'Curata'!C65 + 'Disal Nila'!C65 + Etirha!C65 + Fincen!C65 + Gaeiya!C65 + Genaire!C65 + Grazail!C65 + Guise!C65 + Laselteh!C65 + Lasri!C65 + Metndria!C65 + 'New Misos'!C65 + Peka!C65 + Pelan!C65 + Phuris!C65 + 'Raledria'!C65 + Slyiaduun!C65 + Tomscilus!C65 -> 2.0918211e+08 | Y65: =((X65-X66)/X66) -> 0.021779136 | Z65: =SUM(X65/C65) -> 0.080079368 | AG65: =SUM(AH65+250) -> 1952 | AH65: 1702 | AI65: =Acrana!C65 + Danocia!C65 + Darewa!C65 + Ealdorii!C65 + Easuhura!C65 + Eldjo!C65 + Emara!C65 + Estijan!C65 + Fermori!C65 + Ikzen!C65 + Ilicuhe!C65 + Koruch!C65 + Lycroa!C65 + Lydroa!C65 + 'Merela Sta'!C65 + 'New Kizura'!C65 + 'Niul Spijan'!C65 + Palina!C65 + Praesyu!C65 + Siana!C65 + Tonder!C65 + Ukhdari!C65 + Urbiqu!C65 + Uularin!C65 + Verusa!C65 + Yaxuto!C65 + Zenashan!C65 + Hkuqo!C65 -> 5.7932469e+08 | AJ65: =((AI65-AI66)/AI66) -> 0.011446248 | AK65: =SUM(AI65/C65) -> 0.22177783 | AR65: =SUM(AS65+250) -> 1952 | AS65: 1702 | AT65: =Amcha!C65 + Byllu!C65 + 'Chaenia'!C65 + 'Cruthi Anoso'!C65 + 'Dual Cenryia'!C65 + Exilium!C65 + Galca!C65 + Inania!C65 + Inrea!C65 + Isnti!C65 + Lieri!C65 + Ocaun!C65 + Otiiric!C65 + Ozinia!C65 + Pelugrotoa!C65 + 'Rtesania'!C65 + Sadain!C65 + Selaja!C65 + Seytinemas!C65 + Sivoso!C65 + Sunsokua!C65 + Taing!C65 + Taoisia!C65 + Trian!C65 + Vayvele!C65 -> 4.0379568e+08 | AU65: =((AT65-AT66)/AT66) -> 0.028456517 | AV65: =SUM(AT65/C65) -> 0.15458159 | BC65: =SUM(BD65+250) -> 1952 | BD65: 1702 | BE65: ='Canldives'!C65 + 'Cloja'!C65 + Dahe!C65 + Eparia!C65 + Etretes!C65 + Haiza!C65 + Ihner!C65 + Kaastini!C65 + Kusierna!C65 + Migoku!C65 + 'North Ayre'!C65 + Oscairia!C65 + Oyreain!C65 + 'Pha Hii'!C65 + 'Pruim Fijan'!C65 + 'Prystr Hii'!C65 + 'Ruylku'!C65 + Sanagara!C65 + Shinam!C65 + Stinebar!C65 + Suenan!C65 + Taval!C65 + Ucrua!C65 + Vesozata!C65 + 'Welenu Fana'!C65 + 'Western Migoku'!C65 -> 6.6159125e+08 | BF65: =((BE65-BE66)/BE66) -> 0.015560671 | BG65: =SUM(BE65/C65) -> 0.25327123 | BN65: =SUM(BO65+250) -> 1952 | BO65: 1702 | BP65: =Andsaudare!C65 + Aplasia!C65 + Astye!C65 + 'Crila Republic'!C65 + 'Elja and Munusia'!C65 + Hiwush!C65 + Iainoa!C65 + Isari!C65 + Isuibul!C65 + Maalle!C65 + Mendereide!C65 + Nia!C65 + 'Niretui and Anulan'!C65 + Ohtina!C65 + Prstreula!C65 + 'Rethern'!C65 + 'Rkmepuia'!C65 + Tvecoca!C65 + Umarcia!C65 + 'United Delet'!C65 + Veelmit!C65 + Walporein!C65 + Yutnitu!C65 -> 81662971 | BQ65: =((BP65-BP66)/BP66) -> 0.019744095 | BR65: =SUM(BP65/C65) -> 0.031262325 | BY65: =SUM(BZ65+250) -> 1952 | BZ65: 1702 | CA65: =Ahokini!C65 + Anymna!C65 + Ashain!C65 + Baluyde!C65 + Desaki!C65 + Erkizil!C65 + 'Far Lands'!C65 + Finae!C65 + Hyelen!C65 + Iareva!C65 + Letan!C65 + 'Mesjan Hyaa'!C65 + Myla!C65 + 'Nheyes Si'!C65 + Onphello!C65 + Quidic!C65 + Shomjind!C65 + 'United Mihili'!C65 + Verste!C65 + Volver!C65 + Wundry!C65 + Yihnurda!C65 + Zhanshe!C65 + Ztesh!C65 -> 3.2992053e+08 | CB65: =((CA65-CA66)/CA66) -> 0.01992269 | CC65: =SUM(CA65/C65) -> 0.12630061
A66: =SUM(B66+250) -> 1951 | B66: 1701 | C66: =Acetoa!C66 + Acrana!C66 + Aetintio!C66 + Ahokini!C66 + Amcha!C66 + Andsaudare!C66 + Anymna!C66 + Aplasia!C66 + Arbiya!C66 + 'Areoix Lie'!C66 + Ashain!C66 + Astye!C66 + Baluyde!C66 + Byllu!C66 + 'Candenat'!C66 + 'Canldives'!C66 + 'Chaenia'!C66 + 'Cloja'!C66 + 'Crila Republic'!C66 + 'Cruthi Anoso'!C66 + 'Curata'!C66 + Dahe!C66 + Danocia!C66 + Darewa!C66 + Desaki!C66 + Deschon!C66 + 'Disal Nila'!C66 + 'Dual Cenryia'!C66 + Ealdorii!C66 + Easuhura!C66 + Eldavpir!C66 + Eldjo!C66 + 'Elja and Munusia'!C66 + Emara!C66 + Enina!C66 + Eparia!C66 + Erkizil!C66 + Estijan!C66 + Etirha!C66 + Etretes!C66 + Exilium!C66 + 'Far Lands'!C66 + 'Feio Lie'!C66 + Fermori!C66 + Finae!C66 + Fincen!C66 + 'Fire Coast'!C66 + Gaeiya!C66 + Galca!C66 + Genaire!C66 + Grazail!C66 + Guise!C66 + Haiza!C66 + Heiso!C66 + Hiwush!C66 + Hkuqo!C66 + Hyelen!C66 + Iainoa!C66 + Iareva!C66 + Ihner!C66 + Ikzen!C66 + Ilicuhe!C66 + Inania!C66 + Inrea!C66 + Iquir!C66 + Isari!C66 + Isnti!C66 + Isuibul!C66 + Jathua!C66 + Jau!C66 + Jshain!C66 + Kaastini!C66 + Koruch!C66 + Kusierna!C66 + Laselteh!C66 + Lasri!C66 + Letan!C66 + Lieri!C66 + Lycroa!C66 + Lydroa!C66 + Maalle!C66 + Mendereide!C66 + 'Merela Sta'!C66 + 'Mesjan Hyaa'!C66 + Metndria!C66 + Migoku!C66 + Myla!C66 + 'New Kizura'!C66 + 'New Misos'!C66 + 'Nheyes Si'!C66 + Nia!C66 + 'Niretui and Anulan'!C66 + 'Niul Spijan'!C66 + 'North Ayre'!C66 + Ocaun!C66 + Ohtina!C66 + Onphello!C66 + Oscairia!C66 + Othya!C66 + Otiiric!C66 + Oyreain!C66 + Ozinia!C66 + Palina!C66 + Peka!C66 + Pelan!C66 + Pelines!C66 + Pelugrotoa!C66 + 'Pha Hii'!C66 + Phuris!C66 + Praesyu!C66 + Prstreula!C66 + 'Pruim Fijan'!C66 + 'Prystr Hii'!C66 + Quidic!C66 + 'Raledria'!C66 + 'Reerica'!C66 + 'Rethern'!C66 + 'Rijan bu'!C66 + 'Rinew'!C66 + 'Rkmepuia'!C66 + 'Rtesania'!C66 + 'Ruylku'!C66 + Saa!C66 + Sadain!C66 + Sanagara!C66 + Sattle!C66 + Selaja!C66 + Seytinemas!C66 + Shinam!C66 + Shomjind!C66 + Siana!C66 + Sivoso!C66 + Slyiaduun!C66 + Stinebar!C66 + Suenan!C66 + Sunsokua!C66 + Taing!C66 + Taniduna!C66 + Taoisia!C66 + Taval!C66 + Terressin!C66 + Tomscilus!C66 + Tonder!C66 + Trevilla!C66 + Trian!C66 + Tvecoca!C66 + Ucrua!C66 + Ukhdari!C66 + Umarcia!C66 + Umendel!C66 + 'United Delet'!C66 + 'United Mihili'!C66 + Urbiqu!C66 + Uularin!C66 + Vayvele!C66 + Veelmit!C66 + Verste!C66 + Verusa!C66 + Vesozata!C66 + Viussi!C66 + Volver!C66 + Walporein!C66 + 'Welenu Fana'!C66 + 'Western Migoku'!C66 + Wundry!C66 + Yaxuto!C66 + Yihnurda!C66 + Yoprioq!C66 + Yutnitu!C66 + Zenashan!C66 + Zhanshe!C66 + Ztesh!C66 -> 2.563412e+09 | D66: =((C66-C67)/$C$67) -> 0.018715995 | K66: =SUM(L66+250) -> 1951 | L66: 1701 | M66: ='Areoix Lie'!C66 + Pelines!C66 + Terressin!C66 + Taniduna!C66 + Iquir!C66 + Deschon!C66 + Othya!C66 + Eldavpir!C66 + 'Candenat'!C66 + Jau!C66 + Viussi!C66 + Jathua!C66 + Jshain!C66 + Acetoa!C66 + Sattle!C66 + 'Reerica'!C66 + 'Feio Lie'!C66 + Umendel!C66 + 'Fire Coast'!C66 + Yoprioq!C66 + 'Rijan bu'!C66 + Saa!C66 + 'Rinew'!C66 + Enina!C66 + Trevilla!C66 -> 3.329567e+08 | O66: =SUM(M66/C66) -> 0.1298881 | V66: =SUM(W66+250) -> 1951 | W66: 1701 | X66: =Aetintio!C66 + Arbiya!C66 + 'Curata'!C66 + 'Disal Nila'!C66 + Etirha!C66 + Fincen!C66 + Gaeiya!C66 + Genaire!C66 + Grazail!C66 + Guise!C66 + Laselteh!C66 + Lasri!C66 + Metndria!C66 + 'New Misos'!C66 + Peka!C66 + Pelan!C66 + Phuris!C66 + 'Raledria'!C66 + Slyiaduun!C66 + Tomscilus!C66 -> 2.0472341e+08 | Z66: =SUM(X66/C66) -> 0.07986364 | AG66: =SUM(AH66+250) -> 1951 | AH66: 1701 | AI66: =Acrana!C66 + Danocia!C66 + Darewa!C66 + Ealdorii!C66 + Easuhura!C66 + Eldjo!C66 + Emara!C66 + Estijan!C66 + Fermori!C66 + Ikzen!C66 + Ilicuhe!C66 + Koruch!C66 + Lycroa!C66 + Lydroa!C66 + 'Merela Sta'!C66 + 'New Kizura'!C66 + 'Niul Spijan'!C66 + Palina!C66 + Praesyu!C66 + Siana!C66 + Tonder!C66 + Ukhdari!C66 + Urbiqu!C66 + Uularin!C66 + Verusa!C66 + Yaxuto!C66 + Zenashan!C66 + Hkuqo!C66 -> 5.7276863e+08 | AK66: =SUM(AI66/C66) -> 0.22343995 | AR66: =SUM(AS66+250) -> 1951 | AS66: 1701 | AT66: =Amcha!C66 + Byllu!C66 + 'Chaenia'!C66 + 'Cruthi Anoso'!C66 + 'Dual Cenryia'!C66 + Exilium!C66 + Galca!C66 + Inania!C66 + Inrea!C66 + Isnti!C66 + Lieri!C66 + Ocaun!C66 + Otiiric!C66 + Ozinia!C66 + Pelugrotoa!C66 + 'Rtesania'!C66 + Sadain!C66 + Selaja!C66 + Seytinemas!C66 + Sivoso!C66 + Sunsokua!C66 + Taing!C66 + Taoisia!C66 + Trian!C66 + Vayvele!C66 -> 3.92623e+08 | AV66: =SUM(AT66/C66) -> 0.15316422 | BC66: =SUM(BD66+250) -> 1951 | BD66: 1701 | BE66: ='Canldives'!C66 + 'Cloja'!C66 + Dahe!C66 + Eparia!C66 + Etretes!C66 + Haiza!C66 + Ihner!C66 + Kaastini!C66 + Kusierna!C66 + Migoku!C66 + 'North Ayre'!C66 + Oscairia!C66 + Oyreain!C66 + 'Pha Hii'!C66 + 'Pruim Fijan'!C66 + 'Prystr Hii'!C66 + 'Ruylku'!C66 + Sanagara!C66 + Shinam!C66 + Stinebar!C66 + Suenan!C66 + Taval!C66 + Ucrua!C66 + Vesozata!C66 + 'Welenu Fana'!C66 + 'Western Migoku'!C66 -> 6.5145419e+08 | BG66: =SUM(BE66/C66) -> 0.25413558 | BN66: =SUM(BO66+250) -> 1951 | BO66: 1701 | BP66: =Andsaudare!C66 + Aplasia!C66 + Astye!C66 + 'Crila Republic'!C66 + 'Elja and Munusia'!C66 + Hiwush!C66 + Iainoa!C66 + Isari!C66 + Isuibul!C66 + Maalle!C66 + Mendereide!C66 + Nia!C66 + 'Niretui and Anulan'!C66 + Ohtina!C66 + Prstreula!C66 + 'Rethern'!C66 + 'Rkmepuia'!C66 + Tvecoca!C66 + Umarcia!C66 + 'United Delet'!C66 + Veelmit!C66 + Walporein!C66 + Yutnitu!C66 -> 80081828 | BR66: =SUM(BP66/C66) -> 0.031240327 | BY66: =SUM(BZ66+250) -> 1951 | BZ66: 1701 | CA66: =Ahokini!C66 + Anymna!C66 + Ashain!C66 + Baluyde!C66 + Desaki!C66 + Erkizil!C66 + 'Far Lands'!C66 + Finae!C66 + Hyelen!C66 + Iareva!C66 + Letan!C66 + 'Mesjan Hyaa'!C66 + Myla!C66 + 'Nheyes Si'!C66 + Onphello!C66 + Quidic!C66 + Shomjind!C66 + 'United Mihili'!C66 + Verste!C66 + Volver!C66 + Wundry!C66 + Yihnurda!C66 + Zhanshe!C66 + Ztesh!C66 -> 3.2347601e+08 | CC66: =SUM(CA66/C66) -> 0.12618963
A67: =SUM(B67+250) -> 1950 | B67: 1700 | C67: =Acetoa!C67 + Acrana!C67 + Aetintio!C67 + Ahokini!C67 + Amcha!C67 + Andsaudare!C67 + Anymna!C67 + Aplasia!C67 + Arbiya!C67 + 'Areoix Lie'!C67 + Ashain!C67 + Astye!C67 + Baluyde!C67 + Byllu!C67 + 'Candenat'!C67 + 'Canldives'!C67 + 'Chaenia'!C67 + 'Cloja'!C67 + 'Crila Republic'!C67 + 'Cruthi Anoso'!C67 + 'Curata'!C67 + Dahe!C67 + Danocia!C67 + Darewa!C67 + Desaki!C67 + Deschon!C67 + 'Disal Nila'!C67 + 'Dual Cenryia'!C67 + Ealdorii!C67 + Easuhura!C67 + Eldavpir!C67 + Eldjo!C67 + 'Elja and Munusia'!C67 + Emara!C67 + Enina!C67 + Eparia!C67 + Erkizil!C67 + Estijan!C67 + Etirha!C67 + Etretes!C67 + Exilium!C67 + 'Far Lands'!C67 + 'Feio Lie'!C67 + Fermori!C67 + Finae!C67 + Fincen!C67 + 'Fire Coast'!C67 + Gaeiya!C67 + Galca!C67 + Genaire!C67 + Grazail!C67 + Guise!C67 + Haiza!C67 + Heiso!C67 + Hiwush!C67 + Hkuqo!C67 + Hyelen!C67 + Iainoa!C67 + Iareva!C67 + Ihner!C67 + Ikzen!C67 + Ilicuhe!C67 + Inania!C67 + Inrea!C67 + Iquir!C67 + Isari!C67 + Isnti!C67 + Isuibul!C67 + Jathua!C67 + Jau!C67 + Jshain!C67 + Kaastini!C67 + Koruch!C67 + Kusierna!C67 + Laselteh!C67 + Lasri!C67 + Letan!C67 + Lieri!C67 + Lycroa!C67 + Lydroa!C67 + Maalle!C67 + Mendereide!C67 + 'Merela Sta'!C67 + 'Mesjan Hyaa'!C67 + Metndria!C67 + Migoku!C67 + Myla!C67 + 'New Kizura'!C67 + 'New Misos'!C67 + 'Nheyes Si'!C67 + Nia!C67 + 'Niretui and Anulan'!C67 + 'Niul Spijan'!C67 + 'North Ayre'!C67 + Ocaun!C67 + Ohtina!C67 + Onphello!C67 + Oscairia!C67 + Othya!C67 + Otiiric!C67 + Oyreain!C67 + Ozinia!C67 + Palina!C67 + Peka!C67 + Pelan!C67 + Pelines!C67 + Pelugrotoa!C67 + 'Pha Hii'!C67 + Phuris!C67 + Praesyu!C67 + Prstreula!C67 + 'Pruim Fijan'!C67 + 'Prystr Hii'!C67 + Quidic!C67 + 'Raledria'!C67 + 'Reerica'!C67 + 'Rethern'!C67 + 'Rijan bu'!C67 + 'Rinew'!C67 + 'Rkmepuia'!C67 + 'Rtesania'!C67 + 'Ruylku'!C67 + Saa!C67 + Sadain!C67 + Sanagara!C67 + Sattle!C67 + Selaja!C67 + Seytinemas!C67 + Shinam!C67 + Shomjind!C67 + Siana!C67 + Sivoso!C67 + Slyiaduun!C67 + Stinebar!C67 + Suenan!C67 + Sunsokua!C67 + Taing!C67 + Taniduna!C67 + Taoisia!C67 + Taval!C67 + Terressin!C67 + Tomscilus!C67 + Tonder!C67 + Trevilla!C67 + Trian!C67 + Tvecoca!C67 + Ucrua!C67 + Ukhdari!C67 + Umarcia!C67 + Umendel!C67 + 'United Delet'!C67 + 'United Mihili'!C67 + Urbiqu!C67 + Uularin!C67 + Vayvele!C67 + Veelmit!C67 + Verste!C67 + Verusa!C67 + Vesozata!C67 + Viussi!C67 + Volver!C67 + Walporein!C67 + 'Welenu Fana'!C67 + 'Western Migoku'!C67 + Wundry!C67 + Yaxuto!C67 + Yihnurda!C67 + Yoprioq!C67 + Yutnitu!C67 + Zenashan!C67 + Zhanshe!C67 + Ztesh!C67 -> 2.5163166e+09 | D67: 0.0194 | K67: =SUM(L67+250) -> 1950 | L67: 1700 | M67: ='Areoix Lie'!C67 + Pelines!C67 + Terressin!C67 + Taniduna!C67 + Iquir!C67 + Deschon!C67 + Othya!C67 + Eldavpir!C67 + 'Candenat'!C67 + Jau!C67 + Viussi!C67 + Jathua!C67 + Jshain!C67 + Acetoa!C67 + Sattle!C67 + 'Reerica'!C67 + 'Feio Lie'!C67 + Umendel!C67 + 'Fire Coast'!C67 + Yoprioq!C67 + 'Rijan bu'!C67 + Saa!C67 + 'Rinew'!C67 + Enina!C67 + Trevilla!C67 -> 324907011 | O67: =SUM(M67/C67) -> 0.12912008 | V67: =SUM(W67+250) -> 1950 | W67: 1700 | X67: =Aetintio!C67 + Arbiya!C67 + 'Curata'!C67 + 'Disal Nila'!C67 + Etirha!C67 + Fincen!C67 + Gaeiya!C67 + Genaire!C67 + Grazail!C67 + Guise!C67 + Laselteh!C67 + Lasri!C67 + Metndria!C67 + 'New Misos'!C67 + Peka!C67 + Pelan!C67 + Phuris!C67 + 'Raledria'!C67 + Slyiaduun!C67 + Tomscilus!C67 -> 200253995 | Z67: =SUM(X67/C67) -> 0.079582194 | AG67: =SUM(AH67+250) -> 1950 | AH67: 1700 | AI67: =Acrana!C67 + Danocia!C67 + Darewa!C67 + Ealdorii!C67 + Easuhura!C67 + Eldjo!C67 + Emara!C67 + Estijan!C67 + Fermori!C67 + Ikzen!C67 + Ilicuhe!C67 + Koruch!C67 + Lycroa!C67 + Lydroa!C67 + 'Merela Sta'!C67 + 'New Kizura'!C67 + 'Niul Spijan'!C67 + Palina!C67 + Praesyu!C67 + Siana!C67 + Tonder!C67 + Ukhdari!C67 + Urbiqu!C67 + Uularin!C67 + Verusa!C67 + Yaxuto!C67 + Zenashan!C67 + Hkuqo!C67 -> 566655831 | AK67: =SUM(AI67/C67) -> 0.22519258 | AR67: =SUM(AS67+250) -> 1950 | AS67: 1700 | AT67: =Amcha!C67 + Byllu!C67 + 'Chaenia'!C67 + 'Cruthi Anoso'!C67 + 'Dual Cenryia'!C67 + Exilium!C67 + Galca!C67 + Inania!C67 + Inrea!C67 + Isnti!C67 + Lieri!C67 + Ocaun!C67 + Otiiric!C67 + Ozinia!C67 + Pelugrotoa!C67 + 'Rtesania'!C67 + Sadain!C67 + Selaja!C67 + Seytinemas!C67 + Sivoso!C67 + Sunsokua!C67 + Taing!C67 + Taoisia!C67 + Trian!C67 + Vayvele!C67 -> 381997123 | AV67: =SUM(AT67/C67) -> 0.15180805 | BC67: =SUM(BD67+250) -> 1950 | BD67: 1700 | BE67: ='Canldives'!C67 + 'Cloja'!C67 + Dahe!C67 + Eparia!C67 + Etretes!C67 + Haiza!C67 + Ihner!C67 + Kaastini!C67 + Kusierna!C67 + Migoku!C67 + 'North Ayre'!C67 + Oscairia!C67 + Oyreain!C67 + 'Pha Hii'!C67 + 'Pruim Fijan'!C67 + 'Prystr Hii'!C67 + 'Ruylku'!C67 + Sanagara!C67 + Shinam!C67 + Stinebar!C67 + Suenan!C67 + Taval!C67 + Ucrua!C67 + Vesozata!C67 + 'Welenu Fana'!C67 + 'Western Migoku'!C67 -> 6.4143497e+08 | BG67: =SUM(BE67/C67) -> 0.25491028 | BN67: =SUM(BO67+250) -> 1950 | BO67: 1700 | BP67: =Andsaudare!C67 + Aplasia!C67 + Astye!C67 + 'Crila Republic'!C67 + 'Elja and Munusia'!C67 + Hiwush!C67 + Iainoa!C67 + Isari!C67 + Isuibul!C67 + Maalle!C67 + Mendereide!C67 + Nia!C67 + 'Niretui and Anulan'!C67 + Ohtina!C67 + Prstreula!C67 + 'Rethern'!C67 + 'Rkmepuia'!C67 + Tvecoca!C67 + Umarcia!C67 + 'United Delet'!C67 + Veelmit!C67 + Walporein!C67 + Yutnitu!C67 -> 78646235 | BR67: =SUM(BP67/C67) -> 0.031254507 | BY67: =SUM(BZ67+250) -> 1950 | BZ67: 1700 | CA67: =Ahokini!C67 + Anymna!C67 + Ashain!C67 + Baluyde!C67 + Desaki!C67 + Erkizil!C67 + 'Far Lands'!C67 + Finae!C67 + Hyelen!C67 + Iareva!C67 + Letan!C67 + 'Mesjan Hyaa'!C67 + Myla!C67 + 'Nheyes Si'!C67 + Onphello!C67 + Quidic!C67 + Shomjind!C67 + 'United Mihili'!C67 + Verste!C67 + Volver!C67 + Wundry!C67 + Yihnurda!C67 + Zhanshe!C67 + Ztesh!C67 -> 317248432 | CC67: =SUM(CA67/C67) -> 0.12607652

Sheet Geoscheme Population
A1: E | B1: A | C1: Middle Acrolan Population | D1: Middle Acrola Population Growth | K1: E | L1: A | M1: Middle Acrolan Population | N1: Middle Acrolan Population Growth | O1: % of World | V1: E | W1: A | X1: North Acrolan Population | Y1: North Acrolan Population Growth | Z1: % of World | AG1: E | AH1: A | AI1: South Acrolan Population | AJ1: South Acrolan Population Growth | AK1: % of World | AR1: E | AS1: A | AT1: Central Atirhan Population | AU1: Central Atirhan Population Growth | AV1: % of World | BC1: E | BD1: A | BE1: East Atirhan Population | BF1: East Atirhan Population Growth | BG1: % of World | BN1: E | BO1: A | BP1: West Atirhan Population | BQ1: West Atirhan Population Growth | BR1: % of World | BY1: E | BZ1: A | CA1: Central Ayuman Population | CB1: Central Ayuman | CC1: % of World | CJ1: E | CK1: A | CL1: North Ayuman Population | CM1: North Ayuman Population Growth | CN1: % of World | CU1: E | CV1: A | CW1: South Ayuman Population | CX1: South Ayuman Population Growth | CY1: % of World | DF1: E | DG1: A | DH1: West Ayuman Population | DI1: West Ayuman Population Growth | DJ1: % of World | DQ1: E | DR1: A | DS1: East Mahean Population | DT1: East Mahean Population Growth | DU1: % of World | EB1: E | EC1: A | ED1: North Mahean Population | EE1: North Mahean Population Growth | EF1: % of World | EM1: E | EN1: A | EO1: South Mahean Population | EP1: South Mahean Population Growth | EQ1: % of World | EX1: E | EY1: A | EZ1: West Mahean Population | FA1: West Mahean Population Growth | FB1: % of World | FI1: E | FJ1: A | FK1: North Massiran Population | FL1: North Massiran Population Growth | FM1: % of World | FT1: E | FU1: A | FV1: South Massiran Population | FW1: South Massiran Population Growth | FX1: % of World | GE1: E | GF1: A | GG1: West Massiran Population | GH1: West Massiran Growth | GI1: % of World | GP1: E | GQ1: A | GR1: North New Ayren Population | GS1: North New Ayren Population Growth | GT1: % of World | HA1: E | HB1: A | HC1: South New Ayren Population | HD1: South New Ayren Population Growth | HE1: % of World | HL1: E | HM1: A | HN1: East Quian Population | HO1: East Quian Population Growth | HP1: % of World | HW1: E | HX1: A | HY1: North Quian Population | HZ1: North Quian Population Growth | IA1: % of World | IH1: E | II1: A | IJ1: South Quian Population | IK1: South Quian Population Growth | IL1: % of World | IS1: E | IT1: A | IU1: West Quian Population | IV1: West Quian Population Growth | IW1: % of World
A2: =SUM(B2+250) -> 2015 | B2: 1765 | C2: =Acetoa!C2 + Acrana!C2 + Aetintio!C2 + Ahokini!C2 + Amcha!C2 + Andsaudare!C2 + Anymna!C2 + Aplasia!C2 + Arbiya!C2 + 'Areoix Lie'!C2 + Ashain!C2 + Astye!C2 + Baluyde!C2 + Byllu!C2 + 'Candenat'!C2 + 'Canldives'!C2 + 'Chaenia'!C2 + 'Cloja'!C2 + 'Crila Republic'!C2 + 'Cruthi Anoso'!C2 + 'Curata'!C2 + Dahe!C2 + Danocia!C2 + Darewa!C2 + Desaki!C2 + Deschon!C2 + 'Disal Nila'!C2 + 'Dual Cenryia'!C2 + Ealdorii!C2 + Easuhura!C2 + Eldavpir!C2 + Eldjo!C2 + 'Elja and Munusia'!C2 + Emara!C2 + Enina!C2 + Eparia!C2 + Erkizil!C2 + Estijan!C2 + Etirha!C2 + Etretes!C2 + Exilium!C2 + 'Far Lands'!C2 + 'Feio Lie'!C2 + Fermori!C2 + Finae!C2 + Fincen!C2 + 'Fire Coast'!C2 + Gaeiya!C2 + Galca!C2 + Genaire!C2 + Grazail!C2 + Guise!C2 + Haiza!C2 + Heiso!C2 + Hiwush!C2 + Hkuqo!C2 + Hyelen!C2 + Iainoa!C2 + Iareva!C2 + Ihner!C2 + Ikzen!C2 + Ilicuhe!C2 + Inania!C2 + Inrea!C2 + Iquir!C2 + Isari!C2 + Isnti!C2 + Isuibul!C2 + Jathua!C2 + Jau!C2 + Jshain!C2 + Kaastini!C2 + Koruch!C2 + Kusierna!C2 + Laselteh!C2 + Lasri!C2 + Letan!C2 + Lieri!C2 + Lycroa!C2 + Lydroa!C2 + Maalle!C2 + Mendereide!C2 + 'Merela Sta'!C2 + 'Mesjan Hyaa'!C2 + Metndria!C2 + Migoku!C2 + Myla!C2 + 'New Kizura'!C2 + 'New Misos'!C2 + 'Nheyes Si'!C2 + Nia!C2 + 'Niretui and Anulan'!C2 + 'Niul Spijan'!C2 + 'North Ayre'!C2 + Ocaun!C2 + Ohtina!C2 + Onphello!C2 + Oscairia!C2 + Othya!C2 + Otiiric!C2 + Oyreain!C2 + Ozinia!C2 + Palina!C2 + Peka!C2 + Pelan!C2 + Pelines!C2 + Pelugrotoa!C2 + 'Pha Hii'!C2 + Phuris!C2 + Praesyu!C2 + Prstreula!C2 + 'Pruim Fijan'!C2 + 'Prystr Hii'!C2 + Quidic!C2 + 'Raledria'!C2 + 'Reerica'!C2 + 'Rethern'!C2 + 'Rijan bu'!C2 + 'Rinew'!C2 + 'Rkmepuia'!C2 + 'Rtesania'!C2 + 'Ruylku'!C2 + Saa!C2 + Sadain!C2 + Sanagara!C2 + Sattle!C2 + Selaja!C2 + Seytinemas!C2 + Shinam!C2 + Shomjind!C2 + Siana!C2 + Sivoso!C2 + Slyiaduun!C2 + Stinebar!C2 + Suenan!C2 + Sunsokua!C2 + Taing!C2 + Taniduna!C2 + Taoisia!C2 + Taval!C2 + Terressin!C2 + Tomscilus!C2 + Tonder!C2 + Trevilla!C2 + Trian!C2 + Tvecoca!C2 + Ucrua!C2 + Ukhdari!C2 + Umarcia!C2 + Umendel!C2 + 'United Delet'!C2 + 'United Mihili'!C2 + Urbiqu!C2 + Uularin!C2 + Vayvele!C2 + Veelmit!C2 + Verste!C2 + Verusa!C2 + Vesozata!C2 + Viussi!C2 + Volver!C2 + Walporein!C2 + 'Welenu Fana'!C2 + 'Western Migoku'!C2 + Wundry!C2 + Yaxuto!C2 + Yihnurda!C2 + Yoprioq!C2 + Yutnitu!C2 + Zenashan!C2 + Zhanshe!C2 + Ztesh!C2 -> 6.8491801e+09 | D2: =((C2-C3)/C3) -> 0.0096461647 | K2: =SUM(L2+250) -> 2015 | L2: 1765 | M2: =Eldavpir!C2 + Iquir!C2 + Viussi!C2 + Umendel!C2 + 'Reerica'!C2 + Saa!C2 + Sattle!C2 -> 1.1136387e+08 | N2: =((M2-M3)/M3) -> 0.022701352 | O2: =SUM(M2/C2) -> 0.016259445 | V2: =SUM(W2+250) -> 2015 | W2: 1765 | X2: ='Areoix Lie'!C2 + Jau!C2 + Terressin!C2 + Acetoa!C2 + 'Feio Lie'!C2 -> 6.9521408e+08 | Y2: =((X2-X3)/X3) -> 0.0045685788 | Z2: =SUM(X2/C2) -> 0.10150326 | AG2: =SUM(AH2+250) -> 2015 | AH2: 1765 | AI2: =Taniduna!C2 + Jathua!C2 + Deschon!C2 + Pelines!C2 + 'Candenat'!C2 + Othya!C2 + Yoprioq!C2 + Jshain!C2 + 'Fire Coast'!C2 + 'Rijan bu'!C2 + 'Rinew'!C2 + Enina!C2 + Trevilla!C2 -> 2.6349019e+08 | AJ2: =((AI2-AI3)/AI3) -> 0.027423403 | AK2: =SUM(AI2/C2) -> 0.038470325 | AR2: =SUM(AS2+250) -> 2015 | AS2: 1765 | AT2: =Gaeiya!C2 + 'Raledria'!C2 + Arbiya!C2 + Fincen!C2 + 'Curata'!C2 -> 3.2638136e+08 | AU2: =((AT2-AT3)/AT3) -> 0.013689917 | AV2: =SUM(AT2/C2) -> 0.047652617 | BC2: =SUM(BD2+250) -> 2015 | BD2: 1765 | BE2: =Etirha!C2 + Laselteh!C2 + Grazail!C2 + 'Disal Nila'!C2 + Pelan!C2 + Peka!C2 + Guise!C2 -> 1.0730611e+08 | BF2: =((BE2-BE3)/BE3) -> 0.0044523595 | BG2: =SUM(BE2/C2) -> 0.015667001 | BN2: =SUM(BO2+250) -> 2015 | BO2: 1765 | BP2: =Genaire!C2 + 'New Misos'!C2 + Phuris!C2 + Lasri!C2 + Slyiaduun!C2 + Aetintio!C2 + Metndria!C2 + Tomscilus!C2 -> 1.0375034e+08 | BQ2: =((BP2-BP3)/BP3) -> 0.010148464 | BR2: =SUM(BP2/C2) -> 0.015147849 | BY2: =SUM(BZ2+250) -> 2015 | BZ2: 1765 | CA2: =Ealdorii!C2 + Ukhdari!C2 + Hkuqo!C2 + Acrana!C2 + Zenashan!C2 -> 2.7079713e+08 | CB2: =((CA2-CA3)/CA3) -> 0.005626408 | CC2: =SUM(CA2/C2) -> 0.03953716 | CJ2: =SUM(CK2+250) -> 2015 | CK2: 1765 | CL2: =Estijan!C2 + Ikzen!C2 + Urbiqu!C2 + Danocia!C2 + Koruch!C2 + 'New Kizura'!C2 + Lydroa!C2 + Fermori!C2 + Uularin!C2 + 'Niul Spijan'!C2 -> 3.0536125e+08 | CM2: =((CL2-CL3)/CL3) -> 0.0095365012 | CN2: =SUM(CL2/C2) -> 0.04458362 | CU2: =SUM(CV2+250) -> 2015 | CV2: 1765 | CW2: =Praesyu!C2 + Lycroa!C2 + Emara!C2 + Eldjo!C2 + Easuhura!C2 + Ilicuhe!C2 + Tonder!C2 -> 2.5004491e+08 | CX2: =((CW2-CW3)/CW3) -> 0.0070197975 | CY2: =SUM(CW2/C2) -> 0.036507276 | DF2: =SUM(DG2+250) -> 2015 | DG2: 1765 | DH2: =Verusa!C2 + Darewa!C2 + Siana!C2 + Yaxuto!C2 + 'Merela Sta'!C2 + Palina!C2 -> 1.7345579e+08 | DI2: =((DH2-DH3)/DH3) -> 0.0025253375 | DJ2: =SUM(DH2/C2) -> 0.025325045 | DQ2: =SUM(DR2+250) -> 2015 | DR2: 1765 | DS2: =Sunsokua!C2 + Vayvele!C2 + Selaja!C2 + Sadain!C2 -> 2.0393006e+08 | DT2: =((DS2-DS3)/DS3) -> 0.011491543 | DU2: =SUM(DS2/C2) -> 0.029774376 | EB2: =SUM(EC2+250) -> 2015 | EC2: 1765 | ED2: =Pelugrotoa!C2 + Lieri!C2 + 'Rtesania'!C2 + Ozinia!C2 -> 4.0187103e+08 | EE2: =((ED2-ED3)/ED3) -> 0.0055854682 | EF2: =SUM(ED2/C2) -> 0.058674327 | EM2: =SUM(EN2+250) -> 2015 | EN2: 1765 | EO2: =Ocaun!C2 + 'Dual Cenryia'!C2 + Byllu!C2 + Exilium!C2 + Inrea!C2 + Amcha!C2 + Isnti!C2 + Galca!C2 + Otiiric!C2 + Taing!C2 + 'Cruthi Anoso'!C2 -> 2.9818876e+08 | EP2: =((EO2-EO3)/EO3) -> 0.018211894 | EQ2: =SUM(EO2/C2) -> 0.043536417 | EX2: =SUM(EY2+250) -> 2015 | EY2: 1765 | EZ2: =Sivoso!C2 + Taoisia!C2 + Seytinemas!C2 + Trian!C2 + 'Chaenia'!C2 -> 1.4685923e+08 | FA2: =((EZ2-EZ3)/EZ3) -> 0.0067047667 | FB2: =SUM(EZ2/C2) -> 0.021441869 | FI2: =SUM(FJ2+250) -> 2015 | FJ2: 1765 | FK2: =Migoku!C2 + 'Welenu Fana'!C2 + Haiza!C2 + Ucrua!C2 + Ihner!C2 + Oscairia!C2 + Shinam!C2 + 'Ruylku'!C2 + Taval!C2 + 'Western Migoku'!C2 + 'Pruim Fijan'!C2 + 'Canldives'!C2 -> 1.9772453e+08 | FL2: =((FK2-FK3)/FK3) -> 0.01301624 | FM2: =SUM(FK2/C2) -> 0.028868351 | FT2: =SUM(FU2+250) -> 2015 | FU2: 1765 | FV2: =Vesozata!C2 + Etretes!C2 + Kusierna!C2 + Eparia!C2 -> 1.5636242e+08 | FW2: =((FV2-FV3)/FV3) -> 0.02573036 | FX2: =SUM(FV2/C2) -> 0.022829364 | GE2: =SUM(GF2+250) -> 2015 | GF2: 1765 | GG2: =Dahe!C2 + Kaastini!C2 + Suenan!C2 + Oyreain!C2 + Sanagara!C2 + 'North Ayre'!C2 + Stinebar!C2 + 'Cloja'!C2 + 'Pha Hii'!C2 + 'Prystr Hii'!C2 -> 1.0350119e+09 | GH2: =((GG2-GG3)/GG3) -> 0.0032492257 | GI2: =SUM(GG2/C2) -> 0.15111471 | GP2: =SUM(GQ2+250) -> 2015 | GQ2: 1765 | GR2: =Maalle!C2 + 'United Delet'!C2 + Ohtina!C2 + Astye!C2 + Prstreula!C2 + Veelmit!C2 + Aplasia!C2 + 'Elja and Munusia'!C2 + Walporein!C2 + 'Crila Republic'!C2 + 'Niretui and Anulan'!C2 + 'Rethern'!C2 + Tvecoca!C2 -> 2.0435369e+08 | GS2: =((GR2-GR3)/GR3) -> 0.010741046 | GT2: =SUM(GR2/C2) -> 0.029836227 | HA2: =SUM(HB2+250) -> 2015 | HB2: 1765 | HC2: =Andsaudare!C2 + Nia!C2 + Umarcia!C2 + Mendereide!C2 + Iainoa!C2 + Isari!C2 + 'Rkmepuia'!C2 + Hiwush!C2 + Isuibul!C2 + Yutnitu!C2 -> 71713508 | HD2: =((HC2-HC3)/HC3) -> 0.012075509 | HE2: =SUM(HC2/C2) -> 0.010470378 | HL2: =SUM(HM2+250) -> 2015 | HM2: 1765 | HN2: =Zhanshe!C2 + Volver!C2 + Finae!C2 + Myla!C2 + 'Nheyes Si'!C2 + Onphello!C2 + Hyelen!C2 -> 1.2317668e+08 | HO2: =((HN2-HN3)/HN3) -> 0.011188839 | HP2: =SUM(HN2/C2) -> 0.01798415 | HW2: =SUM(HX2+250) -> 2015 | HX2: 1765 | HY2: =Yihnurda!C2 + Ztesh!C2 + Wundry!C2 + Anymna!C2 + Shomjind!C2 + Baluyde!C2 + Letan!C2 -> 6.0031751e+08 | HZ2: =((HY2-HY3)/HY3) -> 0.014393493 | IA2: =SUM(HY2/C2) -> 0.087648083 | IH2: =SUM(II2+250) -> 2015 | II2: 1765 | IJ2: =Iareva!C2 + 'United Mihili'!C2 + 'Mesjan Hyaa'!C2 + Desaki!C2 + 'Far Lands'!C2 -> 74200935 | IK2: =((IJ2-IJ3)/IJ3) -> 0.011565106 | IL2: =SUM(IJ2/C2) -> 0.01083355 | IS2: =SUM(IT2+250) -> 2015 | IT2: 1765 | IU2: =Verste!C2 + Quidic!C2 + Erkizil!C2 + Ashain!C2 + Ahokini!C2 -> 3.7121914e+08 | IV2: =((IU2-IU3)/IU3) -> 0.0082218894 | IW2: =SUM(IU2/C2) -> 0.054199062
A3: =SUM(B3+250) -> 2014 | B3: 1764 | C3: =Acetoa!C3 + Acrana!C3 + Aetintio!C3 + Ahokini!C3 + Amcha!C3 + Andsaudare!C3 + Anymna!C3 + Aplasia!C3 + Arbiya!C3 + 'Areoix Lie'!C3 + Ashain!C3 + Astye!C3 + Baluyde!C3 + Byllu!C3 + 'Candenat'!C3 + 'Canldives'!C3 + 'Chaenia'!C3 + 'Cloja'!C3 + 'Crila Republic'!C3 + 'Cruthi Anoso'!C3 + 'Curata'!C3 + Dahe!C3 + Danocia!C3 + Darewa!C3 + Desaki!C3 + Deschon!C3 + 'Disal Nila'!C3 + 'Dual Cenryia'!C3 + Ealdorii!C3 + Easuhura!C3 + Eldavpir!C3 + Eldjo!C3 + 'Elja and Munusia'!C3 + Emara!C3 + Enina!C3 + Eparia!C3 + Erkizil!C3 + Estijan!C3 + Etirha!C3 + Etretes!C3 + Exilium!C3 + 'Far Lands'!C3 + 'Feio Lie'!C3 + Fermori!C3 + Finae!C3 + Fincen!C3 + 'Fire Coast'!C3 + Gaeiya!C3 + Galca!C3 + Genaire!C3 + Grazail!C3 + Guise!C3 + Haiza!C3 + Heiso!C3 + Hiwush!C3 + Hkuqo!C3 + Hyelen!C3 + Iainoa!C3 + Iareva!C3 + Ihner!C3 + Ikzen!C3 + Ilicuhe!C3 + Inania!C3 + Inrea!C3 + Iquir!C3 + Isari!C3 + Isnti!C3 + Isuibul!C3 + Jathua!C3 + Jau!C3 + Jshain!C3 + Kaastini!C3 + Koruch!C3 + Kusierna!C3 + Laselteh!C3 + Lasri!C3 + Letan!C3 + Lieri!C3 + Lycroa!C3 + Lydroa!C3 + Maalle!C3 + Mendereide!C3 + 'Merela Sta'!C3 + 'Mesjan Hyaa'!C3 + Metndria!C3 + Migoku!C3 + Myla!C3 + 'New Kizura'!C3 + 'New Misos'!C3 + 'Nheyes Si'!C3 + Nia!C3 + 'Niretui and Anulan'!C3 + 'Niul Spijan'!C3 + 'North Ayre'!C3 + Ocaun!C3 + Ohtina!C3 + Onphello!C3 + Oscairia!C3 + Othya!C3 + Otiiric!C3 + Oyreain!C3 + Ozinia!C3 + Palina!C3 + Peka!C3 + Pelan!C3 + Pelines!C3 + Pelugrotoa!C3 + 'Pha Hii'!C3 + Phuris!C3 + Praesyu!C3 + Prstreula!C3 + 'Pruim Fijan'!C3 + 'Prystr Hii'!C3 + Quidic!C3 + 'Raledria'!C3 + 'Reerica'!C3 + 'Rethern'!C3 + 'Rijan bu'!C3 + 'Rinew'!C3 + 'Rkmepuia'!C3 + 'Rtesania'!C3 + 'Ruylku'!C3 + Saa!C3 + Sadain!C3 + Sanagara!C3 + Sattle!C3 + Selaja!C3 + Seytinemas!C3 + Shinam!C3 + Shomjind!C3 + Siana!C3 + Sivoso!C3 + Slyiaduun!C3 + Stinebar!C3 + Suenan!C3 + Sunsokua!C3 + Taing!C3 + Taniduna!C3 + Taoisia!C3 + Taval!C3 + Terressin!C3 + Tomscilus!C3 + Tonder!C3 + Trevilla!C3 + Trian!C3 + Tvecoca!C3 + Ucrua!C3 + Ukhdari!C3 + Umarcia!C3 + Umendel!C3 + 'United Delet'!C3 + 'United Mihili'!C3 + Urbiqu!C3 + Uularin!C3 + Vayvele!C3 + Veelmit!C3 + Verste!C3 + Verusa!C3 + Vesozata!C3 + Viussi!C3 + Volver!C3 + Walporein!C3 + 'Welenu Fana'!C3 + 'Western Migoku'!C3 + Wundry!C3 + Yaxuto!C3 + Yihnurda!C3 + Yoprioq!C3 + Yutnitu!C3 + Zenashan!C3 + Zhanshe!C3 + Ztesh!C3 -> 6.783743e+09 | D3: =((C3-C4)/C4) -> 0.0098200828 | K3: =SUM(L3+250) -> 2014 | L3: 1764 | M3: =Eldavpir!C3 + Iquir!C3 + Viussi!C3 + Umendel!C3 + 'Reerica'!C3 + Saa!C3 + Sattle!C3 -> 1.0889187e+08 | N3: =((M3-M4)/M4) -> 0.023619424 | O3: =SUM(M3/C3) -> 0.016051887 | V3: =SUM(W3+250) -> 2014 | W3: 1764 | X3: ='Areoix Lie'!C3 + Jau!C3 + Terressin!C3 + Acetoa!C3 + 'Feio Lie'!C3 -> 6.9205239e+08 | Y3: =((X3-X4)/X4) -> 0.0047854166 | Z3: =SUM(X3/C3) -> 0.1020163 | AG3: =SUM(AH3+250) -> 2014 | AH3: 1764 | AI3: =Taniduna!C3 + Jathua!C3 + Deschon!C3 + Pelines!C3 + 'Candenat'!C3 + Othya!C3 + Yoprioq!C3 + Jshain!C3 + 'Fire Coast'!C3 + 'Rijan bu'!C3 + 'Rinew'!C3 + Enina!C3 + Trevilla!C3 -> 2.5645726e+08 | AJ3: =((AI3-AI4)/AI4) -> 0.027768771 | AK3: =SUM(AI3/C3) -> 0.037804683 | AR3: =SUM(AS3+250) -> 2014 | AS3: 1764 | AT3: =Gaeiya!C3 + 'Raledria'!C3 + Arbiya!C3 + Fincen!C3 + 'Curata'!C3 -> 3.2197357e+08 | AU3: =((AT3-AT4)/AT4) -> 0.014181202 | AV3: =SUM(AT3/C3) -> 0.047462524 | BC3: =SUM(BD3+250) -> 2014 | BD3: 1764 | BE3: =Etirha!C3 + Laselteh!C3 + Grazail!C3 + 'Disal Nila'!C3 + Pelan!C3 + Peka!C3 + Guise!C3 -> 1.0683046e+08 | BF3: =((BE3-BE4)/BE4) -> 0.0047757311 | BG3: =SUM(BE3/C3) -> 0.015748011 | BN3: =SUM(BO3+250) -> 2014 | BO3: 1764 | BP3: =Genaire!C3 + 'New Misos'!C3 + Phuris!C3 + Lasri!C3 + Slyiaduun!C3 + Aetintio!C3 + Metndria!C3 + Tomscilus!C3 -> 1.0270801e+08 | BQ3: =((BP3-BP4)/BP4) -> 0.010305758 | BR3: =SUM(BP3/C3) -> 0.015140316 | BY3: =SUM(BZ3+250) -> 2014 | BZ3: 1764 | CA3: =Ealdorii!C3 + Ukhdari!C3 + Hkuqo!C3 + Acrana!C3 + Zenashan!C3 -> 2.6928204e+08 | CB3: =((CA3-CA4)/CA4) -> 0.0063470105 | CC3: =SUM(CA3/C3) -> 0.039695201 | CJ3: =SUM(CK3+250) -> 2014 | CK3: 1764 | CL3: =Estijan!C3 + Ikzen!C3 + Urbiqu!C3 + Danocia!C3 + Koruch!C3 + 'New Kizura'!C3 + Lydroa!C3 + Fermori!C3 + Uularin!C3 + 'Niul Spijan'!C3 -> 3.0247668e+08 | CM3: =((CL3-CL4)/CL4) -> 0.0096614808 | CN3: =SUM(CL3/C3) -> 0.044588463 | CU3: =SUM(CV3+250) -> 2014 | CV3: 1764 | CW3: =Praesyu!C3 + Lycroa!C3 + Emara!C3 + Eldjo!C3 + Easuhura!C3 + Ilicuhe!C3 + Tonder!C3 -> 2.4830188e+08 | CX3: =((CW3-CW4)/CW4) -> 0.0057930164 | CY3: =SUM(CW3/C3) -> 0.036602489 | DF3: =SUM(DG3+250) -> 2014 | DG3: 1764 | DH3: =Verusa!C3 + Darewa!C3 + Siana!C3 + Yaxuto!C3 + 'Merela Sta'!C3 + Palina!C3 -> 1.7301886e+08 | DI3: =((DH3-DH4)/DH4) -> 0.0022939881 | DJ3: =SUM(DH3/C3) -> 0.025504926 | DQ3: =SUM(DR3+250) -> 2014 | DR3: 1764 | DS3: =Sunsokua!C3 + Vayvele!C3 + Selaja!C3 + Sadain!C3 -> 2.0161322e+08 | DT3: =((DS3-DS4)/DS4) -> 0.011979 | DU3: =SUM(DS3/C3) -> 0.029720055 | EB3: =SUM(EC3+250) -> 2014 | EC3: 1764 | ED3: =Pelugrotoa!C3 + Lieri!C3 + 'Rtesania'!C3 + Ozinia!C3 -> 3.9963886e+08 | EE3: =((ED3-ED4)/ED4) -> 0.0057165764 | EF3: =SUM(ED3/C3) -> 0.058911262 | EM3: =SUM(EN3+250) -> 2014 | EN3: 1764 | EO3: =Ocaun!C3 + 'Dual Cenryia'!C3 + Byllu!C3 + Exilium!C3 + Inrea!C3 + Amcha!C3 + Isnti!C3 + Galca!C3 + Otiiric!C3 + Taing!C3 + 'Cruthi Anoso'!C3 -> 2.9285531e+08 | EP3: =((EO3-EO4)/EO4) -> 0.018132868 | EQ3: =SUM(EO3/C3) -> 0.043170166 | EX3: =SUM(EY3+250) -> 2014 | EY3: 1764 | EZ3: =Sivoso!C3 + Taoisia!C3 + Seytinemas!C3 + Trian!C3 + 'Chaenia'!C3 -> 1.4588113e+08 | FA3: =((EZ3-EZ4)/EZ4) -> 0.0068603171 | FB3: =SUM(EZ3/C3) -> 0.021504518 | FI3: =SUM(FJ3+250) -> 2014 | FJ3: 1764 | FK3: =Migoku!C3 + 'Welenu Fana'!C3 + Haiza!C3 + Ucrua!C3 + Ihner!C3 + Oscairia!C3 + Shinam!C3 + 'Ruylku'!C3 + Taval!C3 + 'Western Migoku'!C3 + 'Pruim Fijan'!C3 + 'Canldives'!C3 -> 1.9518397e+08 | FL3: =((FK3-FK4)/FK4) -> 0.01374137 | FM3: =SUM(FK3/C3) -> 0.028772312 | FT3: =SUM(FU3+250) -> 2014 | FU3: 1764 | FV3: =Vesozata!C3 + Etretes!C3 + Kusierna!C3 + Eparia!C3 -> 1.5244009e+08 | FW3: =((FV3-FV4)/FV4) -> 0.024955511 | FX3: =SUM(FV3/C3) -> 0.022471383 | GE3: =SUM(GF3+250) -> 2014 | GF3: 1764 | GG3: =Dahe!C3 + Kaastini!C3 + Suenan!C3 + Oyreain!C3 + Sanagara!C3 + 'North Ayre'!C3 + Stinebar!C3 + 'Cloja'!C3 + 'Pha Hii'!C3 + 'Prystr Hii'!C3 -> 1.0316598e+09 | GH3: =((GG3-GG4)/GG4) -> 0.0031424058 | GI3: =SUM(GG3/C3) -> 0.15207825 | GP3: =SUM(GQ3+250) -> 2014 | GQ3: 1764 | GR3: =Maalle!C3 + 'United Delet'!C3 + Ohtina!C3 + Astye!C3 + Prstreula!C3 + Veelmit!C3 + Aplasia!C3 + 'Elja and Munusia'!C3 + Walporein!C3 + 'Crila Republic'!C3 + 'Niretui and Anulan'!C3 + 'Rethern'!C3 + Tvecoca!C3 -> 2.0218204e+08 | GS3: =((GR3-GR4)/GR4) -> 0.011291506 | GT3: =SUM(GR3/C3) -> 0.029803907 | HA3: =SUM(HB3+250) -> 2014 | HB3: 1764 | HC3: =Andsaudare!C3 + Nia!C3 + Umarcia!C3 + Mendereide!C3 + Iainoa!C3 + Isari!C3 + 'Rkmepuia'!C3 + Hiwush!C3 + Isuibul!C3 + Yutnitu!C3 -> 70857863 | HD3: =((HC3-HC4)/HC4) -> 0.012287193 | HE3: =SUM(HC3/C3) -> 0.010445246 | HL3: =SUM(HM3+250) -> 2014 | HM3: 1764 | HN3: =Zhanshe!C3 + Volver!C3 + Finae!C3 + Myla!C3 + 'Nheyes Si'!C3 + Onphello!C3 + Hyelen!C3 -> 1.2181373e+08 | HO3: =((HN3-HN4)/HN4) -> 0.012012952 | HP3: =SUM(HN3/C3) -> 0.017956713 | HW3: =SUM(HX3+250) -> 2014 | HX3: 1764 | HY3: =Yihnurda!C3 + Ztesh!C3 + Wundry!C3 + Anymna!C3 + Shomjind!C3 + Baluyde!C3 + Letan!C3 -> 5.9179945e+08 | HZ3: =((HY3-HY4)/HY4) -> 0.015177084 | IA3: =SUM(HY3/C3) -> 0.087237893 | IH3: =SUM(II3+250) -> 2014 | II3: 1764 | IJ3: =Iareva!C3 + 'United Mihili'!C3 + 'Mesjan Hyaa'!C3 + Desaki!C3 + 'Far Lands'!C3 -> 73352604 | IK3: =((IJ3-IJ4)/IJ4) -> 0.011734019 | IL3: =SUM(IJ3/C3) -> 0.010812999 | IS3: =SUM(IT3+250) -> 2014 | IT3: 1764 | IU3: =Verste!C3 + Quidic!C3 + Erkizil!C3 + Ashain!C3 + Ahokini!C3 -> 3.681919e+08 | IV3: =((IU3-IU4)/IU4) -> 0.0086202355 | IW3: =SUM(IU3/C3) -> 0.054275626
A4: =SUM(B4+250) -> 2013 | B4: 1763 | C4: =Acetoa!C4 + Acrana!C4 + Aetintio!C4 + Ahokini!C4 + Amcha!C4 + Andsaudare!C4 + Anymna!C4 + Aplasia!C4 + Arbiya!C4 + 'Areoix Lie'!C4 + Ashain!C4 + Astye!C4 + Baluyde!C4 + Byllu!C4 + 'Candenat'!C4 + 'Canldives'!C4 + 'Chaenia'!C4 + 'Cloja'!C4 + 'Crila Republic'!C4 + 'Cruthi Anoso'!C4 + 'Curata'!C4 + Dahe!C4 + Danocia!C4 + Darewa!C4 + Desaki!C4 + Deschon!C4 + 'Disal Nila'!C4 + 'Dual Cenryia'!C4 + Ealdorii!C4 + Easuhura!C4 + Eldavpir!C4 + Eldjo!C4 + 'Elja and Munusia'!C4 + Emara!C4 + Enina!C4 + Eparia!C4 + Erkizil!C4 + Estijan!C4 + Etirha!C4 + Etretes!C4 + Exilium!C4 + 'Far Lands'!C4 + 'Feio Lie'!C4 + Fermori!C4 + Finae!C4 + Fincen!C4 + 'Fire Coast'!C4 + Gaeiya!C4 + Galca!C4 + Genaire!C4 + Grazail!C4 + Guise!C4 + Haiza!C4 + Heiso!C4 + Hiwush!C4 + Hkuqo!C4 + Hyelen!C4 + Iainoa!C4 + Iareva!C4 + Ihner!C4 + Ikzen!C4 + Ilicuhe!C4 + Inania!C4 + Inrea!C4 + Iquir!C4 + Isari!C4 + Isnti!C4 + Isuibul!C4 + Jathua!C4 + Jau!C4 + Jshain!C4 + Kaastini!C4 + Koruch!C4 + Kusierna!C4 + Laselteh!C4 + Lasri!C4 + Letan!C4 + Lieri!C4 + Lycroa!C4 + Lydroa!C4 + Maalle!C4 + Mendereide!C4 + 'Merela Sta'!C4 + 'Mesjan Hyaa'!C4 + Metndria!C4 + Migoku!C4 + Myla!C4 + 'New Kizura'!C4 + 'New Misos'!C4 + 'Nheyes Si'!C4 + Nia!C4 + 'Niretui and Anulan'!C4 + 'Niul Spijan'!C4 + 'North Ayre'!C4 + Ocaun!C4 + Ohtina!C4 + Onphello!C4 + Oscairia!C4 + Othya!C4 + Otiiric!C4 + Oyreain!C4 + Ozinia!C4 + Palina!C4 + Peka!C4 + Pelan!C4 + Pelines!C4 + Pelugrotoa!C4 + 'Pha Hii'!C4 + Phuris!C4 + Praesyu!C4 + Prstreula!C4 + 'Pruim Fijan'!C4 + 'Prystr Hii'!C4 + Quidic!C4 + 'Raledria'!C4 + 'Reerica'!C4 + 'Rethern'!C4 + 'Rijan bu'!C4 + 'Rinew'!C4 + 'Rkmepuia'!C4 + 'Rtesania'!C4 + 'Ruylku'!C4 + Saa!C4 + Sadain!C4 + Sanagara!C4 + Sattle!C4 + Selaja!C4 + Seytinemas!C4 + Shinam!C4 + Shomjind!C4 + Siana!C4 + Sivoso!C4 + Slyiaduun!C4 + Stinebar!C4 + Suenan!C4 + Sunsokua!C4 + Taing!C4 + Taniduna!C4 + Taoisia!C4 + Taval!C4 + Terressin!C4 + Tomscilus!C4 + Tonder!C4 + Trevilla!C4 + Trian!C4 + Tvecoca!C4 + Ucrua!C4 + Ukhdari!C4 + Umarcia!C4 + Umendel!C4 + 'United Delet'!C4 + 'United Mihili'!C4 + Urbiqu!C4 + Uularin!C4 + Vayvele!C4 + Veelmit!C4 + Verste!C4 + Verusa!C4 + Vesozata!C4 + Viussi!C4 + Volver!C4 + Walporein!C4 + 'Welenu Fana'!C4 + 'Western Migoku'!C4 + Wundry!C4 + Yaxuto!C4 + Yihnurda!C4 + Yoprioq!C4 + Yutnitu!C4 + Zenashan!C4 + Zhanshe!C4 + Ztesh!C4 -> 6.7177739e+09 | D4: =((C4-C5)/C5) -> 0.0098609584 | K4: =SUM(L4+250) -> 2013 | L4: 1763 | M4: =Eldavpir!C4 + Iquir!C4 + Viussi!C4 + Umendel!C4 + 'Reerica'!C4 + Saa!C4 + Sattle!C4 -> 1.0637926e+08 | N4: =((M4-M5)/M5) -> 0.02443424 | O4: =SUM(M4/C4) -> 0.015835492 | V4: =SUM(W4+250) -> 2013 | W4: 1763 | X4: ='Areoix Lie'!C4 + Jau!C4 + Terressin!C4 + Acetoa!C4 + 'Feio Lie'!C4 -> 6.887564e+08 | Y4: =((X4-X5)/X5) -> 0.0038484269 | Z4: =SUM(X4/C4) -> 0.10252748 | AG4: =SUM(AH4+250) -> 2013 | AH4: 1763 | AI4: =Taniduna!C4 + Jathua!C4 + Deschon!C4 + Pelines!C4 + 'Candenat'!C4 + Othya!C4 + Yoprioq!C4 + Jshain!C4 + 'Fire Coast'!C4 + 'Rijan bu'!C4 + 'Rinew'!C4 + Enina!C4 + Trevilla!C4 -> 2.4952817e+08 | AJ4: =((AI4-AI5)/AI5) -> 0.027967143 | AK4: =SUM(AI4/C4) -> 0.037144472 | AR4: =SUM(AS4+250) -> 2013 | AS4: 1763 | AT4: =Gaeiya!C4 + 'Raledria'!C4 + Arbiya!C4 + Fincen!C4 + 'Curata'!C4 -> 3.1747144e+08 | AU4: =((AT4-AT5)/AT5) -> 0.016275924 | AV4: =SUM(AT4/C4) -> 0.047258429 | BC4: =SUM(BD4+250) -> 2013 | BD4: 1763 | BE4: =Etirha!C4 + Laselteh!C4 + Grazail!C4 + 'Disal Nila'!C4 + Pelan!C4 + Peka!C4 + Guise!C4 -> 1.0632269e+08 | BF4: =((BE4-BE5)/BE5) -> 0.0045213351 | BG4: =SUM(BE4/C4) -> 0.015827072 | BN4: =SUM(BO4+250) -> 2013 | BO4: 1763 | BP4: =Genaire!C4 + 'New Misos'!C4 + Phuris!C4 + Lasri!C4 + Slyiaduun!C4 + Aetintio!C4 + Metndria!C4 + Tomscilus!C4 -> 1.0166033e+08 | BQ4: =((BP4-BP5)/BP5) -> 0.010266049 | BR4: =SUM(BP4/C4) -> 0.015133038 | BY4: =SUM(BZ4+250) -> 2013 | BZ4: 1763 | CA4: =Ealdorii!C4 + Ukhdari!C4 + Hkuqo!C4 + Acrana!C4 + Zenashan!C4 -> 2.6758369e+08 | CB4: =((CA4-CA5)/CA5) -> 0.0065552043 | CC4: =SUM(CA4/C4) -> 0.039832196 | CJ4: =SUM(CK4+250) -> 2013 | CK4: 1763 | CL4: =Estijan!C4 + Ikzen!C4 + Urbiqu!C4 + Danocia!C4 + Koruch!C4 + 'New Kizura'!C4 + Lydroa!C4 + Fermori!C4 + Uularin!C4 + 'Niul Spijan'!C4 -> 2.9958227e+08 | CM4: =((CL4-CL5)/CL5) -> 0.0094286563 | CN4: =SUM(CL4/C4) -> 0.044595468 | CU4: =SUM(CV4+250) -> 2013 | CV4: 1763 | CW4: =Praesyu!C4 + Lycroa!C4 + Emara!C4 + Eldjo!C4 + Easuhura!C4 + Ilicuhe!C4 + Tonder!C4 -> 2.4687175e+08 | CX4: =((CW4-CW5)/CW5) -> 0.0052339792 | CY4: =SUM(CW4/C4) -> 0.036749041 | DF4: =SUM(DG4+250) -> 2013 | DG4: 1763 | DH4: =Verusa!C4 + Darewa!C4 + Siana!C4 + Yaxuto!C4 + 'Merela Sta'!C4 + Palina!C4 -> 1.7262287e+08 | DI4: =((DH4-DH5)/DH5) -> 0.0032401828 | DJ4: =SUM(DH4/C4) -> 0.025696439 | DQ4: =SUM(DR4+250) -> 2013 | DR4: 1763 | DS4: =Sunsokua!C4 + Vayvele!C4 + Selaja!C4 + Sadain!C4 -> 1.9922668e+08 | DT4: =((DS4-DS5)/DS5) -> 0.012390854 | DU4: =SUM(DS4/C4) -> 0.029656651 | EB4: =SUM(EC4+250) -> 2013 | EC4: 1763 | ED4: =Pelugrotoa!C4 + Lieri!C4 + 'Rtesania'!C4 + Ozinia!C4 -> 3.9736728e+08 | EE4: =((ED4-ED5)/ED5) -> 0.005450607 | EF4: =SUM(ED4/C4) -> 0.059151631 | EM4: =SUM(EN4+250) -> 2013 | EN4: 1763 | EO4: =Ocaun!C4 + 'Dual Cenryia'!C4 + Byllu!C4 + Exilium!C4 + Inrea!C4 + Amcha!C4 + Isnti!C4 + Galca!C4 + Otiiric!C4 + Taing!C4 + 'Cruthi Anoso'!C4 -> 2.8763958e+08 | EP4: =((EO4-EO5)/EO5) -> 0.017948948 | EQ4: =SUM(EO4/C4) -> 0.042817693 | EX4: =SUM(EY4+250) -> 2013 | EY4: 1763 | EZ4: =Sivoso!C4 + Taoisia!C4 + Seytinemas!C4 + Trian!C4 + 'Chaenia'!C4 -> 1.4488715e+08 | FA4: =((EZ4-EZ5)/EZ5) -> 0.0072086932 | FB4: =SUM(EZ4/C4) -> 0.021567733 | FI4: =SUM(FJ4+250) -> 2013 | FJ4: 1763 | FK4: =Migoku!C4 + 'Welenu Fana'!C4 + Haiza!C4 + Ucrua!C4 + Ihner!C4 + Oscairia!C4 + Shinam!C4 + 'Ruylku'!C4 + Taval!C4 + 'Western Migoku'!C4 + 'Pruim Fijan'!C4 + 'Canldives'!C4 -> 1.9253823e+08 | FL4: =((FK4-FK5)/FK5) -> 0.012408477 | FM4: =SUM(FK4/C4) -> 0.028661017 | FT4: =SUM(FU4+250) -> 2013 | FU4: 1763 | FV4: =Vesozata!C4 + Etretes!C4 + Kusierna!C4 + Eparia!C4 -> 1.4872849e+08 | FW4: =((FV4-FV5)/FV5) -> 0.024345645 | FX4: =SUM(FV4/C4) -> 0.02213955 | GE4: =SUM(GF4+250) -> 2013 | GF4: 1763 | GG4: =Dahe!C4 + Kaastini!C4 + Suenan!C4 + Oyreain!C4 + Sanagara!C4 + 'North Ayre'!C4 + Stinebar!C4 + 'Cloja'!C4 + 'Pha Hii'!C4 + 'Prystr Hii'!C4 -> 1.028428e+09 | GH4: =((GG4-GG5)/GG5) -> 0.0032348318 | GI4: =SUM(GG4/C4) -> 0.1530906 | GP4: =SUM(GQ4+250) -> 2013 | GQ4: 1763 | GR4: =Maalle!C4 + 'United Delet'!C4 + Ohtina!C4 + Astye!C4 + Prstreula!C4 + Veelmit!C4 + Aplasia!C4 + 'Elja and Munusia'!C4 + Walporein!C4 + 'Crila Republic'!C4 + 'Niretui and Anulan'!C4 + 'Rethern'!C4 + Tvecoca!C4 -> 1.9992459e+08 | GS4: =((GR4-GR5)/GR5) -> 0.011790848 | GT4: =SUM(GR4/C4) -> 0.029760542 | HA4: =SUM(HB4+250) -> 2013 | HB4: 1763 | HC4: =Andsaudare!C4 + Nia!C4 + Umarcia!C4 + Mendereide!C4 + Iainoa!C4 + Isari!C4 + 'Rkmepuia'!C4 + Hiwush!C4 + Isuibul!C4 + Yutnitu!C4 -> 69997787 | HD4: =((HC4-HC5)/HC5) -> 0.011945464 | HE4: =SUM(HC4/C4) -> 0.010419789 | HL4: =SUM(HM4+250) -> 2013 | HM4: 1763 | HN4: =Zhanshe!C4 + Volver!C4 + Finae!C4 + Myla!C4 + 'Nheyes Si'!C4 + Onphello!C4 + Hyelen!C4 -> 1.2036776e+08 | HO4: =((HN4-HN5)/HN5) -> 0.012758943 | HP4: =SUM(HN4/C4) -> 0.017917804 | HW4: =SUM(HX4+250) -> 2013 | HX4: 1763 | HY4: =Yihnurda!C4 + Ztesh!C4 + Wundry!C4 + Anymna!C4 + Shomjind!C4 + Baluyde!C4 + Letan!C4 -> 5.8295194e+08 | HZ4: =((HY4-HY5)/HY5) -> 0.015792314 | IA4: =SUM(HY4/C4) -> 0.086777546 | IH4: =SUM(II4+250) -> 2013 | II4: 1763 | IJ4: =Iareva!C4 + 'United Mihili'!C4 + 'Mesjan Hyaa'!C4 + Desaki!C4 + 'Far Lands'!C4 -> 72501866 | IK4: =((IJ4-IJ5)/IJ5) -> 0.012549955 | IL4: =SUM(IJ4/C4) -> 0.010792543 | IS4: =SUM(IT4+250) -> 2013 | IT4: 1763 | IU4: =Verste!C4 + Quidic!C4 + Erkizil!C4 + Ashain!C4 + Ahokini!C4 -> 3.6504513e+08 | IV4: =((IU4-IU5)/IU5) -> 0.008908933 | IW4: =SUM(IU4/C4) -> 0.054340192
A5: =SUM(B5+250) -> 2012 | B5: 1762 | C5: =Acetoa!C5 + Acrana!C5 + Aetintio!C5 + Ahokini!C5 + Amcha!C5 + Andsaudare!C5 + Anymna!C5 + Aplasia!C5 + Arbiya!C5 + 'Areoix Lie'!C5 + Ashain!C5 + Astye!C5 + Baluyde!C5 + Byllu!C5 + 'Candenat'!C5 + 'Canldives'!C5 + 'Chaenia'!C5 + 'Cloja'!C5 + 'Crila Republic'!C5 + 'Cruthi Anoso'!C5 + 'Curata'!C5 + Dahe!C5 + Danocia!C5 + Darewa!C5 + Desaki!C5 + Deschon!C5 + 'Disal Nila'!C5 + 'Dual Cenryia'!C5 + Ealdorii!C5 + Easuhura!C5 + Eldavpir!C5 + Eldjo!C5 + 'Elja and Munusia'!C5 + Emara!C5 + Enina!C5 + Eparia!C5 + Erkizil!C5 + Estijan!C5 + Etirha!C5 + Etretes!C5 + Exilium!C5 + 'Far Lands'!C5 + 'Feio Lie'!C5 + Fermori!C5 + Finae!C5 + Fincen!C5 + 'Fire Coast'!C5 + Gaeiya!C5 + Galca!C5 + Genaire!C5 + Grazail!C5 + Guise!C5 + Haiza!C5 + Heiso!C5 + Hiwush!C5 + Hkuqo!C5 + Hyelen!C5 + Iainoa!C5 + Iareva!C5 + Ihner!C5 + Ikzen!C5 + Ilicuhe!C5 + Inania!C5 + Inrea!C5 + Iquir!C5 + Isari!C5 + Isnti!C5 + Isuibul!C5 + Jathua!C5 + Jau!C5 + Jshain!C5 + Kaastini!C5 + Koruch!C5 + Kusierna!C5 + Laselteh!C5 + Lasri!C5 + Letan!C5 + Lieri!C5 + Lycroa!C5 + Lydroa!C5 + Maalle!C5 + Mendereide!C5 + 'Merela Sta'!C5 + 'Mesjan Hyaa'!C5 + Metndria!C5 + Migoku!C5 + Myla!C5 + 'New Kizura'!C5 + 'New Misos'!C5 + 'Nheyes Si'!C5 + Nia!C5 + 'Niretui and Anulan'!C5 + 'Niul Spijan'!C5 + 'North Ayre'!C5 + Ocaun!C5 + Ohtina!C5 + Onphello!C5 + Oscairia!C5 + Othya!C5 + Otiiric!C5 + Oyreain!C5 + Ozinia!C5 + Palina!C5 + Peka!C5 + Pelan!C5 + Pelines!C5 + Pelugrotoa!C5 + 'Pha Hii'!C5 + Phuris!C5 + Praesyu!C5 + Prstreula!C5 + 'Pruim Fijan'!C5 + 'Prystr Hii'!C5 + Quidic!C5 + 'Raledria'!C5 + 'Reerica'!C5 + 'Rethern'!C5 + 'Rijan bu'!C5 + 'Rinew'!C5 + 'Rkmepuia'!C5 + 'Rtesania'!C5 + 'Ruylku'!C5 + Saa!C5 + Sadain!C5 + Sanagara!C5 + Sattle!C5 + Selaja!C5 + Seytinemas!C5 + Shinam!C5 + Shomjind!C5 + Siana!C5 + Sivoso!C5 + Slyiaduun!C5 + Stinebar!C5 + Suenan!C5 + Sunsokua!C5 + Taing!C5 + Taniduna!C5 + Taoisia!C5 + Taval!C5 + Terressin!C5 + Tomscilus!C5 + Tonder!C5 + Trevilla!C5 + Trian!C5 + Tvecoca!C5 + Ucrua!C5 + Ukhdari!C5 + Umarcia!C5 + Umendel!C5 + 'United Delet'!C5 + 'United Mihili'!C5 + Urbiqu!C5 + Uularin!C5 + Vayvele!C5 + Veelmit!C5 + Verste!C5 + Verusa!C5 + Vesozata!C5 + Viussi!C5 + Volver!C5 + Walporein!C5 + 'Welenu Fana'!C5 + 'Western Migoku'!C5 + Wundry!C5 + Yaxuto!C5 + Yihnurda!C5 + Yoprioq!C5 + Yutnitu!C5 + Zenashan!C5 + Zhanshe!C5 + Ztesh!C5 -> 6.6521771e+09 | D5: =((C5-C6)/C6) -> 0.01007584 | K5: =SUM(L5+250) -> 2012 | L5: 1762 | M5: =Eldavpir!C5 + Iquir!C5 + Viussi!C5 + Umendel!C5 + 'Reerica'!C5 + Saa!C5 + Sattle!C5 -> 1.0384196e+08 | N5: =((M5-M6)/M6) -> 0.025298397 | O5: =SUM(M5/C5) -> 0.015610222 | V5: =SUM(W5+250) -> 2012 | W5: 1762 | X5: ='Areoix Lie'!C5 + Jau!C5 + Terressin!C5 + Acetoa!C5 + 'Feio Lie'!C5 -> 6.8611593e+08 | Y5: =((X5-X6)/X6) -> 0.0030286276 | Z5: =SUM(X5/C5) -> 0.10314156 | AG5: =SUM(AH5+250) -> 2012 | AH5: 1762 | AI5: =Taniduna!C5 + Jathua!C5 + Deschon!C5 + Pelines!C5 + 'Candenat'!C5 + Othya!C5 + Yoprioq!C5 + Jshain!C5 + 'Fire Coast'!C5 + 'Rijan bu'!C5 + 'Rinew'!C5 + Enina!C5 + Trevilla!C5 -> 2.4273944e+08 | AJ5: =((AI5-AI6)/AI6) -> 0.02815798 | AK5: =SUM(AI5/C5) -> 0.036490225 | AR5: =SUM(AS5+250) -> 2012 | AS5: 1762 | AT5: =Gaeiya!C5 + 'Raledria'!C5 + Arbiya!C5 + Fincen!C5 + 'Curata'!C5 -> 3.1238705e+08 | AU5: =((AT5-AT6)/AT6) -> 0.016593313 | AV5: =SUM(AT5/C5) -> 0.046960123 | BC5: =SUM(BD5+250) -> 2012 | BD5: 1762 | BE5: =Etirha!C5 + Laselteh!C5 + Grazail!C5 + 'Disal Nila'!C5 + Pelan!C5 + Peka!C5 + Guise!C5 -> 1.0584414e+08 | BF5: =((BE5-BE6)/BE6) -> 0.0046965741 | BG5: =SUM(BE5/C5) -> 0.015911203 | BN5: =SUM(BO5+250) -> 2012 | BO5: 1762 | BP5: =Genaire!C5 + 'New Misos'!C5 + Phuris!C5 + Lasri!C5 + Slyiaduun!C5 + Aetintio!C5 + Metndria!C5 + Tomscilus!C5 -> 1.0062728e+08 | BQ5: =((BP5-BP6)/BP6) -> 0.011109091 | BR5: =SUM(BP5/C5) -> 0.01512697 | BY5: =SUM(BZ5+250) -> 2012 | BZ5: 1762 | CA5: =Ealdorii!C5 + Ukhdari!C5 + Hkuqo!C5 + Acrana!C5 + Zenashan!C5 -> 2.6584104e+08 | CB5: =((CA5-CA6)/CA6) -> 0.0074572442 | CC5: =SUM(CA5/C5) -> 0.039963014 | CJ5: =SUM(CK5+250) -> 2012 | CK5: 1762 | CL5: =Estijan!C5 + Ikzen!C5 + Urbiqu!C5 + Danocia!C5 + Koruch!C5 + 'New Kizura'!C5 + Lydroa!C5 + Fermori!C5 + Uularin!C5 + 'Niul Spijan'!C5 -> 2.9678399e+08 | CM5: =((CL5-CL6)/CL6) -> 0.010009225 | CN5: =SUM(CL5/C5) -> 0.044614566 | CU5: =SUM(CV5+250) -> 2012 | CV5: 1762 | CW5: =Praesyu!C5 + Lycroa!C5 + Emara!C5 + Eldjo!C5 + Easuhura!C5 + Ilicuhe!C5 + Tonder!C5 -> 2.4558636e+08 | CX5: =((CW5-CW6)/CW6) -> 0.0048031024 | CY5: =SUM(CW5/C5) -> 0.036918193 | DF5: =SUM(DG5+250) -> 2012 | DG5: 1762 | DH5: =Verusa!C5 + Darewa!C5 + Siana!C5 + Yaxuto!C5 + 'Merela Sta'!C5 + Palina!C5 -> 1.7206534e+08 | DI5: =((DH5-DH6)/DH6) -> 0.0029068378 | DJ5: =SUM(DH5/C5) -> 0.02586602 | DQ5: =SUM(DR5+250) -> 2012 | DR5: 1762 | DS5: =Sunsokua!C5 + Vayvele!C5 + Selaja!C5 + Sadain!C5 -> 1.967883e+08 | DT5: =((DS5-DS6)/DS6) -> 0.012495885 | DU5: =SUM(DS5/C5) -> 0.029582541 | EB5: =SUM(EC5+250) -> 2012 | EC5: 1762 | ED5: =Pelugrotoa!C5 + Lieri!C5 + 'Rtesania'!C5 + Ozinia!C5 -> 3.9521313e+08 | EE5: =((ED5-ED6)/ED6) -> 0.0062491881 | EF5: =SUM(ED5/C5) -> 0.059411096 | EM5: =SUM(EN5+250) -> 2012 | EN5: 1762 | EO5: =Ocaun!C5 + 'Dual Cenryia'!C5 + Byllu!C5 + Exilium!C5 + Inrea!C5 + Amcha!C5 + Isnti!C5 + Galca!C5 + Otiiric!C5 + Taing!C5 + 'Cruthi Anoso'!C5 -> 2.8256779e+08 | EP5: =((EO5-EO6)/EO6) -> 0.017606391 | EQ5: =SUM(EO5/C5) -> 0.042477491 | EX5: =SUM(EY5+250) -> 2012 | EY5: 1762 | EZ5: =Sivoso!C5 + Taoisia!C5 + Seytinemas!C5 + Trian!C5 + 'Chaenia'!C5 -> 1.4385018e+08 | FA5: =((EZ5-EZ6)/EZ6) -> 0.0076190764 | FB5: =SUM(EZ5/C5) -> 0.021624527 | FI5: =SUM(FJ5+250) -> 2012 | FJ5: 1762 | FK5: =Migoku!C5 + 'Welenu Fana'!C5 + Haiza!C5 + Ucrua!C5 + Ihner!C5 + Oscairia!C5 + Shinam!C5 + 'Ruylku'!C5 + Taval!C5 + 'Western Migoku'!C5 + 'Pruim Fijan'!C5 + 'Canldives'!C5 -> 1.9017841e+08 | FL5: =((FK5-FK6)/FK6) -> 0.015776834 | FM5: =SUM(FK5/C5) -> 0.028588897 | FT5: =SUM(FU5+250) -> 2012 | FU5: 1762 | FV5: =Vesozata!C5 + Etretes!C5 + Kusierna!C5 + Eparia!C5 -> 1.4519366e+08 | FW5: =((FV5-FV6)/FV6) -> 0.023709831 | FX5: =SUM(FV5/C5) -> 0.021826487 | GE5: =SUM(GF5+250) -> 2012 | GF5: 1762 | GG5: =Dahe!C5 + Kaastini!C5 + Suenan!C5 + Oyreain!C5 + Sanagara!C5 + 'North Ayre'!C5 + Stinebar!C5 + 'Cloja'!C5 + 'Pha Hii'!C5 + 'Prystr Hii'!C5 -> 1.025112e+09 | GH5: =((GG5-GG6)/GG6) -> 0.0032459972 | GI5: =SUM(GG5/C5) -> 0.15410173 | GP5: =SUM(GQ5+250) -> 2012 | GQ5: 1762 | GR5: =Maalle!C5 + 'United Delet'!C5 + Ohtina!C5 + Astye!C5 + Prstreula!C5 + Veelmit!C5 + Aplasia!C5 + 'Elja and Munusia'!C5 + Walporein!C5 + 'Crila Republic'!C5 + 'Niretui and Anulan'!C5 + 'Rethern'!C5 + Tvecoca!C5 -> 1.9759478e+08 | GS5: =((GR5-GR6)/GR6) -> 0.012690528 | GT5: =SUM(GR5/C5) -> 0.029703777 | HA5: =SUM(HB5+250) -> 2012 | HB5: 1762 | HC5: =Andsaudare!C5 + Nia!C5 + Umarcia!C5 + Mendereide!C5 + Iainoa!C5 + Isari!C5 + 'Rkmepuia'!C5 + Hiwush!C5 + Isuibul!C5 + Yutnitu!C5 -> 69171501 | HD5: =((HC5-HC6)/HC6) -> 0.01205965 | HE5: =SUM(HC5/C5) -> 0.010398325 | HL5: =SUM(HM5+250) -> 2012 | HM5: 1762 | HN5: =Zhanshe!C5 + Volver!C5 + Finae!C5 + Myla!C5 + 'Nheyes Si'!C5 + Onphello!C5 + Hyelen!C5 -> 1.1885134e+08 | HO5: =((HN5-HN6)/HN6) -> 0.013514679 | HP5: =SUM(HN5/C5) -> 0.017866533 | HW5: =SUM(HX5+250) -> 2012 | HX5: 1762 | HY5: =Yihnurda!C5 + Ztesh!C5 + Wundry!C5 + Anymna!C5 + Shomjind!C5 + Baluyde!C5 + Letan!C5 -> 5.738889e+08 | HZ5: =((HY5-HY6)/HY6) -> 0.0163453 | IA5: =SUM(HY5/C5) -> 0.08627084 | IH5: =SUM(II5+250) -> 2012 | II5: 1762 | IJ5: =Iareva!C5 + 'United Mihili'!C5 + 'Mesjan Hyaa'!C5 + Desaki!C5 + 'Far Lands'!C5 -> 71603249 | IK5: =((IJ5-IJ6)/IJ6) -> 0.013885436 | IL5: =SUM(IJ5/C5) -> 0.010763882 | IS5: =SUM(IT5+250) -> 2012 | IT5: 1762 | IU5: =Verste!C5 + Quidic!C5 + Erkizil!C5 + Ashain!C5 + Ahokini!C5 -> 3.6182168e+08 | IV5: =((IU5-IU6)/IU6) -> 0.0092361296 | IW5: =SUM(IU5/C5) -> 0.054391469
A6: =SUM(B6+250) -> 2011 | B6: 1761 | C6: =Acetoa!C6 + Acrana!C6 + Aetintio!C6 + Ahokini!C6 + Amcha!C6 + Andsaudare!C6 + Anymna!C6 + Aplasia!C6 + Arbiya!C6 + 'Areoix Lie'!C6 + Ashain!C6 + Astye!C6 + Baluyde!C6 + Byllu!C6 + 'Candenat'!C6 + 'Canldives'!C6 + 'Chaenia'!C6 + 'Cloja'!C6 + 'Crila Republic'!C6 + 'Cruthi Anoso'!C6 + 'Curata'!C6 + Dahe!C6 + Danocia!C6 + Darewa!C6 + Desaki!C6 + Deschon!C6 + 'Disal Nila'!C6 + 'Dual Cenryia'!C6 + Ealdorii!C6 + Easuhura!C6 + Eldavpir!C6 + Eldjo!C6 + 'Elja and Munusia'!C6 + Emara!C6 + Enina!C6 + Eparia!C6 + Erkizil!C6 + Estijan!C6 + Etirha!C6 + Etretes!C6 + Exilium!C6 + 'Far Lands'!C6 + 'Feio Lie'!C6 + Fermori!C6 + Finae!C6 + Fincen!C6 + 'Fire Coast'!C6 + Gaeiya!C6 + Galca!C6 + Genaire!C6 + Grazail!C6 + Guise!C6 + Haiza!C6 + Heiso!C6 + Hiwush!C6 + Hkuqo!C6 + Hyelen!C6 + Iainoa!C6 + Iareva!C6 + Ihner!C6 + Ikzen!C6 + Ilicuhe!C6 + Inania!C6 + Inrea!C6 + Iquir!C6 + Isari!C6 + Isnti!C6 + Isuibul!C6 + Jathua!C6 + Jau!C6 + Jshain!C6 + Kaastini!C6 + Koruch!C6 + Kusierna!C6 + Laselteh!C6 + Lasri!C6 + Letan!C6 + Lieri!C6 + Lycroa!C6 + Lydroa!C6 + Maalle!C6 + Mendereide!C6 + 'Merela Sta'!C6 + 'Mesjan Hyaa'!C6 + Metndria!C6 + Migoku!C6 + Myla!C6 + 'New Kizura'!C6 + 'New Misos'!C6 + 'Nheyes Si'!C6 + Nia!C6 + 'Niretui and Anulan'!C6 + 'Niul Spijan'!C6 + 'North Ayre'!C6 + Ocaun!C6 + Ohtina!C6 + Onphello!C6 + Oscairia!C6 + Othya!C6 + Otiiric!C6 + Oyreain!C6 + Ozinia!C6 + Palina!C6 + Peka!C6 + Pelan!C6 + Pelines!C6 + Pelugrotoa!C6 + 'Pha Hii'!C6 + Phuris!C6 + Praesyu!C6 + Prstreula!C6 + 'Pruim Fijan'!C6 + 'Prystr Hii'!C6 + Quidic!C6 + 'Raledria'!C6 + 'Reerica'!C6 + 'Rethern'!C6 + 'Rijan bu'!C6 + 'Rinew'!C6 + 'Rkmepuia'!C6 + 'Rtesania'!C6 + 'Ruylku'!C6 + Saa!C6 + Sadain!C6 + Sanagara!C6 + Sattle!C6 + Selaja!C6 + Seytinemas!C6 + Shinam!C6 + Shomjind!C6 + Siana!C6 + Sivoso!C6 + Slyiaduun!C6 + Stinebar!C6 + Suenan!C6 + Sunsokua!C6 + Taing!C6 + Taniduna!C6 + Taoisia!C6 + Taval!C6 + Terressin!C6 + Tomscilus!C6 + Tonder!C6 + Trevilla!C6 + Trian!C6 + Tvecoca!C6 + Ucrua!C6 + Ukhdari!C6 + Umarcia!C6 + Umendel!C6 + 'United Delet'!C6 + 'United Mihili'!C6 + Urbiqu!C6 + Uularin!C6 + Vayvele!C6 + Veelmit!C6 + Verste!C6 + Verusa!C6 + Vesozata!C6 + Viussi!C6 + Volver!C6 + Walporein!C6 + 'Welenu Fana'!C6 + 'Western Migoku'!C6 + Wundry!C6 + Yaxuto!C6 + Yihnurda!C6 + Yoprioq!C6 + Yutnitu!C6 + Zenashan!C6 + Zhanshe!C6 + Ztesh!C6 -> 6.5858194e+09 | D6: =((C6-C7)/C7) -> 0.010086267 | K6: =SUM(L6+250) -> 2011 | L6: 1761 | M6: =Eldavpir!C6 + Iquir!C6 + Viussi!C6 + Umendel!C6 + 'Reerica'!C6 + Saa!C6 + Sattle!C6 -> 1.0127974e+08 | N6: =((M6-M7)/M7) -> 0.025979554 | O6: =SUM(M6/C6) -> 0.015378457 | V6: =SUM(W6+250) -> 2011 | W6: 1761 | X6: ='Areoix Lie'!C6 + Jau!C6 + Terressin!C6 + Acetoa!C6 + 'Feio Lie'!C6 -> 6.8404422e+08 | Y6: =((X6-X7)/X7) -> 0.0043564915 | Z6: =SUM(X6/C6) -> 0.10386623 | AG6: =SUM(AH6+250) -> 2011 | AH6: 1761 | AI6: =Taniduna!C6 + Jathua!C6 + Deschon!C6 + Pelines!C6 + 'Candenat'!C6 + Othya!C6 + Yoprioq!C6 + Jshain!C6 + 'Fire Coast'!C6 + 'Rijan bu'!C6 + 'Rinew'!C6 + Enina!C6 + Trevilla!C6 -> 2.3609158e+08 | AJ6: =((AI6-AI7)/AI7) -> 0.028144439 | AK6: =SUM(AI6/C6) -> 0.035848474 | AR6: =SUM(AS6+250) -> 2011 | AS6: 1761 | AT6: =Gaeiya!C6 + 'Raledria'!C6 + Arbiya!C6 + Fincen!C6 + 'Curata'!C6 -> 3.0728812e+08 | AU6: =((AT6-AT7)/AT7) -> 0.013364265 | AV6: =SUM(AT6/C6) -> 0.046659057 | BC6: =SUM(BD6+250) -> 2011 | BD6: 1761 | BE6: =Etirha!C6 + Laselteh!C6 + Grazail!C6 + 'Disal Nila'!C6 + Pelan!C6 + Peka!C6 + Guise!C6 -> 1.0534936e+08 | BF6: =((BE6-BE7)/BE7) -> 0.0037164471 | BG6: =SUM(BE6/C6) -> 0.015996393 | BN6: =SUM(BO6+250) -> 2011 | BO6: 1761 | BP6: =Genaire!C6 + 'New Misos'!C6 + Phuris!C6 + Lasri!C6 + Slyiaduun!C6 + Aetintio!C6 + Metndria!C6 + Tomscilus!C6 -> 99521688 | BQ6: =((BP6-BP7)/BP7) -> 0.011769997 | BR6: =SUM(BP6/C6) -> 0.015111512 | BY6: =SUM(BZ6+250) -> 2011 | BZ6: 1761 | CA6: =Ealdorii!C6 + Ukhdari!C6 + Hkuqo!C6 + Acrana!C6 + Zenashan!C6 -> 2.6387328e+08 | CB6: =((CA6-CA7)/CA7) -> 0.0076478151 | CC6: =SUM(CA6/C6) -> 0.040066886 | CJ6: =SUM(CK6+250) -> 2011 | CK6: 1761 | CL6: =Estijan!C6 + Ikzen!C6 + Urbiqu!C6 + Danocia!C6 + Koruch!C6 + 'New Kizura'!C6 + Lydroa!C6 + Fermori!C6 + Uularin!C6 + 'Niul Spijan'!C6 -> 2.9384286e+08 | CM6: =((CL6-CL7)/CL7) -> 0.010142905 | CN6: =SUM(CL6/C6) -> 0.044617509 | CU6: =SUM(CV6+250) -> 2011 | CV6: 1761 | CW6: =Praesyu!C6 + Lycroa!C6 + Emara!C6 + Eldjo!C6 + Easuhura!C6 + Ilicuhe!C6 + Tonder!C6 -> 2.4441242e+08 | CX6: =((CW6-CW7)/CW7) -> 0.0043686325 | CY6: =SUM(CW6/C6) -> 0.037111922 | DF6: =SUM(DG6+250) -> 2011 | DG6: 1761 | DH6: =Verusa!C6 + Darewa!C6 + Siana!C6 + Yaxuto!C6 + 'Merela Sta'!C6 + Palina!C6 -> 1.7156663e+08 | DI6: =((DH6-DH7)/DH7) -> 0.0032016394 | DJ6: =SUM(DH6/C6) -> 0.026050916 | DQ6: =SUM(DR6+250) -> 2011 | DR6: 1761 | DS6: =Sunsokua!C6 + Vayvele!C6 + Selaja!C6 + Sadain!C6 -> 1.9435961e+08 | DT6: =((DS6-DS7)/DS7) -> 0.012682244 | DU6: =SUM(DS6/C6) -> 0.029511834 | EB6: =SUM(EC6+250) -> 2011 | EC6: 1761 | ED6: =Pelugrotoa!C6 + Lieri!C6 + 'Rtesania'!C6 + Ozinia!C6 -> 3.9275871e+08 | EE6: =((ED6-ED7)/ED7) -> 0.0053042601 | EF6: =SUM(ED6/C6) -> 0.05963703 | EM6: =SUM(EN6+250) -> 2011 | EN6: 1761 | EO6: =Ocaun!C6 + 'Dual Cenryia'!C6 + Byllu!C6 + Exilium!C6 + Inrea!C6 + Amcha!C6 + Isnti!C6 + Galca!C6 + Otiiric!C6 + Taing!C6 + 'Cruthi Anoso'!C6 -> 2.7767887e+08 | EP6: =((EO6-EO7)/EO7) -> 0.017197536 | EQ6: =SUM(EO6/C6) -> 0.042163146 | EX6: =SUM(EY6+250) -> 2011 | EY6: 1761 | EZ6: =Sivoso!C6 + Taoisia!C6 + Seytinemas!C6 + Trian!C6 + 'Chaenia'!C6 -> 1.4276246e+08 | FA6: =((EZ6-EZ7)/EZ7) -> 0.007980069 | FB6: =SUM(EZ6/C6) -> 0.021677252 | FI6: =SUM(FJ6+250) -> 2011 | FJ6: 1761 | FK6: =Migoku!C6 + 'Welenu Fana'!C6 + Haiza!C6 + Ucrua!C6 + Ihner!C6 + Oscairia!C6 + Shinam!C6 + 'Ruylku'!C6 + Taval!C6 + 'Western Migoku'!C6 + 'Pruim Fijan'!C6 + 'Canldives'!C6 -> 1.872246e+08 | FL6: =((FK6-FK7)/FK7) -> 0.016159252 | FM6: =SUM(FK6/C6) -> 0.028428444 | FT6: =SUM(FU6+250) -> 2011 | FU6: 1761 | FV6: =Vesozata!C6 + Etretes!C6 + Kusierna!C6 + Eparia!C6 -> 1.4183087e+08 | FW6: =((FV6-FV7)/FV7) -> 0.023028458 | FX6: =SUM(FV6/C6) -> 0.021535797 | GE6: =SUM(GF6+250) -> 2011 | GF6: 1761 | GG6: =Dahe!C6 + Kaastini!C6 + Suenan!C6 + Oyreain!C6 + Sanagara!C6 + 'North Ayre'!C6 + Stinebar!C6 + 'Cloja'!C6 + 'Pha Hii'!C6 + 'Prystr Hii'!C6 -> 1.0217952e+09 | GH6: =((GG6-GG7)/GG7) -> 0.0032538775 | GI6: =SUM(GG6/C6) -> 0.15515081 | GP6: =SUM(GQ6+250) -> 2011 | GQ6: 1761 | GR6: =Maalle!C6 + 'United Delet'!C6 + Ohtina!C6 + Astye!C6 + Prstreula!C6 + Veelmit!C6 + Aplasia!C6 + 'Elja and Munusia'!C6 + Walporein!C6 + 'Crila Republic'!C6 + 'Niretui and Anulan'!C6 + 'Rethern'!C6 + Tvecoca!C6 -> 1.9511863e+08 | GS6: =((GR6-GR7)/GR7) -> 0.013883209 | GT6: =SUM(GR6/C6) -> 0.029627084 | HA6: =SUM(HB6+250) -> 2011 | HB6: 1761 | HC6: =Andsaudare!C6 + Nia!C6 + Umarcia!C6 + Mendereide!C6 + Iainoa!C6 + Isari!C6 + 'Rkmepuia'!C6 + Hiwush!C6 + Isuibul!C6 + Yutnitu!C6 -> 68347257 | HD6: =((HC6-HC7)/HC7) -> 0.012920293 | HE6: =SUM(HC6/C6) -> 0.010377943 | HL6: =SUM(HM6+250) -> 2011 | HM6: 1761 | HN6: =Zhanshe!C6 + Volver!C6 + Finae!C6 + Myla!C6 + 'Nheyes Si'!C6 + Onphello!C6 + Hyelen!C6 -> 1.1726652e+08 | HO6: =((HN6-HN7)/HN7) -> 0.012586932 | HP6: =SUM(HN6/C6) -> 0.017805912 | HW6: =SUM(HX6+250) -> 2011 | HX6: 1761 | HY6: =Yihnurda!C6 + Ztesh!C6 + Wundry!C6 + Anymna!C6 + Shomjind!C6 + Baluyde!C6 + Letan!C6 -> 5.6465938e+08 | HZ6: =((HY6-HY7)/HY7) -> 0.017117542 | IA6: =SUM(HY6/C6) -> 0.085738667 | IH6: =SUM(II6+250) -> 2011 | II6: 1761 | IJ6: =Iareva!C6 + 'United Mihili'!C6 + 'Mesjan Hyaa'!C6 + Desaki!C6 + 'Far Lands'!C6 -> 70622623 | IK6: =((IJ6-IJ7)/IJ7) -> 0.014999957 | IL6: =SUM(IJ6/C6) -> 0.010723437 | IS6: =SUM(IT6+250) -> 2011 | IT6: 1761 | IU6: =Verste!C6 + Quidic!C6 + Erkizil!C6 + Ashain!C6 + Ahokini!C6 -> 3.5851043e+08 | IV6: =((IU6-IU7)/IU7) -> 0.0094050681 | IW6: =SUM(IU6/C6) -> 0.054436724
A7: =SUM(B7+250) -> 2010 | B7: 1760 | C7: =Acetoa!C7 + Acrana!C7 + Aetintio!C7 + Ahokini!C7 + Amcha!C7 + Andsaudare!C7 + Anymna!C7 + Aplasia!C7 + Arbiya!C7 + 'Areoix Lie'!C7 + Ashain!C7 + Astye!C7 + Baluyde!C7 + Byllu!C7 + 'Candenat'!C7 + 'Canldives'!C7 + 'Chaenia'!C7 + 'Cloja'!C7 + 'Crila Republic'!C7 + 'Cruthi Anoso'!C7 + 'Curata'!C7 + Dahe!C7 + Danocia!C7 + Darewa!C7 + Desaki!C7 + Deschon!C7 + 'Disal Nila'!C7 + 'Dual Cenryia'!C7 + Ealdorii!C7 + Easuhura!C7 + Eldavpir!C7 + Eldjo!C7 + 'Elja and Munusia'!C7 + Emara!C7 + Enina!C7 + Eparia!C7 + Erkizil!C7 + Estijan!C7 + Etirha!C7 + Etretes!C7 + Exilium!C7 + 'Far Lands'!C7 + 'Feio Lie'!C7 + Fermori!C7 + Finae!C7 + Fincen!C7 + 'Fire Coast'!C7 + Gaeiya!C7 + Galca!C7 + Genaire!C7 + Grazail!C7 + Guise!C7 + Haiza!C7 + Heiso!C7 + Hiwush!C7 + Hkuqo!C7 + Hyelen!C7 + Iainoa!C7 + Iareva!C7 + Ihner!C7 + Ikzen!C7 + Ilicuhe!C7 + Inania!C7 + Inrea!C7 + Iquir!C7 + Isari!C7 + Isnti!C7 + Isuibul!C7 + Jathua!C7 + Jau!C7 + Jshain!C7 + Kaastini!C7 + Koruch!C7 + Kusierna!C7 + Laselteh!C7 + Lasri!C7 + Letan!C7 + Lieri!C7 + Lycroa!C7 + Lydroa!C7 + Maalle!C7 + Mendereide!C7 + 'Merela Sta'!C7 + 'Mesjan Hyaa'!C7 + Metndria!C7 + Migoku!C7 + Myla!C7 + 'New Kizura'!C7 + 'New Misos'!C7 + 'Nheyes Si'!C7 + Nia!C7 + 'Niretui and Anulan'!C7 + 'Niul Spijan'!C7 + 'North Ayre'!C7 + Ocaun!C7 + Ohtina!C7 + Onphello!C7 + Oscairia!C7 + Othya!C7 + Otiiric!C7 + Oyreain!C7 + Ozinia!C7 + Palina!C7 + Peka!C7 + Pelan!C7 + Pelines!C7 + Pelugrotoa!C7 + 'Pha Hii'!C7 + Phuris!C7 + Praesyu!C7 + Prstreula!C7 + 'Pruim Fijan'!C7 + 'Prystr Hii'!C7 + Quidic!C7 + 'Raledria'!C7 + 'Reerica'!C7 + 'Rethern'!C7 + 'Rijan bu'!C7 + 'Rinew'!C7 + 'Rkmepuia'!C7 + 'Rtesania'!C7 + 'Ruylku'!C7 + Saa!C7 + Sadain!C7 + Sanagara!C7 + Sattle!C7 + Selaja!C7 + Seytinemas!C7 + Shinam!C7 + Shomjind!C7 + Siana!C7 + Sivoso!C7 + Slyiaduun!C7 + Stinebar!C7 + Suenan!C7 + Sunsokua!C7 + Taing!C7 + Taniduna!C7 + Taoisia!C7 + Taval!C7 + Terressin!C7 + Tomscilus!C7 + Tonder!C7 + Trevilla!C7 + Trian!C7 + Tvecoca!C7 + Ucrua!C7 + Ukhdari!C7 + Umarcia!C7 + Umendel!C7 + 'United Delet'!C7 + 'United Mihili'!C7 + Urbiqu!C7 + Uularin!C7 + Vayvele!C7 + Veelmit!C7 + Verste!C7 + Verusa!C7 + Vesozata!C7 + Viussi!C7 + Volver!C7 + Walporein!C7 + 'Welenu Fana'!C7 + 'Western Migoku'!C7 + Wundry!C7 + Yaxuto!C7 + Yihnurda!C7 + Yoprioq!C7 + Yutnitu!C7 + Zenashan!C7 + Zhanshe!C7 + Ztesh!C7 -> 6.5200564e+09 | D7: =((C7-C8)/C8) -> 0.01041509 | K7: =SUM(L7+250) -> 2010 | L7: 1760 | M7: =Eldavpir!C7 + Iquir!C7 + Viussi!C7 + Umendel!C7 + 'Reerica'!C7 + Saa!C7 + Sattle!C7 -> 98715168 | N7: =((M7-M8)/M8) -> 0.026705984 | O7: =SUM(M7/C7) -> 0.015140232 | V7: =SUM(W7+250) -> 2010 | W7: 1760 | X7: ='Areoix Lie'!C7 + Jau!C7 + Terressin!C7 + Acetoa!C7 + 'Feio Lie'!C7 -> 6.8107711e+08 | Y7: =((X7-X8)/X8) -> 0.0054124607 | Z7: =SUM(X7/C7) -> 0.10445878 | AG7: =SUM(AH7+250) -> 2010 | AH7: 1760 | AI7: =Taniduna!C7 + Jathua!C7 + Deschon!C7 + Pelines!C7 + 'Candenat'!C7 + Othya!C7 + Yoprioq!C7 + Jshain!C7 + 'Fire Coast'!C7 + 'Rijan bu'!C7 + 'Rinew'!C7 + Enina!C7 + Trevilla!C7 -> 2.296288e+08 | AJ7: =((AI7-AI8)/AI8) -> 0.028260642 | AK7: =SUM(AI7/C7) -> 0.035218837 | AR7: =SUM(AS7+250) -> 2010 | AS7: 1760 | AT7: =Gaeiya!C7 + 'Raledria'!C7 + Arbiya!C7 + Fincen!C7 + 'Curata'!C7 -> 3.032356e+08 | AU7: =((AT7-AT8)/AT8) -> 0.014973856 | AV7: =SUM(AT7/C7) -> 0.046508126 | BC7: =SUM(BD7+250) -> 2010 | BD7: 1760 | BE7: =Etirha!C7 + Laselteh!C7 + Grazail!C7 + 'Disal Nila'!C7 + Pelan!C7 + Peka!C7 + Guise!C7 -> 1.0495928e+08 | BF7: =((BE7-BE8)/BE8) -> 0.0050655329 | BG7: =SUM(BE7/C7) -> 0.01609791 | BN7: =SUM(BO7+250) -> 2010 | BO7: 1760 | BP7: =Genaire!C7 + 'New Misos'!C7 + Phuris!C7 + Lasri!C7 + Slyiaduun!C7 + Aetintio!C7 + Metndria!C7 + Tomscilus!C7 -> 98363944 | BQ7: =((BP7-BP8)/BP8) -> 0.012024337 | BR7: =SUM(BP7/C7) -> 0.015086364 | BY7: =SUM(BZ7+250) -> 2010 | BZ7: 1760 | CA7: =Ealdorii!C7 + Ukhdari!C7 + Hkuqo!C7 + Acrana!C7 + Zenashan!C7 -> 2.6187054e+08 | CB7: =((CA7-CA8)/CA8) -> 0.0081496764 | CC7: =SUM(CA7/C7) -> 0.040163846 | CJ7: =SUM(CK7+250) -> 2010 | CK7: 1760 | CL7: =Estijan!C7 + Ikzen!C7 + Urbiqu!C7 + Danocia!C7 + Koruch!C7 + 'New Kizura'!C7 + Lydroa!C7 + Fermori!C7 + Uularin!C7 + 'Niul Spijan'!C7 -> 2.9089236e+08 | CM7: =((CL7-CL8)/CL8) -> 0.010162217 | CN7: =SUM(CL7/C7) -> 0.044615007 | CU7: =SUM(CV7+250) -> 2010 | CV7: 1760 | CW7: =Praesyu!C7 + Lycroa!C7 + Emara!C7 + Eldjo!C7 + Easuhura!C7 + Ilicuhe!C7 + Tonder!C7 -> 2.4334931e+08 | CX7: =((CW7-CW8)/CW8) -> 0.0037847273 | CY7: =SUM(CW7/C7) -> 0.037323192 | DF7: =SUM(DG7+250) -> 2010 | DG7: 1760 | DH7: =Verusa!C7 + Darewa!C7 + Siana!C7 + Yaxuto!C7 + 'Merela Sta'!C7 + Palina!C7 -> 1.7101909e+08 | DI7: =((DH7-DH8)/DH8) -> 0.0033967467 | DJ7: =SUM(DH7/C7) -> 0.026229694 | DQ7: =SUM(DR7+250) -> 2010 | DR7: 1760 | DS7: =Sunsokua!C7 + Vayvele!C7 + Selaja!C7 + Sadain!C7 -> 1.9192556e+08 | DT7: =((DS7-DS8)/DS8) -> 0.012553057 | DU7: =SUM(DS7/C7) -> 0.029436181 | EB7: =SUM(EC7+250) -> 2010 | EC7: 1760 | ED7: =Pelugrotoa!C7 + Lieri!C7 + 'Rtesania'!C7 + Ozinia!C7 -> 3.9068641e+08 | EE7: =((ED7-ED8)/ED8) -> 0.0045647949 | EF7: =SUM(ED7/C7) -> 0.05992071 | EM7: =SUM(EN7+250) -> 2010 | EN7: 1760 | EO7: =Ocaun!C7 + 'Dual Cenryia'!C7 + Byllu!C7 + Exilium!C7 + Inrea!C7 + Amcha!C7 + Isnti!C7 + Galca!C7 + Otiiric!C7 + Taing!C7 + 'Cruthi Anoso'!C7 -> 2.7298421e+08 | EP7: =((EO7-EO8)/EO8) -> 0.016990958 | EQ7: =SUM(EO7/C7) -> 0.041868382 | EX7: =SUM(EY7+250) -> 2010 | EY7: 1760 | EZ7: =Sivoso!C7 + Taoisia!C7 + Seytinemas!C7 + Trian!C7 + 'Chaenia'!C7 -> 1.4163223e+08 | FA7: =((EZ7-EZ8)/EZ8) -> 0.0084765572 | FB7: =SUM(EZ7/C7) -> 0.021722547 | FI7: =SUM(FJ7+250) -> 2010 | FJ7: 1760 | FK7: =Migoku!C7 + 'Welenu Fana'!C7 + Haiza!C7 + Ucrua!C7 + Ihner!C7 + Oscairia!C7 + Shinam!C7 + 'Ruylku'!C7 + Taval!C7 + 'Western Migoku'!C7 + 'Pruim Fijan'!C7 + 'Canldives'!C7 -> 1.842473e+08 | FL7: =((FK7-FK8)/FK8) -> 0.018324881 | FM7: =SUM(FK7/C7) -> 0.028258544 | FT7: =SUM(FU7+250) -> 2010 | FU7: 1760 | FV7: =Vesozata!C7 + Etretes!C7 + Kusierna!C7 + Eparia!C7 -> 1.3863825e+08 | FW7: =((FV7-FV8)/FV8) -> 0.022328116 | FX7: =SUM(FV7/C7) -> 0.021263351 | GE7: =SUM(GF7+250) -> 2010 | GF7: 1760 | GG7: =Dahe!C7 + Kaastini!C7 + Suenan!C7 + Oyreain!C7 + Sanagara!C7 + 'North Ayre'!C7 + Stinebar!C7 + 'Cloja'!C7 + 'Pha Hii'!C7 + 'Prystr Hii'!C7 -> 1.0184812e+09 | GH7: =((GG7-GG8)/GG8) -> 0.0032011242 | GI7: =SUM(GG7/C7) -> 0.15620742 | GP7: =SUM(GQ7+250) -> 2010 | GQ7: 1760 | GR7: =Maalle!C7 + 'United Delet'!C7 + Ohtina!C7 + Astye!C7 + Prstreula!C7 + Veelmit!C7 + Aplasia!C7 + 'Elja and Munusia'!C7 + Walporein!C7 + 'Crila Republic'!C7 + 'Niretui and Anulan'!C7 + 'Rethern'!C7 + Tvecoca!C7 -> 1.9244685e+08 | GS7: =((GR7-GR8)/GR8) -> 0.015261575 | GT7: =SUM(GR7/C7) -> 0.029516132 | HA7: =SUM(HB7+250) -> 2010 | HB7: 1760 | HC7: =Andsaudare!C7 + Nia!C7 + Umarcia!C7 + Mendereide!C7 + Iainoa!C7 + Isari!C7 + 'Rkmepuia'!C7 + Hiwush!C7 + Isuibul!C7 + Yutnitu!C7 -> 67475455 | HD7: =((HC7-HC8)/HC8) -> 0.014192735 | HE7: =SUM(HC7/C7) -> 0.010348907 | HL7: =SUM(HM7+250) -> 2010 | HM7: 1760 | HN7: =Zhanshe!C7 + Volver!C7 + Finae!C7 + Myla!C7 + 'Nheyes Si'!C7 + Onphello!C7 + Hyelen!C7 -> 1.1580884e+08 | HO7: =((HN7-HN8)/HN8) -> 0.011775414 | HP7: =SUM(HN7/C7) -> 0.017761939 | HW7: =SUM(HX7+250) -> 2010 | HX7: 1760 | HY7: =Yihnurda!C7 + Ztesh!C7 + Wundry!C7 + Anymna!C7 + Shomjind!C7 + Baluyde!C7 + Letan!C7 -> 5.5515646e+08 | HZ7: =((HY7-HY8)/HY8) -> 0.0180935 | IA7: =SUM(HY7/C7) -> 0.08514596 | IH7: =SUM(II7+250) -> 2010 | II7: 1760 | IJ7: =Iareva!C7 + 'United Mihili'!C7 + 'Mesjan Hyaa'!C7 + Desaki!C7 + 'Far Lands'!C7 -> 69578941 | IK7: =((IJ7-IJ8)/IJ8) -> 0.015564154 | IL7: =SUM(IJ7/C7) -> 0.010671524 | IS7: =SUM(IT7+250) -> 2010 | IT7: 1760 | IU7: =Verste!C7 + Quidic!C7 + Erkizil!C7 + Ashain!C7 + Ahokini!C7 -> 3.5517003e+08 | IV7: =((IU7-IU8)/IU8) -> 0.0095518902 | IW7: =SUM(IU7/C7) -> 0.054473461
A8: =SUM(B8+250) -> 2009 | B8: 1759 | C8: =Acetoa!C8 + Acrana!C8 + Aetintio!C8 + Ahokini!C8 + Amcha!C8 + Andsaudare!C8 + Anymna!C8 + Aplasia!C8 + Arbiya!C8 + 'Areoix Lie'!C8 + Ashain!C8 + Astye!C8 + Baluyde!C8 + Byllu!C8 + 'Candenat'!C8 + 'Canldives'!C8 + 'Chaenia'!C8 + 'Cloja'!C8 + 'Crila Republic'!C8 + 'Cruthi Anoso'!C8 + 'Curata'!C8 + Dahe!C8 + Danocia!C8 + Darewa!C8 + Desaki!C8 + Deschon!C8 + 'Disal Nila'!C8 + 'Dual Cenryia'!C8 + Ealdorii!C8 + Easuhura!C8 + Eldavpir!C8 + Eldjo!C8 + 'Elja and Munusia'!C8 + Emara!C8 + Enina!C8 + Eparia!C8 + Erkizil!C8 + Estijan!C8 + Etirha!C8 + Etretes!C8 + Exilium!C8 + 'Far Lands'!C8 + 'Feio Lie'!C8 + Fermori!C8 + Finae!C8 + Fincen!C8 + 'Fire Coast'!C8 + Gaeiya!C8 + Galca!C8 + Genaire!C8 + Grazail!C8 + Guise!C8 + Haiza!C8 + Heiso!C8 + Hiwush!C8 + Hkuqo!C8 + Hyelen!C8 + Iainoa!C8 + Iareva!C8 + Ihner!C8 + Ikzen!C8 + Ilicuhe!C8 + Inania!C8 + Inrea!C8 + Iquir!C8 + Isari!C8 + Isnti!C8 + Isuibul!C8 + Jathua!C8 + Jau!C8 + Jshain!C8 + Kaastini!C8 + Koruch!C8 + Kusierna!C8 + Laselteh!C8 + Lasri!C8 + Letan!C8 + Lieri!C8 + Lycroa!C8 + Lydroa!C8 + Maalle!C8 + Mendereide!C8 + 'Merela Sta'!C8 + 'Mesjan Hyaa'!C8 + Metndria!C8 + Migoku!C8 + Myla!C8 + 'New Kizura'!C8 + 'New Misos'!C8 + 'Nheyes Si'!C8 + Nia!C8 + 'Niretui and Anulan'!C8 + 'Niul Spijan'!C8 + 'North Ayre'!C8 + Ocaun!C8 + Ohtina!C8 + Onphello!C8 + Oscairia!C8 + Othya!C8 + Otiiric!C8 + Oyreain!C8 + Ozinia!C8 + Palina!C8 + Peka!C8 + Pelan!C8 + Pelines!C8 + Pelugrotoa!C8 + 'Pha Hii'!C8 + Phuris!C8 + Praesyu!C8 + Prstreula!C8 + 'Pruim Fijan'!C8 + 'Prystr Hii'!C8 + Quidic!C8 + 'Raledria'!C8 + 'Reerica'!C8 + 'Rethern'!C8 + 'Rijan bu'!C8 + 'Rinew'!C8 + 'Rkmepuia'!C8 + 'Rtesania'!C8 + 'Ruylku'!C8 + Saa!C8 + Sadain!C8 + Sanagara!C8 + Sattle!C8 + Selaja!C8 + Seytinemas!C8 + Shinam!C8 + Shomjind!C8 + Siana!C8 + Sivoso!C8 + Slyiaduun!C8 + Stinebar!C8 + Suenan!C8 + Sunsokua!C8 + Taing!C8 + Taniduna!C8 + Taoisia!C8 + Taval!C8 + Terressin!C8 + Tomscilus!C8 + Tonder!C8 + Trevilla!C8 + Trian!C8 + Tvecoca!C8 + Ucrua!C8 + Ukhdari!C8 + Umarcia!C8 + Umendel!C8 + 'United Delet'!C8 + 'United Mihili'!C8 + Urbiqu!C8 + Uularin!C8 + Vayvele!C8 + Veelmit!C8 + Verste!C8 + Verusa!C8 + Vesozata!C8 + Viussi!C8 + Volver!C8 + Walporein!C8 + 'Welenu Fana'!C8 + 'Western Migoku'!C8 + Wundry!C8 + Yaxuto!C8 + Yihnurda!C8 + Yoprioq!C8 + Yutnitu!C8 + Zenashan!C8 + Zhanshe!C8 + Ztesh!C8 -> 6.4528494e+09 | D8: =((C8-C9)/C9) -> 0.010869919 | K8: =SUM(L8+250) -> 2009 | L8: 1759 | M8: =Eldavpir!C8 + Iquir!C8 + Viussi!C8 + Umendel!C8 + 'Reerica'!C8 + Saa!C8 + Sattle!C8 -> 96147455 | N8: =((M8-M9)/M9) -> 0.027304652 | O8: =SUM(M8/C8) -> 0.0149 | V8: =SUM(W8+250) -> 2009 | W8: 1759 | X8: ='Areoix Lie'!C8 + Jau!C8 + Terressin!C8 + Acetoa!C8 + 'Feio Lie'!C8 -> 6.7741065e+08 | Y8: =((X8-X9)/X9) -> 0.0054396486 | Z8: =SUM(X8/C8) -> 0.10497853 | AG8: =SUM(AH8+250) -> 2009 | AH8: 1759 | AI8: =Taniduna!C8 + Jathua!C8 + Deschon!C8 + Pelines!C8 + 'Candenat'!C8 + Othya!C8 + Yoprioq!C8 + Jshain!C8 + 'Fire Coast'!C8 + 'Rijan bu'!C8 + 'Rinew'!C8 + Enina!C8 + Trevilla!C8 -> 2.233177e+08 | AJ8: =((AI8-AI9)/AI9) -> 0.02811292 | AK8: =SUM(AI8/C8) -> 0.034607611 | AR8: =SUM(AS8+250) -> 2009 | AS8: 1759 | AT8: =Gaeiya!C8 + 'Raledria'!C8 + Arbiya!C8 + Fincen!C8 + 'Curata'!C8 -> 2.9876199e+08 | AU8: =((AT8-AT9)/AT9) -> 0.019600187 | AV8: =SUM(AT8/C8) -> 0.046299234 | BC8: =SUM(BD8+250) -> 2009 | BD8: 1759 | BE8: =Etirha!C8 + Laselteh!C8 + Grazail!C8 + 'Disal Nila'!C8 + Pelan!C8 + Peka!C8 + Guise!C8 -> 1.0443029e+08 | BF8: =((BE8-BE9)/BE9) -> 0.005002257 | BG8: =SUM(BE8/C8) -> 0.016183593 | BN8: =SUM(BO8+250) -> 2009 | BO8: 1759 | BP8: =Genaire!C8 + 'New Misos'!C8 + Phuris!C8 + Lasri!C8 + Slyiaduun!C8 + Aetintio!C8 + Metndria!C8 + Tomscilus!C8 -> 97195236 | BQ8: =((BP8-BP9)/BP9) -> 0.011379158 | BR8: =SUM(BP8/C8) -> 0.015062375 | BY8: =SUM(BZ8+250) -> 2009 | BZ8: 1759 | CA8: =Ealdorii!C8 + Ukhdari!C8 + Hkuqo!C8 + Acrana!C8 + Zenashan!C8 -> 2.5975363e+08 | CB8: =((CA8-CA9)/CA9) -> 0.0074730561 | CC8: =SUM(CA8/C8) -> 0.040254098 | CJ8: =SUM(CK8+250) -> 2009 | CK8: 1759 | CL8: =Estijan!C8 + Ikzen!C8 + Urbiqu!C8 + Danocia!C8 + Koruch!C8 + 'New Kizura'!C8 + Lydroa!C8 + Fermori!C8 + Uularin!C8 + 'Niul Spijan'!C8 -> 2.8796599e+08 | CM8: =((CL8-CL9)/CL9) -> 0.010970124 | CN8: =SUM(CL8/C8) -> 0.044626176 | CU8: =SUM(CV8+250) -> 2009 | CV8: 1759 | CW8: =Praesyu!C8 + Lycroa!C8 + Emara!C8 + Eldjo!C8 + Easuhura!C8 + Ilicuhe!C8 + Tonder!C8 -> 2.4243178e+08 | CX8: =((CW8-CW9)/CW9) -> 0.0038366785 | CY8: =SUM(CW8/C8) -> 0.037569725 | DF8: =SUM(DG8+250) -> 2009 | DG8: 1759 | DH8: =Verusa!C8 + Darewa!C8 + Siana!C8 + Yaxuto!C8 + 'Merela Sta'!C8 + Palina!C8 -> 1.7044014e+08 | DI8: =((DH8-DH9)/DH9) -> 0.0023771367 | DJ8: =SUM(DH8/C8) -> 0.02641316 | DQ8: =SUM(DR8+250) -> 2009 | DR8: 1759 | DS8: =Sunsokua!C8 + Vayvele!C8 + Selaja!C8 + Sadain!C8 -> 1.8954618e+08 | DT8: =((DS8-DS9)/DS9) -> 0.012211207 | DU8: =SUM(DS8/C8) -> 0.029374028 | EB8: =SUM(EC8+250) -> 2009 | EC8: 1759 | ED8: =Pelugrotoa!C8 + Lieri!C8 + 'Rtesania'!C8 + Ozinia!C8 -> 3.8891111e+08 | EE8: =((ED8-ED9)/ED9) -> 0.0061442778 | EF8: =SUM(ED8/C8) -> 0.060269671 | EM8: =SUM(EN8+250) -> 2009 | EN8: 1759 | EO8: =Ocaun!C8 + 'Dual Cenryia'!C8 + Byllu!C8 + Exilium!C8 + Inrea!C8 + Amcha!C8 + Isnti!C8 + Galca!C8 + Otiiric!C8 + Taing!C8 + 'Cruthi Anoso'!C8 -> 2.6842344e+08 | EP8: =((EO8-EO9)/EO9) -> 0.016755313 | EQ8: =SUM(EO8/C8) -> 0.041597661 | EX8: =SUM(EY8+250) -> 2009 | EY8: 1759 | EZ8: =Sivoso!C8 + Taoisia!C8 + Seytinemas!C8 + Trian!C8 + 'Chaenia'!C8 -> 1.4044177e+08 | FA8: =((EZ8-EZ9)/EZ9) -> 0.0090503904 | FB8: =SUM(EZ8/C8) -> 0.021764303 | FI8: =SUM(FJ8+250) -> 2009 | FJ8: 1759 | FK8: =Migoku!C8 + 'Welenu Fana'!C8 + Haiza!C8 + Ucrua!C8 + Ihner!C8 + Oscairia!C8 + Shinam!C8 + 'Ruylku'!C8 + Taval!C8 + 'Western Migoku'!C8 + 'Pruim Fijan'!C8 + 'Canldives'!C8 -> 1.8093175e+08 | FL8: =((FK8-FK9)/FK9) -> 0.019363582 | FM8: =SUM(FK8/C8) -> 0.028039047 | FT8: =SUM(FU8+250) -> 2009 | FU8: 1759 | FV8: =Vesozata!C8 + Etretes!C8 + Kusierna!C8 + Eparia!C8 -> 1.3561032e+08 | FW8: =((FV8-FV9)/FV9) -> 0.022700081 | FX8: =SUM(FV8/C8) -> 0.021015572 | GE8: =SUM(GF8+250) -> 2009 | GF8: 1759 | GG8: =Dahe!C8 + Kaastini!C8 + Suenan!C8 + Oyreain!C8 + Sanagara!C8 + 'North Ayre'!C8 + Stinebar!C8 + 'Cloja'!C8 + 'Pha Hii'!C8 + 'Prystr Hii'!C8 -> 1.0152313e+09 | GH8: =((GG8-GG9)/GG9) -> 0.0034250602 | GI8: =SUM(GG8/C8) -> 0.1573307 | GP8: =SUM(GQ8+250) -> 2009 | GQ8: 1759 | GR8: =Maalle!C8 + 'United Delet'!C8 + Ohtina!C8 + Astye!C8 + Prstreula!C8 + Veelmit!C8 + Aplasia!C8 + 'Elja and Munusia'!C8 + Walporein!C8 + 'Crila Republic'!C8 + 'Niretui and Anulan'!C8 + 'Rethern'!C8 + Tvecoca!C8 -> 1.8955395e+08 | GS8: =((GR8-GR9)/GR9) -> 0.015829746 | GT8: =SUM(GR8/C8) -> 0.029375233 | HA8: =SUM(HB8+250) -> 2009 | HB8: 1759 | HC8: =Andsaudare!C8 + Nia!C8 + Umarcia!C8 + Mendereide!C8 + Iainoa!C8 + Isari!C8 + 'Rkmepuia'!C8 + Hiwush!C8 + Isuibul!C8 + Yutnitu!C8 -> 66531195 | HD8: =((HC8-HC9)/HC9) -> 0.014659943 | HE8: =SUM(HC8/C8) -> 0.010310359 | HL8: =SUM(HM8+250) -> 2009 | HM8: 1759 | HN8: =Zhanshe!C8 + Volver!C8 + Finae!C8 + Myla!C8 + 'Nheyes Si'!C8 + Onphello!C8 + Hyelen!C8 -> 1.1446102e+08 | HO8: =((HN8-HN9)/HN9) -> 0.012037942 | HP8: =SUM(HN8/C8) -> 0.017738058 | HW8: =SUM(HX8+250) -> 2009 | HX8: 1759 | HY8: =Yihnurda!C8 + Ztesh!C8 + Wundry!C8 + Anymna!C8 + Shomjind!C8 + Baluyde!C8 + Letan!C8 -> 5.4529025e+08 | HZ8: =((HY8-HY9)/HY9) -> 0.018991024 | IA8: =SUM(HY8/C8) -> 0.084503794 | IH8: =SUM(II8+250) -> 2009 | II8: 1759 | IJ8: =Iareva!C8 + 'United Mihili'!C8 + 'Mesjan Hyaa'!C8 + Desaki!C8 + 'Far Lands'!C8 -> 68512601 | IK8: =((IJ8-IJ9)/IJ9) -> 0.016655841 | IL8: =SUM(IJ8/C8) -> 0.010617418 | IS8: =SUM(IT8+250) -> 2009 | IT8: 1759 | IU8: =Verste!C8 + Quidic!C8 + Erkizil!C8 + Ashain!C8 + Ahokini!C8 -> 3.5180959e+08 | IV8: =((IU8-IU9)/IU9) -> 0.0098075328 | IW8: =SUM(IU8/C8) -> 0.054520037
A9: =SUM(B9+250) -> 2008 | B9: 1758 | C9: =Acetoa!C9 + Acrana!C9 + Aetintio!C9 + Ahokini!C9 + Amcha!C9 + Andsaudare!C9 + Anymna!C9 + Aplasia!C9 + Arbiya!C9 + 'Areoix Lie'!C9 + Ashain!C9 + Astye!C9 + Baluyde!C9 + Byllu!C9 + 'Candenat'!C9 + 'Canldives'!C9 + 'Chaenia'!C9 + 'Cloja'!C9 + 'Crila Republic'!C9 + 'Cruthi Anoso'!C9 + 'Curata'!C9 + Dahe!C9 + Danocia!C9 + Darewa!C9 + Desaki!C9 + Deschon!C9 + 'Disal Nila'!C9 + 'Dual Cenryia'!C9 + Ealdorii!C9 + Easuhura!C9 + Eldavpir!C9 + Eldjo!C9 + 'Elja and Munusia'!C9 + Emara!C9 + Enina!C9 + Eparia!C9 + Erkizil!C9 + Estijan!C9 + Etirha!C9 + Etretes!C9 + Exilium!C9 + 'Far Lands'!C9 + 'Feio Lie'!C9 + Fermori!C9 + Finae!C9 + Fincen!C9 + 'Fire Coast'!C9 + Gaeiya!C9 + Galca!C9 + Genaire!C9 + Grazail!C9 + Guise!C9 + Haiza!C9 + Heiso!C9 + Hiwush!C9 + Hkuqo!C9 + Hyelen!C9 + Iainoa!C9 + Iareva!C9 + Ihner!C9 + Ikzen!C9 + Ilicuhe!C9 + Inania!C9 + Inrea!C9 + Iquir!C9 + Isari!C9 + Isnti!C9 + Isuibul!C9 + Jathua!C9 + Jau!C9 + Jshain!C9 + Kaastini!C9 + Koruch!C9 + Kusierna!C9 + Laselteh!C9 + Lasri!C9 + Letan!C9 + Lieri!C9 + Lycroa!C9 + Lydroa!C9 + Maalle!C9 + Mendereide!C9 + 'Merela Sta'!C9 + 'Mesjan Hyaa'!C9 + Metndria!C9 + Migoku!C9 + Myla!C9 + 'New Kizura'!C9 + 'New Misos'!C9 + 'Nheyes Si'!C9 + Nia!C9 + 'Niretui and Anulan'!C9 + 'Niul Spijan'!C9 + 'North Ayre'!C9 + Ocaun!C9 + Ohtina!C9 + Onphello!C9 + Oscairia!C9 + Othya!C9 + Otiiric!C9 + Oyreain!C9 + Ozinia!C9 + Palina!C9 + Peka!C9 + Pelan!C9 + Pelines!C9 + Pelugrotoa!C9 + 'Pha Hii'!C9 + Phuris!C9 + Praesyu!C9 + Prstreula!C9 + 'Pruim Fijan'!C9 + 'Prystr Hii'!C9 + Quidic!C9 + 'Raledria'!C9 + 'Reerica'!C9 + 'Rethern'!C9 + 'Rijan bu'!C9 + 'Rinew'!C9 + 'Rkmepuia'!C9 + 'Rtesania'!C9 + 'Ruylku'!C9 + Saa!C9 + Sadain!C9 + Sanagara!C9 + Sattle!C9 + Selaja!C9 + Seytinemas!C9 + Shinam!C9 + Shomjind!C9 + Siana!C9 + Sivoso!C9 + Slyiaduun!C9 + Stinebar!C9 + Suenan!C9 + Sunsokua!C9 + Taing!C9 + Taniduna!C9 + Taoisia!C9 + Taval!C9 + Terressin!C9 + Tomscilus!C9 + Tonder!C9 + Trevilla!C9 + Trian!C9 + Tvecoca!C9 + Ucrua!C9 + Ukhdari!C9 + Umarcia!C9 + Umendel!C9 + 'United Delet'!C9 + 'United Mihili'!C9 + Urbiqu!C9 + Uularin!C9 + Vayvele!C9 + Veelmit!C9 + Verste!C9 + Verusa!C9 + Vesozata!C9 + Viussi!C9 + Volver!C9 + Walporein!C9 + 'Welenu Fana'!C9 + 'Western Migoku'!C9 + Wundry!C9 + Yaxuto!C9 + Yihnurda!C9 + Yoprioq!C9 + Yutnitu!C9 + Zenashan!C9 + Zhanshe!C9 + Ztesh!C9 -> 6.3834617e+09 | D9: =((C9-C10)/C10) -> 0.011523894 | K9: =SUM(L9+250) -> 2008 | L9: 1758 | M9: =Eldavpir!C9 + Iquir!C9 + Viussi!C9 + Umendel!C9 + 'Reerica'!C9 + Saa!C9 + Sattle!C9 -> 93591959 | N9: =((M9-M10)/M10) -> 0.027573138 | O9: =SUM(M9/C9) -> 0.014661631 | V9: =SUM(W9+250) -> 2008 | W9: 1758 | X9: ='Areoix Lie'!C9 + Jau!C9 + Terressin!C9 + Acetoa!C9 + 'Feio Lie'!C9 -> 6.7374571e+08 | Y9: =((X9-X10)/X10) -> 0.010526759 | Z9: =SUM(X9/C9) -> 0.10554551 | AG9: =SUM(AH9+250) -> 2008 | AH9: 1758 | AI9: =Taniduna!C9 + Jathua!C9 + Deschon!C9 + Pelines!C9 + 'Candenat'!C9 + Othya!C9 + Yoprioq!C9 + Jshain!C9 + 'Fire Coast'!C9 + 'Rijan bu'!C9 + 'Rinew'!C9 + Enina!C9 + Trevilla!C9 -> 2.1721126e+08 | AJ9: =((AI9-AI10)/AI10) -> 0.028131117 | AK9: =SUM(AI9/C9) -> 0.034027189 | AR9: =SUM(AS9+250) -> 2008 | AS9: 1758 | AT9: =Gaeiya!C9 + 'Raledria'!C9 + Arbiya!C9 + Fincen!C9 + 'Curata'!C9 -> 2.9301876e+08 | AU9: =((AT9-AT10)/AT10) -> 0.019088597 | AV9: =SUM(AT9/C9) -> 0.0459028 | BC9: =SUM(BD9+250) -> 2008 | BD9: 1758 | BE9: =Etirha!C9 + Laselteh!C9 + Grazail!C9 + 'Disal Nila'!C9 + Pelan!C9 + Peka!C9 + Guise!C9 -> 1.039105e+08 | BF9: =((BE9-BE10)/BE10) -> 0.0054894647 | BG9: =SUM(BE9/C9) -> 0.01627808 | BN9: =SUM(BO9+250) -> 2008 | BO9: 1758 | BP9: =Genaire!C9 + 'New Misos'!C9 + Phuris!C9 + Lasri!C9 + Slyiaduun!C9 + Aetintio!C9 + Metndria!C9 + Tomscilus!C9 -> 96101680 | BQ9: =((BP9-BP10)/BP10) -> 0.011188655 | BR9: =SUM(BP9/C9) -> 0.015054791 | BY9: =SUM(BZ9+250) -> 2008 | BZ9: 1758 | CA9: =Ealdorii!C9 + Ukhdari!C9 + Hkuqo!C9 + Acrana!C9 + Zenashan!C9 -> 2.5782688e+08 | CB9: =((CA9-CA10)/CA10) -> 0.0071712208 | CC9: =SUM(CA9/C9) -> 0.040389821 | CJ9: =SUM(CK9+250) -> 2008 | CK9: 1758 | CL9: =Estijan!C9 + Ikzen!C9 + Urbiqu!C9 + Danocia!C9 + Koruch!C9 + 'New Kizura'!C9 + Lydroa!C9 + Fermori!C9 + Uularin!C9 + 'Niul Spijan'!C9 -> 2.8484125e+08 | CM9: =((CL9-CL10)/CL10) -> 0.011105783 | CN9: =SUM(CL9/C9) -> 0.044621752 | CU9: =SUM(CV9+250) -> 2008 | CV9: 1758 | CW9: =Praesyu!C9 + Lycroa!C9 + Emara!C9 + Eldjo!C9 + Easuhura!C9 + Ilicuhe!C9 + Tonder!C9 -> 2.415052e+08 | CX9: =((CW9-CW10)/CW10) -> 0.0048915464 | CY9: =SUM(CW9/C9) -> 0.037832952 | DF9: =SUM(DG9+250) -> 2008 | DG9: 1758 | DH9: =Verusa!C9 + Darewa!C9 + Siana!C9 + Yaxuto!C9 + 'Merela Sta'!C9 + Palina!C9 -> 1.7003595e+08 | DI9: =((DH9-DH10)/DH10) -> 0.0021847494 | DJ9: =SUM(DH9/C9) -> 0.026636949 | DQ9: =SUM(DR9+250) -> 2008 | DR9: 1758 | DS9: =Sunsokua!C9 + Vayvele!C9 + Selaja!C9 + Sadain!C9 -> 1.8725951e+08 | DT9: =((DS9-DS10)/DS10) -> 0.011779005 | DU9: =SUM(DS9/C9) -> 0.029335104 | EB9: =SUM(EC9+250) -> 2008 | EC9: 1758 | ED9: =Pelugrotoa!C9 + Lieri!C9 + 'Rtesania'!C9 + Ozinia!C9 -> 3.8653612e+08 | EE9: =((ED9-ED10)/ED10) -> 0.0059996397 | EF9: =SUM(ED9/C9) -> 0.060552744 | EM9: =SUM(EN9+250) -> 2008 | EN9: 1758 | EO9: =Ocaun!C9 + 'Dual Cenryia'!C9 + Byllu!C9 + Exilium!C9 + Inrea!C9 + Amcha!C9 + Isnti!C9 + Galca!C9 + Otiiric!C9 + Taing!C9 + 'Cruthi Anoso'!C9 -> 2.6400004e+08 | EP9: =((EO9-EO10)/EO10) -> 0.016413312 | EQ9: =SUM(EO9/C9) -> 0.041356877 | EX9: =SUM(EY9+250) -> 2008 | EY9: 1758 | EZ9: =Sivoso!C9 + Taoisia!C9 + Seytinemas!C9 + Trian!C9 + 'Chaenia'!C9 -> 1.3918211e+08 | FA9: =((EZ9-EZ10)/EZ10) -> 0.0093277633 | FB9: =SUM(EZ9/C9) -> 0.021803548 | FI9: =SUM(FJ9+250) -> 2008 | FJ9: 1758 | FK9: =Migoku!C9 + 'Welenu Fana'!C9 + Haiza!C9 + Ucrua!C9 + Ihner!C9 + Oscairia!C9 + Shinam!C9 + 'Ruylku'!C9 + Taval!C9 + 'Western Migoku'!C9 + 'Pruim Fijan'!C9 + 'Canldives'!C9 -> 1.7749481e+08 | FL9: =((FK9-FK10)/FK10) -> 0.022375388 | FM9: =SUM(FK9/C9) -> 0.027805417 | FT9: =SUM(FU9+250) -> 2008 | FU9: 1758 | FV9: =Vesozata!C9 + Etretes!C9 + Kusierna!C9 + Eparia!C9 -> 1.3260029e+08 | FW9: =((FV9-FV10)/FV10) -> 0.021178784 | FX9: =SUM(FV9/C9) -> 0.020772473 | GE9: =SUM(GF9+250) -> 2008 | GF9: 1758 | GG9: =Dahe!C9 + Kaastini!C9 + Suenan!C9 + Oyreain!C9 + Sanagara!C9 + 'North Ayre'!C9 + Stinebar!C9 + 'Cloja'!C9 + 'Pha Hii'!C9 + 'Prystr Hii'!C9 -> 1.011766e+09 | GH9: =((GG9-GG10)/GG10) -> 0.0035532132 | GI9: =SUM(GG9/C9) -> 0.15849801 | GP9: =SUM(GQ9+250) -> 2008 | GQ9: 1758 | GR9: =Maalle!C9 + 'United Delet'!C9 + Ohtina!C9 + Astye!C9 + Prstreula!C9 + Veelmit!C9 + Aplasia!C9 + 'Elja and Munusia'!C9 + Walporein!C9 + 'Crila Republic'!C9 + 'Niretui and Anulan'!C9 + 'Rethern'!C9 + Tvecoca!C9 -> 1.8660012e+08 | GS9: =((GR9-GR10)/GR10) -> 0.015576415 | GT9: =SUM(GR9/C9) -> 0.029231807 | HA9: =SUM(HB9+250) -> 2008 | HB9: 1758 | HC9: =Andsaudare!C9 + Nia!C9 + Umarcia!C9 + Mendereide!C9 + Iainoa!C9 + Isari!C9 + 'Rkmepuia'!C9 + Hiwush!C9 + Isuibul!C9 + Yutnitu!C9 -> 65569943 | HD9: =((HC9-HC10)/HC10) -> 0.014209192 | HE9: =SUM(HC9/C9) -> 0.010271847 | HL9: =SUM(HM9+250) -> 2008 | HM9: 1758 | HN9: =Zhanshe!C9 + Volver!C9 + Finae!C9 + Myla!C9 + 'Nheyes Si'!C9 + Onphello!C9 + Hyelen!C9 -> 1.1309953e+08 | HO9: =((HN9-HN10)/HN10) -> 0.012104701 | HP9: =SUM(HN9/C9) -> 0.017717586 | HW9: =SUM(HX9+250) -> 2008 | HX9: 1758 | HY9: =Yihnurda!C9 + Ztesh!C9 + Wundry!C9 + Anymna!C9 + Shomjind!C9 + Baluyde!C9 + Letan!C9 -> 5.3512763e+08 | HZ9: =((HY9-HY10)/HY10) -> 0.019605299 | IA9: =SUM(HY9/C9) -> 0.083830319 | IH9: =SUM(II9+250) -> 2008 | II9: 1758 | IJ9: =Iareva!C9 + 'United Mihili'!C9 + 'Mesjan Hyaa'!C9 + Desaki!C9 + 'Far Lands'!C9 -> 67390161 | IK9: =((IJ9-IJ10)/IJ10) -> 0.019023765 | IL9: =SUM(IJ9/C9) -> 0.010556993 | IS9: =SUM(IT9+250) -> 2008 | IT9: 1758 | IU9: =Verste!C9 + Quidic!C9 + Erkizil!C9 + Ashain!C9 + Ahokini!C9 -> 3.4839272e+08 | IV9: =((IU9-IU10)/IU10) -> 0.0099451671 | IW9: =SUM(IU9/C9) -> 0.054577396
A10: =SUM(B10+250) -> 2007 | B10: 1757 | C10: =Acetoa!C10 + Acrana!C10 + Aetintio!C10 + Ahokini!C10 + Amcha!C10 + Andsaudare!C10 + Anymna!C10 + Aplasia!C10 + Arbiya!C10 + 'Areoix Lie'!C10 + Ashain!C10 + Astye!C10 + Baluyde!C10 + Byllu!C10 + 'Candenat'!C10 + 'Canldives'!C10 + 'Chaenia'!C10 + 'Cloja'!C10 + 'Crila Republic'!C10 + 'Cruthi Anoso'!C10 + 'Curata'!C10 + Dahe!C10 + Danocia!C10 + Darewa!C10 + Desaki!C10 + Deschon!C10 + 'Disal Nila'!C10 + 'Dual Cenryia'!C10 + Ealdorii!C10 + Easuhura!C10 + Eldavpir!C10 + Eldjo!C10 + 'Elja and Munusia'!C10 + Emara!C10 + Enina!C10 + Eparia!C10 + Erkizil!C10 + Estijan!C10 + Etirha!C10 + Etretes!C10 + Exilium!C10 + 'Far Lands'!C10 + 'Feio Lie'!C10 + Fermori!C10 + Finae!C10 + Fincen!C10 + 'Fire Coast'!C10 + Gaeiya!C10 + Galca!C10 + Genaire!C10 + Grazail!C10 + Guise!C10 + Haiza!C10 + Heiso!C10 + Hiwush!C10 + Hkuqo!C10 + Hyelen!C10 + Iainoa!C10 + Iareva!C10 + Ihner!C10 + Ikzen!C10 + Ilicuhe!C10 + Inania!C10 + Inrea!C10 + Iquir!C10 + Isari!C10 + Isnti!C10 + Isuibul!C10 + Jathua!C10 + Jau!C10 + Jshain!C10 + Kaastini!C10 + Koruch!C10 + Kusierna!C10 + Laselteh!C10 + Lasri!C10 + Letan!C10 + Lieri!C10 + Lycroa!C10 + Lydroa!C10 + Maalle!C10 + Mendereide!C10 + 'Merela Sta'!C10 + 'Mesjan Hyaa'!C10 + Metndria!C10 + Migoku!C10 + Myla!C10 + 'New Kizura'!C10 + 'New Misos'!C10 + 'Nheyes Si'!C10 + Nia!C10 + 'Niretui and Anulan'!C10 + 'Niul Spijan'!C10 + 'North Ayre'!C10 + Ocaun!C10 + Ohtina!C10 + Onphello!C10 + Oscairia!C10 + Othya!C10 + Otiiric!C10 + Oyreain!C10 + Ozinia!C10 + Palina!C10 + Peka!C10 + Pelan!C10 + Pelines!C10 + Pelugrotoa!C10 + 'Pha Hii'!C10 + Phuris!C10 + Praesyu!C10 + Prstreula!C10 + 'Pruim Fijan'!C10 + 'Prystr Hii'!C10 + Quidic!C10 + 'Raledria'!C10 + 'Reerica'!C10 + 'Rethern'!C10 + 'Rijan bu'!C10 + 'Rinew'!C10 + 'Rkmepuia'!C10 + 'Rtesania'!C10 + 'Ruylku'!C10 + Saa!C10 + Sadain!C10 + Sanagara!C10 + Sattle!C10 + Selaja!C10 + Seytinemas!C10 + Shinam!C10 + Shomjind!C10 + Siana!C10 + Sivoso!C10 + Slyiaduun!C10 + Stinebar!C10 + Suenan!C10 + Sunsokua!C10 + Taing!C10 + Taniduna!C10 + Taoisia!C10 + Taval!C10 + Terressin!C10 + Tomscilus!C10 + Tonder!C10 + Trevilla!C10 + Trian!C10 + Tvecoca!C10 + Ucrua!C10 + Ukhdari!C10 + Umarcia!C10 + Umendel!C10 + 'United Delet'!C10 + 'United Mihili'!C10 + Urbiqu!C10 + Uularin!C10 + Vayvele!C10 + Veelmit!C10 + Verste!C10 + Verusa!C10 + Vesozata!C10 + Viussi!C10 + Volver!C10 + Walporein!C10 + 'Welenu Fana'!C10 + 'Western Migoku'!C10 + Wundry!C10 + Yaxuto!C10 + Yihnurda!C10 + Yoprioq!C10 + Yutnitu!C10 + Zenashan!C10 + Zhanshe!C10 + Ztesh!C10 -> 6.3107374e+09 | D10: =((C10-C11)/C11) -> 0.011187138 | K10: =SUM(L10+250) -> 2007 | L10: 1757 | M10: =Eldavpir!C10 + Iquir!C10 + Viussi!C10 + Umendel!C10 + 'Reerica'!C10 + Saa!C10 + Sattle!C10 -> 91080582 | N10: =((M10-M11)/M11) -> 0.027098612 | O10: =SUM(M10/C10) -> 0.014432637 | V10: =SUM(W10+250) -> 2007 | W10: 1757 | X10: ='Areoix Lie'!C10 + Jau!C10 + Terressin!C10 + Acetoa!C10 + 'Feio Lie'!C10 -> 6.6672724e+08 | Y10: =((X10-X11)/X11) -> 0.0070756697 | Z10: =SUM(X10/C10) -> 0.10564966 | AG10: =SUM(AH10+250) -> 2007 | AH10: 1757 | AI10: =Taniduna!C10 + Jathua!C10 + Deschon!C10 + Pelines!C10 + 'Candenat'!C10 + Othya!C10 + Yoprioq!C10 + Jshain!C10 + 'Fire Coast'!C10 + 'Rijan bu'!C10 + 'Rinew'!C10 + Enina!C10 + Trevilla!C10 -> 2.1126805e+08 | AJ10: =((AI10-AI11)/AI11) -> 0.027988386 | AK10: =SUM(AI10/C10) -> 0.033477554 | AR10: =SUM(AS10+250) -> 2007 | AS10: 1757 | AT10: =Gaeiya!C10 + 'Raledria'!C10 + Arbiya!C10 + Fincen!C10 + 'Curata'!C10 -> 2.8753021e+08 | AU10: =((AT10-AT11)/AT11) -> 0.017411656 | AV10: =SUM(AT10/C10) -> 0.045562063 | BC10: =SUM(BD10+250) -> 2007 | BD10: 1757 | BE10: =Etirha!C10 + Laselteh!C10 + Grazail!C10 + 'Disal Nila'!C10 + Pelan!C10 + Peka!C10 + Guise!C10 -> 1.033432e+08 | BF10: =((BE10-BE11)/BE11) -> 0.0062106531 | BG10: =SUM(BE10/C10) -> 0.016375772 | BN10: =SUM(BO10+250) -> 2007 | BO10: 1757 | BP10: =Genaire!C10 + 'New Misos'!C10 + Phuris!C10 + Lasri!C10 + Slyiaduun!C10 + Aetintio!C10 + Metndria!C10 + Tomscilus!C10 -> 95038329 | BQ10: =((BP10-BP11)/BP11) -> 0.011011001 | BR10: =SUM(BP10/C10) -> 0.015059782 | BY10: =SUM(BZ10+250) -> 2007 | BZ10: 1757 | CA10: =Ealdorii!C10 + Ukhdari!C10 + Hkuqo!C10 + Acrana!C10 + Zenashan!C10 -> 2.5599111e+08 | CB10: =((CA10-CA11)/CA11) -> 0.0069254623 | CC10: =SUM(CA10/C10) -> 0.040564373 | CJ10: =SUM(CK10+250) -> 2007 | CK10: 1757 | CL10: =Estijan!C10 + Ikzen!C10 + Urbiqu!C10 + Danocia!C10 + Koruch!C10 + 'New Kizura'!C10 + Lydroa!C10 + Fermori!C10 + Uularin!C10 + 'Niul Spijan'!C10 -> 2.8171261e+08 | CM10: =((CL10-CL11)/CL11) -> 0.011045394 | CN10: =SUM(CL10/C10) -> 0.044640204 | CU10: =SUM(CV10+250) -> 2007 | CV10: 1757 | CW10: =Praesyu!C10 + Lycroa!C10 + Emara!C10 + Eldjo!C10 + Easuhura!C10 + Ilicuhe!C10 + Tonder!C10 -> 2.4032961e+08 | CX10: =((CW10-CW11)/CW11) -> 0.0044600011 | CY10: =SUM(CW10/C10) -> 0.038082652 | DF10: =SUM(DG10+250) -> 2007 | DG10: 1757 | DH10: =Verusa!C10 + Darewa!C10 + Siana!C10 + Yaxuto!C10 + 'Merela Sta'!C10 + Palina!C10 -> 1.6966527e+08 | DI10: =((DH10-DH11)/DH11) -> 0.0023450013 | DJ10: =SUM(DH10/C10) -> 0.026885173 | DQ10: =SUM(DR10+250) -> 2007 | DR10: 1757 | DS10: =Sunsokua!C10 + Vayvele!C10 + Selaja!C10 + Sadain!C10 -> 1.8507946e+08 | DT10: =((DS10-DS11)/DS11) -> 0.011254098 | DU10: =SUM(DS10/C10) -> 0.029327708 | EB10: =SUM(EC10+250) -> 2007 | EC10: 1757 | ED10: =Pelugrotoa!C10 + Lieri!C10 + 'Rtesania'!C10 + Ozinia!C10 -> 3.8423087e+08 | EE10: =((ED10-ED11)/ED11) -> 0.0062630912 | EF10: =SUM(ED10/C10) -> 0.060885258 | EM10: =SUM(EN10+250) -> 2007 | EN10: 1757 | EO10: =Ocaun!C10 + 'Dual Cenryia'!C10 + Byllu!C10 + Exilium!C10 + Inrea!C10 + Amcha!C10 + Isnti!C10 + Galca!C10 + Otiiric!C10 + Taing!C10 + 'Cruthi Anoso'!C10 -> 2.5973689e+08 | EP10: =((EO10-EO11)/EO11) -> 0.015747564 | EQ10: =SUM(EO10/C10) -> 0.041157931 | EX10: =SUM(EY10+250) -> 2007 | EY10: 1757 | EZ10: =Sivoso!C10 + Taoisia!C10 + Seytinemas!C10 + Trian!C10 + 'Chaenia'!C10 -> 1.3789585e+08 | FA10: =((EZ10-EZ11)/EZ11) -> 0.0096209346 | FB10: =SUM(EZ10/C10) -> 0.021850989 | FI10: =SUM(FJ10+250) -> 2007 | FJ10: 1757 | FK10: =Migoku!C10 + 'Welenu Fana'!C10 + Haiza!C10 + Ucrua!C10 + Ihner!C10 + Oscairia!C10 + Shinam!C10 + 'Ruylku'!C10 + Taval!C10 + 'Western Migoku'!C10 + 'Pruim Fijan'!C10 + 'Canldives'!C10 -> 1.7361021e+08 | FL10: =((FK10-FK11)/FK11) -> 0.024023967 | FM10: =SUM(FK10/C10) -> 0.02751029 | FT10: =SUM(FU10+250) -> 2007 | FU10: 1757 | FV10: =Vesozata!C10 + Etretes!C10 + Kusierna!C10 + Eparia!C10 -> 1.2985022e+08 | FW10: =((FV10-FV11)/FV11) -> 0.020862543 | FX10: =SUM(FV10/C10) -> 0.020576077 | GE10: =SUM(GF10+250) -> 2007 | GF10: 1757 | GG10: =Dahe!C10 + Kaastini!C10 + Suenan!C10 + Oyreain!C10 + Sanagara!C10 + 'North Ayre'!C10 + Stinebar!C10 + 'Cloja'!C10 + 'Pha Hii'!C10 + 'Prystr Hii'!C10 -> 1.0081837e+09 | GH10: =((GG10-GG11)/GG11) -> 0.0038445193 | GI10: =SUM(GG10/C10) -> 0.15975687 | GP10: =SUM(GQ10+250) -> 2007 | GQ10: 1757 | GR10: =Maalle!C10 + 'United Delet'!C10 + Ohtina!C10 + Astye!C10 + Prstreula!C10 + Veelmit!C10 + Aplasia!C10 + 'Elja and Munusia'!C10 + Walporein!C10 + 'Crila Republic'!C10 + 'Niretui and Anulan'!C10 + 'Rethern'!C10 + Tvecoca!C10 -> 1.8373814e+08 | GS10: =((GR10-GR11)/GR11) -> 0.015601421 | GT10: =SUM(GR10/C10) -> 0.029115162 | HA10: =SUM(HB10+250) -> 2007 | HB10: 1757 | HC10: =Andsaudare!C10 + Nia!C10 + Umarcia!C10 + Mendereide!C10 + Iainoa!C10 + Isari!C10 + 'Rkmepuia'!C10 + Hiwush!C10 + Isuibul!C10 + Yutnitu!C10 -> 64651300 | HD10: =((HC10-HC11)/HC11) -> 0.014000605 | HE10: =SUM(HC10/C10) -> 0.010244651 | HL10: =SUM(HM10+250) -> 2007 | HM10: 1757 | HN10: =Zhanshe!C10 + Volver!C10 + Finae!C10 + Myla!C10 + 'Nheyes Si'!C10 + Onphello!C10 + Hyelen!C10 -> 1.1174687e+08 | HO10: =((HN10-HN11)/HN11) -> 0.012609315 | HP10: =SUM(HN10/C10) -> 0.017707418 | HW10: =SUM(HX10+250) -> 2007 | HX10: 1757 | HY10: =Yihnurda!C10 + Ztesh!C10 + Wundry!C10 + Anymna!C10 + Shomjind!C10 + Baluyde!C10 + Letan!C10 -> 5.2483802e+08 | HZ10: =((HY10-HY11)/HY11) -> 0.020085125 | IA10: =SUM(HY10/C10) -> 0.083165879 | IH10: =SUM(II10+250) -> 2007 | II10: 1757 | IJ10: =Iareva!C10 + 'United Mihili'!C10 + 'Mesjan Hyaa'!C10 + Desaki!C10 + 'Far Lands'!C10 -> 66132080 | IK10: =((IJ10-IJ11)/IJ11) -> 0.019753932 | IL10: =SUM(IJ10/C10) -> 0.010479295 | IS10: =SUM(IT10+250) -> 2007 | IT10: 1757 | IU10: =Verste!C10 + Quidic!C10 + Erkizil!C10 + Ashain!C10 + Ahokini!C10 -> 3.4496201e+08 | IV10: =((IU10-IU11)/IU11) -> 0.010474482 | IW10: =SUM(IU10/C10) -> 0.05466271
A11: =SUM(B11+250) -> 2006 | B11: 1756 | C11: =Acetoa!C11 + Acrana!C11 + Aetintio!C11 + Ahokini!C11 + Amcha!C11 + Andsaudare!C11 + Anymna!C11 + Aplasia!C11 + Arbiya!C11 + 'Areoix Lie'!C11 + Ashain!C11 + Astye!C11 + Baluyde!C11 + Byllu!C11 + 'Candenat'!C11 + 'Canldives'!C11 + 'Chaenia'!C11 + 'Cloja'!C11 + 'Crila Republic'!C11 + 'Cruthi Anoso'!C11 + 'Curata'!C11 + Dahe!C11 + Danocia!C11 + Darewa!C11 + Desaki!C11 + Deschon!C11 + 'Disal Nila'!C11 + 'Dual Cenryia'!C11 + Ealdorii!C11 + Easuhura!C11 + Eldavpir!C11 + Eldjo!C11 + 'Elja and Munusia'!C11 + Emara!C11 + Enina!C11 + Eparia!C11 + Erkizil!C11 + Estijan!C11 + Etirha!C11 + Etretes!C11 + Exilium!C11 + 'Far Lands'!C11 + 'Feio Lie'!C11 + Fermori!C11 + Finae!C11 + Fincen!C11 + 'Fire Coast'!C11 + Gaeiya!C11 + Galca!C11 + Genaire!C11 + Grazail!C11 + Guise!C11 + Haiza!C11 + Heiso!C11 + Hiwush!C11 + Hkuqo!C11 + Hyelen!C11 + Iainoa!C11 + Iareva!C11 + Ihner!C11 + Ikzen!C11 + Ilicuhe!C11 + Inania!C11 + Inrea!C11 + Iquir!C11 + Isari!C11 + Isnti!C11 + Isuibul!C11 + Jathua!C11 + Jau!C11 + Jshain!C11 + Kaastini!C11 + Koruch!C11 + Kusierna!C11 + Laselteh!C11 + Lasri!C11 + Letan!C11 + Lieri!C11 + Lycroa!C11 + Lydroa!C11 + Maalle!C11 + Mendereide!C11 + 'Merela Sta'!C11 + 'Mesjan Hyaa'!C11 + Metndria!C11 + Migoku!C11 + Myla!C11 + 'New Kizura'!C11 + 'New Misos'!C11 + 'Nheyes Si'!C11 + Nia!C11 + 'Niretui and Anulan'!C11 + 'Niul Spijan'!C11 + 'North Ayre'!C11 + Ocaun!C11 + Ohtina!C11 + Onphello!C11 + Oscairia!C11 + Othya!C11 + Otiiric!C11 + Oyreain!C11 + Ozinia!C11 + Palina!C11 + Peka!C11 + Pelan!C11 + Pelines!C11 + Pelugrotoa!C11 + 'Pha Hii'!C11 + Phuris!C11 + Praesyu!C11 + Prstreula!C11 + 'Pruim Fijan'!C11 + 'Prystr Hii'!C11 + Quidic!C11 + 'Raledria'!C11 + 'Reerica'!C11 + 'Rethern'!C11 + 'Rijan bu'!C11 + 'Rinew'!C11 + 'Rkmepuia'!C11 + 'Rtesania'!C11 + 'Ruylku'!C11 + Saa!C11 + Sadain!C11 + Sanagara!C11 + Sattle!C11 + Selaja!C11 + Seytinemas!C11 + Shinam!C11 + Shomjind!C11 + Siana!C11 + Sivoso!C11 + Slyiaduun!C11 + Stinebar!C11 + Suenan!C11 + Sunsokua!C11 + Taing!C11 + Taniduna!C11 + Taoisia!C11 + Taval!C11 + Terressin!C11 + Tomscilus!C11 + Tonder!C11 + Trevilla!C11 + Trian!C11 + Tvecoca!C11 + Ucrua!C11 + Ukhdari!C11 + Umarcia!C11 + Umendel!C11 + 'United Delet'!C11 + 'United Mihili'!C11 + Urbiqu!C11 + Uularin!C11 + Vayvele!C11 + Veelmit!C11 + Verste!C11 + Verusa!C11 + Vesozata!C11 + Viussi!C11 + Volver!C11 + Walporein!C11 + 'Welenu Fana'!C11 + 'Western Migoku'!C11 + Wundry!C11 + Yaxuto!C11 + Yihnurda!C11 + Yoprioq!C11 + Yutnitu!C11 + Zenashan!C11 + Zhanshe!C11 + Ztesh!C11 -> 6.2409194e+09 | D11: =((C11-C12)/C12) -> 0.011344612 | K11: =SUM(L11+250) -> 2006 | L11: 1756 | M11: =Eldavpir!C11 + Iquir!C11 + Viussi!C11 + Umendel!C11 + 'Reerica'!C11 + Saa!C11 + Sattle!C11 -> 88677543 | N11: =((M11-M12)/M12) -> 0.027023199 | O11: =SUM(M11/C11) -> 0.014209051 | V11: =SUM(W11+250) -> 2006 | W11: 1756 | X11: ='Areoix Lie'!C11 + Jau!C11 + Terressin!C11 + Acetoa!C11 + 'Feio Lie'!C11 -> 6.6204284e+08 | Y11: =((X11-X12)/X12) -> 0.0083671114 | Z11: =SUM(X11/C11) -> 0.10608098 | AG11: =SUM(AH11+250) -> 2006 | AH11: 1756 | AI11: =Taniduna!C11 + Jathua!C11 + Deschon!C11 + Pelines!C11 + 'Candenat'!C11 + Othya!C11 + Yoprioq!C11 + Jshain!C11 + 'Fire Coast'!C11 + 'Rijan bu'!C11 + 'Rinew'!C11 + Enina!C11 + Trevilla!C11 -> 2.0551599e+08 | AJ11: =((AI11-AI12)/AI12) -> 0.027793154 | AK11: =SUM(AI11/C11) -> 0.032930403 | AR11: =SUM(AS11+250) -> 2006 | AS11: 1756 | AT11: =Gaeiya!C11 + 'Raledria'!C11 + Arbiya!C11 + Fincen!C11 + 'Curata'!C11 -> 2.8260951e+08 | AU11: =((AT11-AT12)/AT12) -> 0.013061652 | AV11: =SUM(AT11/C11) -> 0.045283314 | BC11: =SUM(BD11+250) -> 2006 | BD11: 1756 | BE11: =Etirha!C11 + Laselteh!C11 + Grazail!C11 + 'Disal Nila'!C11 + Pelan!C11 + Peka!C11 + Guise!C11 -> 1.0270533e+08 | BF11: =((BE11-BE12)/BE12) -> 0.0064182711 | BG11: =SUM(BE11/C11) -> 0.016456763 | BN11: =SUM(BO11+250) -> 2006 | BO11: 1756 | BP11: =Genaire!C11 + 'New Misos'!C11 + Phuris!C11 + Lasri!C11 + Slyiaduun!C11 + Aetintio!C11 + Metndria!C11 + Tomscilus!C11 -> 94003259 | BQ11: =((BP11-BP12)/BP12) -> 0.010786242 | BR11: =SUM(BP11/C11) -> 0.015062406 | BY11: =SUM(BZ11+250) -> 2006 | BZ11: 1756 | CA11: =Ealdorii!C11 + Ukhdari!C11 + Hkuqo!C11 + Acrana!C11 + Zenashan!C11 -> 2.5423044e+08 | CB11: =((CA11-CA12)/CA12) -> 0.0070867831 | CC11: =SUM(CA11/C11) -> 0.040736057 | CJ11: =SUM(CK11+250) -> 2006 | CK11: 1756 | CL11: =Estijan!C11 + Ikzen!C11 + Urbiqu!C11 + Danocia!C11 + Koruch!C11 + 'New Kizura'!C11 + Lydroa!C11 + Fermori!C11 + Uularin!C11 + 'Niul Spijan'!C11 -> 2.7863497e+08 | CM11: =((CL11-CL12)/CL12) -> 0.011931924 | CN11: =SUM(CL11/C11) -> 0.044646463 | CU11: =SUM(CV11+250) -> 2006 | CV11: 1756 | CW11: =Praesyu!C11 + Lycroa!C11 + Emara!C11 + Eldjo!C11 + Easuhura!C11 + Ilicuhe!C11 + Tonder!C11 -> 2.392625e+08 | CX11: =((CW11-CW12)/CW12) -> 0.0045694918 | CY11: =SUM(CW11/C11) -> 0.038337701 | DF11: =SUM(DG11+250) -> 2006 | DG11: 1756 | DH11: =Verusa!C11 + Darewa!C11 + Siana!C11 + Yaxuto!C11 + 'Merela Sta'!C11 + Palina!C11 -> 1.6926833e+08 | DI11: =((DH11-DH12)/DH12) -> 0.0023206407 | DJ11: =SUM(DH11/C11) -> 0.02712234 | DQ11: =SUM(DR11+250) -> 2006 | DR11: 1756 | DS11: =Sunsokua!C11 + Vayvele!C11 + Selaja!C11 + Sadain!C11 -> 1.8301974e+08 | DT11: =((DS11-DS12)/DS12) -> 0.010891817 | DU11: =SUM(DS11/C11) -> 0.029325766 | EB11: =SUM(EC11+250) -> 2006 | EC11: 1756 | ED11: =Pelugrotoa!C11 + Lieri!C11 + 'Rtesania'!C11 + Ozinia!C11 -> 3.8183938e+08 | EE11: =((ED11-ED12)/ED12) -> 0.0069349065 | EF11: =SUM(ED11/C11) -> 0.061183194 | EM11: =SUM(EN11+250) -> 2006 | EN11: 1756 | EO11: =Ocaun!C11 + 'Dual Cenryia'!C11 + Byllu!C11 + Exilium!C11 + Inrea!C11 + Amcha!C11 + Isnti!C11 + Galca!C11 + Otiiric!C11 + Taing!C11 + 'Cruthi Anoso'!C11 -> 2.5571008e+08 | EP11: =((EO11-EO12)/EO12) -> 0.018295544 | EQ11: =SUM(EO11/C11) -> 0.040973143 | EX11: =SUM(EY11+250) -> 2006 | EY11: 1756 | EZ11: =Sivoso!C11 + Taoisia!C11 + Seytinemas!C11 + Trian!C11 + 'Chaenia'!C11 -> 1.3658181e+08 | FA11: =((EZ11-EZ12)/EZ12) -> 0.0099030175 | FB11: =SUM(EZ11/C11) -> 0.021884886 | FI11: =SUM(FJ11+250) -> 2006 | FJ11: 1756 | FK11: =Migoku!C11 + 'Welenu Fana'!C11 + Haiza!C11 + Ucrua!C11 + Ihner!C11 + Oscairia!C11 + Shinam!C11 + 'Ruylku'!C11 + Taval!C11 + 'Western Migoku'!C11 + 'Pruim Fijan'!C11 + 'Canldives'!C11 -> 1.6953726e+08 | FL11: =((FK11-FK12)/FK12) -> 0.025225284 | FM11: =SUM(FK11/C11) -> 0.02716543 | FT11: =SUM(FU11+250) -> 2006 | FU11: 1756 | FV11: =Vesozata!C11 + Etretes!C11 + Kusierna!C11 + Eparia!C11 -> 1.2719657e+08 | FW11: =((FV11-FV12)/FV12) -> 0.020829155 | FX11: =SUM(FV11/C11) -> 0.020381063 | GE11: =SUM(GF11+250) -> 2006 | GF11: 1756 | GG11: =Dahe!C11 + Kaastini!C11 + Suenan!C11 + Oyreain!C11 + Sanagara!C11 + 'North Ayre'!C11 + Stinebar!C11 + 'Cloja'!C11 + 'Pha Hii'!C11 + 'Prystr Hii'!C11 -> 1.0043225e+09 | GH11: =((GG11-GG12)/GG12) -> 0.0038737239 | GI11: =SUM(GG11/C11) -> 0.16092542 | GP11: =SUM(GQ11+250) -> 2006 | GQ11: 1756 | GR11: =Maalle!C11 + 'United Delet'!C11 + Ohtina!C11 + Astye!C11 + Prstreula!C11 + Veelmit!C11 + Aplasia!C11 + 'Elja and Munusia'!C11 + Walporein!C11 + 'Crila Republic'!C11 + 'Niretui and Anulan'!C11 + 'Rethern'!C11 + Tvecoca!C11 -> 1.809156e+08 | GS11: =((GR11-GR12)/GR12) -> 0.015437305 | GT11: =SUM(GR11/C11) -> 0.028988613 | HA11: =SUM(HB11+250) -> 2006 | HB11: 1756 | HC11: =Andsaudare!C11 + Nia!C11 + Umarcia!C11 + Mendereide!C11 + Iainoa!C11 + Isari!C11 + 'Rkmepuia'!C11 + Hiwush!C11 + Isuibul!C11 + Yutnitu!C11 -> 63758641 | HD11: =((HC11-HC12)/HC12) -> 0.014049893 | HE11: =SUM(HC11/C11) -> 0.010216226 | HL11: =SUM(HM11+250) -> 2006 | HM11: 1756 | HN11: =Zhanshe!C11 + Volver!C11 + Finae!C11 + Myla!C11 + 'Nheyes Si'!C11 + Onphello!C11 + Hyelen!C11 -> 1.1035536e+08 | HO11: =((HN11-HN12)/HN12) -> 0.011280233 | HP11: =SUM(HN11/C11) -> 0.017682549 | HW11: =SUM(HX11+250) -> 2006 | HX11: 1756 | HY11: =Yihnurda!C11 + Ztesh!C11 + Wundry!C11 + Anymna!C11 + Shomjind!C11 + Baluyde!C11 + Letan!C11 -> 5.1450414e+08 | HZ11: =((HY11-HY12)/HY12) -> 0.020421748 | IA11: =SUM(HY11/C11) -> 0.082440441 | IH11: =SUM(II11+250) -> 2006 | II11: 1756 | IJ11: =Iareva!C11 + 'United Mihili'!C11 + 'Mesjan Hyaa'!C11 + Desaki!C11 + 'Far Lands'!C11 -> 64851017 | IK11: =((IJ11-IJ12)/IJ12) -> 0.018788554 | IL11: =SUM(IJ11/C11) -> 0.01039126 | IS11: =SUM(IT11+250) -> 2006 | IT11: 1756 | IU11: =Verste!C11 + Quidic!C11 + Erkizil!C11 + Ashain!C11 + Ahokini!C11 -> 3.4138617e+08 | IV11: =((IU11-IU12)/IU12) -> 0.011012627 | IW11: =SUM(IU11/C11) -> 0.054701262
A12: =SUM(B12+250) -> 2005 | B12: 1755 | C12: =Acetoa!C12 + Acrana!C12 + Aetintio!C12 + Ahokini!C12 + Amcha!C12 + Andsaudare!C12 + Anymna!C12 + Aplasia!C12 + Arbiya!C12 + 'Areoix Lie'!C12 + Ashain!C12 + Astye!C12 + Baluyde!C12 + Byllu!C12 + 'Candenat'!C12 + 'Canldives'!C12 + 'Chaenia'!C12 + 'Cloja'!C12 + 'Crila Republic'!C12 + 'Cruthi Anoso'!C12 + 'Curata'!C12 + Dahe!C12 + Danocia!C12 + Darewa!C12 + Desaki!C12 + Deschon!C12 + 'Disal Nila'!C12 + 'Dual Cenryia'!C12 + Ealdorii!C12 + Easuhura!C12 + Eldavpir!C12 + Eldjo!C12 + 'Elja and Munusia'!C12 + Emara!C12 + Enina!C12 + Eparia!C12 + Erkizil!C12 + Estijan!C12 + Etirha!C12 + Etretes!C12 + Exilium!C12 + 'Far Lands'!C12 + 'Feio Lie'!C12 + Fermori!C12 + Finae!C12 + Fincen!C12 + 'Fire Coast'!C12 + Gaeiya!C12 + Galca!C12 + Genaire!C12 + Grazail!C12 + Guise!C12 + Haiza!C12 + Heiso!C12 + Hiwush!C12 + Hkuqo!C12 + Hyelen!C12 + Iainoa!C12 + Iareva!C12 + Ihner!C12 + Ikzen!C12 + Ilicuhe!C12 + Inania!C12 + Inrea!C12 + Iquir!C12 + Isari!C12 + Isnti!C12 + Isuibul!C12 + Jathua!C12 + Jau!C12 + Jshain!C12 + Kaastini!C12 + Koruch!C12 + Kusierna!C12 + Laselteh!C12 + Lasri!C12 + Letan!C12 + Lieri!C12 + Lycroa!C12 + Lydroa!C12 + Maalle!C12 + Mendereide!C12 + 'Merela Sta'!C12 + 'Mesjan Hyaa'!C12 + Metndria!C12 + Migoku!C12 + Myla!C12 + 'New Kizura'!C12 + 'New Misos'!C12 + 'Nheyes Si'!C12 + Nia!C12 + 'Niretui and Anulan'!C12 + 'Niul Spijan'!C12 + 'North Ayre'!C12 + Ocaun!C12 + Ohtina!C12 + Onphello!C12 + Oscairia!C12 + Othya!C12 + Otiiric!C12 + Oyreain!C12 + Ozinia!C12 + Palina!C12 + Peka!C12 + Pelan!C12 + Pelines!C12 + Pelugrotoa!C12 + 'Pha Hii'!C12 + Phuris!C12 + Praesyu!C12 + Prstreula!C12 + 'Pruim Fijan'!C12 + 'Prystr Hii'!C12 + Quidic!C12 + 'Raledria'!C12 + 'Reerica'!C12 + 'Rethern'!C12 + 'Rijan bu'!C12 + 'Rinew'!C12 + 'Rkmepuia'!C12 + 'Rtesania'!C12 + 'Ruylku'!C12 + Saa!C12 + Sadain!C12 + Sanagara!C12 + Sattle!C12 + Selaja!C12 + Seytinemas!C12 + Shinam!C12 + Shomjind!C12 + Siana!C12 + Sivoso!C12 + Slyiaduun!C12 + Stinebar!C12 + Suenan!C12 + Sunsokua!C12 + Taing!C12 + Taniduna!C12 + Taoisia!C12 + Taval!C12 + Terressin!C12 + Tomscilus!C12 + Tonder!C12 + Trevilla!C12 + Trian!C12 + Tvecoca!C12 + Ucrua!C12 + Ukhdari!C12 + Umarcia!C12 + Umendel!C12 + 'United Delet'!C12 + 'United Mihili'!C12 + Urbiqu!C12 + Uularin!C12 + Vayvele!C12 + Veelmit!C12 + Verste!C12 + Verusa!C12 + Vesozata!C12 + Viussi!C12 + Volver!C12 + Walporein!C12 + 'Welenu Fana'!C12 + 'Western Migoku'!C12 + Wundry!C12 + Yaxuto!C12 + Yihnurda!C12 + Yoprioq!C12 + Yutnitu!C12 + Zenashan!C12 + Zhanshe!C12 + Ztesh!C12 -> 6.1709128e+09 | D12: =((C12-C13)/C13) -> 0.011302747 | K12: =SUM(L12+250) -> 2005 | L12: 1755 | M12: =Eldavpir!C12 + Iquir!C12 + Viussi!C12 + Umendel!C12 + 'Reerica'!C12 + Saa!C12 + Sattle!C12 -> 86344246 | N12: =((M12-M13)/M13) -> 0.026662972 | O12: =SUM(M12/C12) -> 0.013992135 | V12: =SUM(W12+250) -> 2005 | W12: 1755 | X12: ='Areoix Lie'!C12 + Jau!C12 + Terressin!C12 + Acetoa!C12 + 'Feio Lie'!C12 -> 6.5654942e+08 | Y12: =((X12-X13)/X13) -> 0.0083968998 | Z12: =SUM(X12/C12) -> 0.10639421 | AG12: =SUM(AH12+250) -> 2005 | AH12: 1755 | AI12: =Taniduna!C12 + Jathua!C12 + Deschon!C12 + Pelines!C12 + 'Candenat'!C12 + Othya!C12 + Yoprioq!C12 + Jshain!C12 + 'Fire Coast'!C12 + 'Rijan bu'!C12 + 'Rinew'!C12 + Enina!C12 + Trevilla!C12 -> 1.9995851e+08 | AJ12: =((AI12-AI13)/AI13) -> 0.027679314 | AK12: =SUM(AI12/C12) -> 0.032403393 | AR12: =SUM(AS12+250) -> 2005 | AS12: 1755 | AT12: =Gaeiya!C12 + 'Raledria'!C12 + Arbiya!C12 + Fincen!C12 + 'Curata'!C12 -> 2.7896576e+08 | AU12: =((AT12-AT13)/AT13) -> 0.011812672 | AV12: =SUM(AT12/C12) -> 0.045206564 | BC12: =SUM(BD12+250) -> 2005 | BD12: 1755 | BE12: =Etirha!C12 + Laselteh!C12 + Grazail!C12 + 'Disal Nila'!C12 + Pelan!C12 + Peka!C12 + Guise!C12 -> 1.0205035e+08 | BF12: =((BE12-BE13)/BE13) -> 0.0072592955 | BG12: =SUM(BE12/C12) -> 0.016537318 | BN12: =SUM(BO12+250) -> 2005 | BO12: 1755 | BP12: =Genaire!C12 + 'New Misos'!C12 + Phuris!C12 + Lasri!C12 + Slyiaduun!C12 + Aetintio!C12 + Metndria!C12 + Tomscilus!C12 -> 93000137 | BQ12: =((BP12-BP13)/BP13) -> 0.011930116 | BR12: =SUM(BP12/C12) -> 0.015070726 | BY12: =SUM(BZ12+250) -> 2005 | BZ12: 1755 | CA12: =Ealdorii!C12 + Ukhdari!C12 + Hkuqo!C12 + Acrana!C12 + Zenashan!C12 -> 2.5244145e+08 | CB12: =((CA12-CA13)/CA13) -> 0.0073003499 | CC12: =SUM(CA12/C12) -> 0.040908283 | CJ12: =SUM(CK12+250) -> 2005 | CK12: 1755 | CL12: =Estijan!C12 + Ikzen!C12 + Urbiqu!C12 + Danocia!C12 + Koruch!C12 + 'New Kizura'!C12 + Lydroa!C12 + Fermori!C12 + Uularin!C12 + 'Niul Spijan'!C12 -> 2.7534952e+08 | CM12: =((CL12-CL13)/CL13) -> 0.011005836 | CN12: =SUM(CL12/C12) -> 0.04462055 | CU12: =SUM(CV12+250) -> 2005 | CV12: 1755 | CW12: =Praesyu!C12 + Lycroa!C12 + Emara!C12 + Eldjo!C12 + Easuhura!C12 + Ilicuhe!C12 + Tonder!C12 -> 2.3817417e+08 | CX12: =((CW12-CW13)/CW13) -> 0.0053790595 | CY12: =SUM(CW12/C12) -> 0.038596263 | DF12: =SUM(DG12+250) -> 2005 | DG12: 1755 | DH12: =Verusa!C12 + Darewa!C12 + Siana!C12 + Yaxuto!C12 + 'Merela Sta'!C12 + Palina!C12 -> 1.6887643e+08 | DI12: =((DH12-DH13)/DH13) -> 0.0021617307 | DJ12: =SUM(DH12/C12) -> 0.027366524 | DQ12: =SUM(DR12+250) -> 2005 | DR12: 1755 | DS12: =Sunsokua!C12 + Vayvele!C12 + Selaja!C12 + Sadain!C12 -> 1.810478e+08 | DT12: =((DS12-DS13)/DS13) -> 0.010668039 | DU12: =SUM(DS12/C12) -> 0.029338901 | EB12: =SUM(EC12+250) -> 2005 | EC12: 1755 | ED12: =Pelugrotoa!C12 + Lieri!C12 + 'Rtesania'!C12 + Ozinia!C12 -> 3.792096e+08 | EE12: =((ED12-ED13)/ED13) -> 0.0059073021 | EF12: =SUM(ED12/C12) -> 0.061451135 | EM12: =SUM(EN12+250) -> 2005 | EN12: 1755 | EO12: =Ocaun!C12 + 'Dual Cenryia'!C12 + Byllu!C12 + Exilium!C12 + Inrea!C12 + Amcha!C12 + Isnti!C12 + Galca!C12 + Otiiric!C12 + Taing!C12 + 'Cruthi Anoso'!C12 -> 2.5111578e+08 | EP12: =((EO12-EO13)/EO13) -> 0.018640863 | EQ12: =SUM(EO12/C12) -> 0.040693459 | EX12: =SUM(EY12+250) -> 2005 | EY12: 1755 | EZ12: =Sivoso!C12 + Taoisia!C12 + Seytinemas!C12 + Trian!C12 + 'Chaenia'!C12 -> 1.352425e+08 | FA12: =((EZ12-EZ13)/EZ13) -> 0.010076051 | FB12: =SUM(EZ12/C12) -> 0.021916126 | FI12: =SUM(FJ12+250) -> 2005 | FJ12: 1755 | FK12: =Migoku!C12 + 'Welenu Fana'!C12 + Haiza!C12 + Ucrua!C12 + Ihner!C12 + Oscairia!C12 + Shinam!C12 + 'Ruylku'!C12 + Taval!C12 + 'Western Migoku'!C12 + 'Pruim Fijan'!C12 + 'Canldives'!C12 -> 1.6536586e+08 | FL12: =((FK12-FK13)/FK13) -> 0.025853351 | FM12: =SUM(FK12/C12) -> 0.026797633 | FT12: =SUM(FU12+250) -> 2005 | FU12: 1755 | FV12: =Vesozata!C12 + Etretes!C12 + Kusierna!C12 + Eparia!C12 -> 1.2460123e+08 | FW12: =((FV12-FV13)/FV13) -> 0.020783034 | FX12: =SUM(FV12/C12) -> 0.020191702 | GE12: =SUM(GF12+250) -> 2005 | GF12: 1755 | GG12: =Dahe!C12 + Kaastini!C12 + Suenan!C12 + Oyreain!C12 + Sanagara!C12 + 'North Ayre'!C12 + Stinebar!C12 + 'Cloja'!C12 + 'Pha Hii'!C12 + 'Prystr Hii'!C12 -> 1.0004471e+09 | GH12: =((GG12-GG13)/GG13) -> 0.0040365626 | GI12: =SUM(GG12/C12) -> 0.16212303 | GP12: =SUM(GQ12+250) -> 2005 | GQ12: 1755 | GR12: =Maalle!C12 + 'United Delet'!C12 + Ohtina!C12 + Astye!C12 + Prstreula!C12 + Veelmit!C12 + Aplasia!C12 + 'Elja and Munusia'!C12 + Walporein!C12 + 'Crila Republic'!C12 + 'Niretui and Anulan'!C12 + 'Rethern'!C12 + Tvecoca!C12 -> 1.7816521e+08 | GS12: =((GR12-GR13)/GR13) -> 0.015309964 | GT12: =SUM(GR12/C12) -> 0.028871776 | HA12: =SUM(HB12+250) -> 2005 | HB12: 1755 | HC12: =Andsaudare!C12 + Nia!C12 + Umarcia!C12 + Mendereide!C12 + Iainoa!C12 + Isari!C12 + 'Rkmepuia'!C12 + Hiwush!C12 + Isuibul!C12 + Yutnitu!C12 -> 62875250 | HD12: =((HC12-HC13)/HC13) -> 0.014825053 | HE12: =SUM(HC12/C12) -> 0.010188971 | HL12: =SUM(HM12+250) -> 2005 | HM12: 1755 | HN12: =Zhanshe!C12 + Volver!C12 + Finae!C12 + Myla!C12 + 'Nheyes Si'!C12 + Onphello!C12 + Hyelen!C12 -> 1.0912441e+08 | HO12: =((HN12-HN13)/HN13) -> 0.010400931 | HP12: =SUM(HN12/C12) -> 0.017683675 | HW12: =SUM(HX12+250) -> 2005 | HX12: 1755 | HY12: =Yihnurda!C12 + Ztesh!C12 + Wundry!C12 + Anymna!C12 + Shomjind!C12 + Baluyde!C12 + Letan!C12 -> 5.0420735e+08 | HZ12: =((HY12-HY13)/HY13) -> 0.020582277 | IA12: =SUM(HY12/C12) -> 0.081707094 | IH12: =SUM(II12+250) -> 2005 | II12: 1755 | IJ12: =Iareva!C12 + 'United Mihili'!C12 + 'Mesjan Hyaa'!C12 + Desaki!C12 + 'Far Lands'!C12 -> 63655031 | IK12: =((IJ12-IJ13)/IJ13) -> 0.01813991 | IL12: =SUM(IJ12/C12) -> 0.010315335 | IS12: =SUM(IT12+250) -> 2005 | IT12: 1755 | IU12: =Verste!C12 + Quidic!C12 + Erkizil!C12 + Ashain!C12 + Ahokini!C12 -> 3.3766756e+08 | IV12: =((IU12-IU13)/IU13) -> 0.01167766 | IW12: =SUM(IU12/C12) -> 0.054719224
A13: =SUM(B13+250) -> 2004 | B13: 1754 | C13: =Acetoa!C13 + Acrana!C13 + Aetintio!C13 + Ahokini!C13 + Amcha!C13 + Andsaudare!C13 + Anymna!C13 + Aplasia!C13 + Arbiya!C13 + 'Areoix Lie'!C13 + Ashain!C13 + Astye!C13 + Baluyde!C13 + Byllu!C13 + 'Candenat'!C13 + 'Canldives'!C13 + 'Chaenia'!C13 + 'Cloja'!C13 + 'Crila Republic'!C13 + 'Cruthi Anoso'!C13 + 'Curata'!C13 + Dahe!C13 + Danocia!C13 + Darewa!C13 + Desaki!C13 + Deschon!C13 + 'Disal Nila'!C13 + 'Dual Cenryia'!C13 + Ealdorii!C13 + Easuhura!C13 + Eldavpir!C13 + Eldjo!C13 + 'Elja and Munusia'!C13 + Emara!C13 + Enina!C13 + Eparia!C13 + Erkizil!C13 + Estijan!C13 + Etirha!C13 + Etretes!C13 + Exilium!C13 + 'Far Lands'!C13 + 'Feio Lie'!C13 + Fermori!C13 + Finae!C13 + Fincen!C13 + 'Fire Coast'!C13 + Gaeiya!C13 + Galca!C13 + Genaire!C13 + Grazail!C13 + Guise!C13 + Haiza!C13 + Heiso!C13 + Hiwush!C13 + Hkuqo!C13 + Hyelen!C13 + Iainoa!C13 + Iareva!C13 + Ihner!C13 + Ikzen!C13 + Ilicuhe!C13 + Inania!C13 + Inrea!C13 + Iquir!C13 + Isari!C13 + Isnti!C13 + Isuibul!C13 + Jathua!C13 + Jau!C13 + Jshain!C13 + Kaastini!C13 + Koruch!C13 + Kusierna!C13 + Laselteh!C13 + Lasri!C13 + Letan!C13 + Lieri!C13 + Lycroa!C13 + Lydroa!C13 + Maalle!C13 + Mendereide!C13 + 'Merela Sta'!C13 + 'Mesjan Hyaa'!C13 + Metndria!C13 + Migoku!C13 + Myla!C13 + 'New Kizura'!C13 + 'New Misos'!C13 + 'Nheyes Si'!C13 + Nia!C13 + 'Niretui and Anulan'!C13 + 'Niul Spijan'!C13 + 'North Ayre'!C13 + Ocaun!C13 + Ohtina!C13 + Onphello!C13 + Oscairia!C13 + Othya!C13 + Otiiric!C13 + Oyreain!C13 + Ozinia!C13 + Palina!C13 + Peka!C13 + Pelan!C13 + Pelines!C13 + Pelugrotoa!C13 + 'Pha Hii'!C13 + Phuris!C13 + Praesyu!C13 + Prstreula!C13 + 'Pruim Fijan'!C13 + 'Prystr Hii'!C13 + Quidic!C13 + 'Raledria'!C13 + 'Reerica'!C13 + 'Rethern'!C13 + 'Rijan bu'!C13 + 'Rinew'!C13 + 'Rkmepuia'!C13 + 'Rtesania'!C13 + 'Ruylku'!C13 + Saa!C13 + Sadain!C13 + Sanagara!C13 + Sattle!C13 + Selaja!C13 + Seytinemas!C13 + Shinam!C13 + Shomjind!C13 + Siana!C13 + Sivoso!C13 + Slyiaduun!C13 + Stinebar!C13 + Suenan!C13 + Sunsokua!C13 + Taing!C13 + Taniduna!C13 + Taoisia!C13 + Taval!C13 + Terressin!C13 + Tomscilus!C13 + Tonder!C13 + Trevilla!C13 + Trian!C13 + Tvecoca!C13 + Ucrua!C13 + Ukhdari!C13 + Umarcia!C13 + Umendel!C13 + 'United Delet'!C13 + 'United Mihili'!C13 + Urbiqu!C13 + Uularin!C13 + Vayvele!C13 + Veelmit!C13 + Verste!C13 + Verusa!C13 + Vesozata!C13 + Viussi!C13 + Volver!C13 + Walporein!C13 + 'Welenu Fana'!C13 + 'Western Migoku'!C13 + Wundry!C13 + Yaxuto!C13 + Yihnurda!C13 + Yoprioq!C13 + Yutnitu!C13 + Zenashan!C13 + Zhanshe!C13 + Ztesh!C13 -> 6.101944e+09 | D13: =((C13-C14)/C14) -> 0.011388603 | K13: =SUM(L13+250) -> 2004 | L13: 1754 | M13: =Eldavpir!C13 + Iquir!C13 + Viussi!C13 + Umendel!C13 + 'Reerica'!C13 + Saa!C13 + Sattle!C13 -> 84101841 | N13: =((M13-M14)/M14) -> 0.026939808 | O13: =SUM(M13/C13) -> 0.013782795 | V13: =SUM(W13+250) -> 2004 | W13: 1754 | X13: ='Areoix Lie'!C13 + Jau!C13 + Terressin!C13 + Acetoa!C13 + 'Feio Lie'!C13 -> 6.5108234e+08 | Y13: =((X13-X14)/X14) -> 0.0086707474 | Z13: =SUM(X13/C13) -> 0.10670081 | AG13: =SUM(AH13+250) -> 2004 | AH13: 1754 | AI13: =Taniduna!C13 + Jathua!C13 + Deschon!C13 + Pelines!C13 + 'Candenat'!C13 + Othya!C13 + Yoprioq!C13 + Jshain!C13 + 'Fire Coast'!C13 + 'Rijan bu'!C13 + 'Rinew'!C13 + Enina!C13 + Trevilla!C13 -> 1.9457287e+08 | AJ13: =((AI13-AI14)/AI14) -> 0.027517144 | AK13: =SUM(AI13/C13) -> 0.03188703 | AR13: =SUM(AS13+250) -> 2004 | AS13: 1754 | AT13: =Gaeiya!C13 + 'Raledria'!C13 + Arbiya!C13 + Fincen!C13 + 'Curata'!C13 -> 2.757089e+08 | AU13: =((AT13-AT14)/AT14) -> 0.010480093 | AV13: =SUM(AT13/C13) -> 0.045183781 | BC13: =SUM(BD13+250) -> 2004 | BD13: 1754 | BE13: =Etirha!C13 + Laselteh!C13 + Grazail!C13 + 'Disal Nila'!C13 + Pelan!C13 + Peka!C13 + Guise!C13 -> 1.0131487e+08 | BF13: =((BE13-BE14)/BE14) -> 0.0078030218 | BG13: =SUM(BE13/C13) -> 0.016603704 | BN13: =SUM(BO13+250) -> 2004 | BO13: 1754 | BP13: =Genaire!C13 + 'New Misos'!C13 + Phuris!C13 + Lasri!C13 + Slyiaduun!C13 + Aetintio!C13 + Metndria!C13 + Tomscilus!C13 -> 91903715 | BQ13: =((BP13-BP14)/BP14) -> 0.012598744 | BR13: =SUM(BP13/C13) -> 0.015061383 | BY13: =SUM(BZ13+250) -> 2004 | BZ13: 1754 | CA13: =Ealdorii!C13 + Ukhdari!C13 + Hkuqo!C13 + Acrana!C13 + Zenashan!C13 -> 2.5061189e+08 | CB13: =((CA13-CA14)/CA14) -> 0.0076523895 | CC13: =SUM(CA13/C13) -> 0.041070828 | CJ13: =SUM(CK13+250) -> 2004 | CK13: 1754 | CL13: =Estijan!C13 + Ikzen!C13 + Urbiqu!C13 + Danocia!C13 + Koruch!C13 + 'New Kizura'!C13 + Lydroa!C13 + Fermori!C13 + Uularin!C13 + 'Niul Spijan'!C13 -> 2.7235206e+08 | CM13: =((CL13-CL14)/CL14) -> 0.0099036529 | CN13: =SUM(CL13/C13) -> 0.044633654 | CU13: =SUM(CV13+250) -> 2004 | CV13: 1754 | CW13: =Praesyu!C13 + Lycroa!C13 + Emara!C13 + Eldjo!C13 + Easuhura!C13 + Ilicuhe!C13 + Tonder!C13 -> 2.3689987e+08 | CX13: =((CW13-CW14)/CW14) -> 0.0062525435 | CY13: =SUM(CW13/C13) -> 0.038823671 | DF13: =SUM(DG13+250) -> 2004 | DG13: 1754 | DH13: =Verusa!C13 + Darewa!C13 + Siana!C13 + Yaxuto!C13 + 'Merela Sta'!C13 + Palina!C13 -> 1.6851216e+08 | DI13: =((DH13-DH14)/DH14) -> 0.0026569333 | DJ13: =SUM(DH13/C13) -> 0.027616142 | DQ13: =SUM(DR13+250) -> 2004 | DR13: 1754 | DS13: =Sunsokua!C13 + Vayvele!C13 + Selaja!C13 + Sadain!C13 -> 1.7913676e+08 | DT13: =((DS13-DS14)/DS14) -> 0.010548585 | DU13: =SUM(DS13/C13) -> 0.029357326 | EB13: =SUM(EC13+250) -> 2004 | EC13: 1754 | ED13: =Pelugrotoa!C13 + Lieri!C13 + 'Rtesania'!C13 + Ozinia!C13 -> 3.7698265e+08 | EE13: =((ED13-ED14)/ED14) -> 0.0059845119 | EF13: =SUM(ED13/C13) -> 0.061780745 | EM13: =SUM(EN13+250) -> 2004 | EN13: 1754 | EO13: =Ocaun!C13 + 'Dual Cenryia'!C13 + Byllu!C13 + Exilium!C13 + Inrea!C13 + Amcha!C13 + Isnti!C13 + Galca!C13 + Otiiric!C13 + Taing!C13 + 'Cruthi Anoso'!C13 -> 2.4652043e+08 | EP13: =((EO13-EO14)/EO14) -> 0.018512593 | EQ13: =SUM(EO13/C13) -> 0.04040031 | EX13: =SUM(EY13+250) -> 2004 | EY13: 1754 | EZ13: =Sivoso!C13 + Taoisia!C13 + Seytinemas!C13 + Trian!C13 + 'Chaenia'!C13 -> 1.3389338e+08 | FA13: =((EZ13-EZ14)/EZ14) -> 0.010140795 | FB13: =SUM(EZ13/C13) -> 0.021942742 | FI13: =SUM(FJ13+250) -> 2004 | FJ13: 1754 | FK13: =Migoku!C13 + 'Welenu Fana'!C13 + Haiza!C13 + Ucrua!C13 + Ihner!C13 + Oscairia!C13 + Shinam!C13 + 'Ruylku'!C13 + Taval!C13 + 'Western Migoku'!C13 + 'Pruim Fijan'!C13 + 'Canldives'!C13 -> 1.6119834e+08 | FL13: =((FK13-FK14)/FK14) -> 0.026040253 | FM13: =SUM(FK13/C13) -> 0.026417538 | FT13: =SUM(FU13+250) -> 2004 | FU13: 1754 | FV13: =Vesozata!C13 + Etretes!C13 + Kusierna!C13 + Eparia!C13 -> 1.2206437e+08 | FW13: =((FV13-FV14)/FV14) -> 0.021007043 | FX13: =SUM(FV13/C13) -> 0.020004177 | GE13: =SUM(GF13+250) -> 2004 | GF13: 1754 | GG13: =Dahe!C13 + Kaastini!C13 + Suenan!C13 + Oyreain!C13 + Sanagara!C13 + 'North Ayre'!C13 + Stinebar!C13 + 'Cloja'!C13 + 'Pha Hii'!C13 + 'Prystr Hii'!C13 -> 9.9642496e+08 | GH13: =((GG13-GG14)/GG14) -> 0.0043002336 | GI13: =SUM(GG13/C13) -> 0.16329631 | GP13: =SUM(GQ13+250) -> 2004 | GQ13: 1754 | GR13: =Maalle!C13 + 'United Delet'!C13 + Ohtina!C13 + Astye!C13 + Prstreula!C13 + Veelmit!C13 + Aplasia!C13 + 'Elja and Munusia'!C13 + Walporein!C13 + 'Crila Republic'!C13 + 'Niretui and Anulan'!C13 + 'Rethern'!C13 + Tvecoca!C13 -> 1.7547864e+08 | GS13: =((GR13-GR14)/GR14) -> 0.015475649 | GT13: =SUM(GR13/C13) -> 0.028757825 | HA13: =SUM(HB13+250) -> 2004 | HB13: 1754 | HC13: =Andsaudare!C13 + Nia!C13 + Umarcia!C13 + Mendereide!C13 + Iainoa!C13 + Isari!C13 + 'Rkmepuia'!C13 + Hiwush!C13 + Isuibul!C13 + Yutnitu!C13 -> 61956738 | HD13: =((HC13-HC14)/HC14) -> 0.015953183 | HE13: =SUM(HC13/C13) -> 0.010153606 | HL13: =SUM(HM13+250) -> 2004 | HM13: 1754 | HN13: =Zhanshe!C13 + Volver!C13 + Finae!C13 + Myla!C13 + 'Nheyes Si'!C13 + Onphello!C13 + Hyelen!C13 -> 1.080011e+08 | HO13: =((HN13-HN14)/HN14) -> 0.01092611 | HP13: =SUM(HN13/C13) -> 0.017699458 | HW13: =SUM(HX13+250) -> 2004 | HX13: 1754 | HY13: =Yihnurda!C13 + Ztesh!C13 + Wundry!C13 + Anymna!C13 + Shomjind!C13 + Baluyde!C13 + Letan!C13 -> 4.940389e+08 | HZ13: =((HY13-HY14)/HY14) -> 0.020786878 | IA13: =SUM(HY13/C13) -> 0.080964181 | IH13: =SUM(II13+250) -> 2004 | II13: 1754 | IJ13: =Iareva!C13 + 'United Mihili'!C13 + 'Mesjan Hyaa'!C13 + Desaki!C13 + 'Far Lands'!C13 -> 62520908 | IK13: =((IJ13-IJ14)/IJ14) -> 0.01765523 | IL13: =SUM(IJ13/C13) -> 0.010246064 | IS13: =SUM(IT13+250) -> 2004 | IT13: 1754 | IU13: =Verste!C13 + Quidic!C13 + Erkizil!C13 + Ashain!C13 + Ahokini!C13 -> 3.3376991e+08 | IV13: =((IU13-IU14)/IU14) -> 0.012236302 | IW13: =SUM(IU13/C13) -> 0.054698946
... A65: =SUM(B65+250) -> 1952 | B65: 1702 | C65: =Acetoa!C65 + Acrana!C65 + Aetintio!C65 + Ahokini!C65 + Amcha!C65 + Andsaudare!C65 + Anymna!C65 + Aplasia!C65 + Arbiya!C65 + 'Areoix Lie'!C65 + Ashain!C65 + Astye!C65 + Baluyde!C65 + Byllu!C65 + 'Candenat'!C65 + 'Canldives'!C65 + 'Chaenia'!C65 + 'Cloja'!C65 + 'Crila Republic'!C65 + 'Cruthi Anoso'!C65 + 'Curata'!C65 + Dahe!C65 + Danocia!C65 + Darewa!C65 + Desaki!C65 + Deschon!C65 + 'Disal Nila'!C65 + 'Dual Cenryia'!C65 + Ealdorii!C65 + Easuhura!C65 + Eldavpir!C65 + Eldjo!C65 + 'Elja and Munusia'!C65 + Emara!C65 + Enina!C65 + Eparia!C65 + Erkizil!C65 + Estijan!C65 + Etirha!C65 + Etretes!C65 + Exilium!C65 + 'Far Lands'!C65 + 'Feio Lie'!C65 + Fermori!C65 + Finae!C65 + Fincen!C65 + 'Fire Coast'!C65 + Gaeiya!C65 + Galca!C65 + Genaire!C65 + Grazail!C65 + Guise!C65 + Haiza!C65 + Heiso!C65 + Hiwush!C65 + Hkuqo!C65 + Hyelen!C65 + Iainoa!C65 + Iareva!C65 + Ihner!C65 + Ikzen!C65 + Ilicuhe!C65 + Inania!C65 + Inrea!C65 + Iquir!C65 + Isari!C65 + Isnti!C65 + Isuibul!C65 + Jathua!C65 + Jau!C65 + Jshain!C65 + Kaastini!C65 + Koruch!C65 + Kusierna!C65 + Laselteh!C65 + Lasri!C65 + Letan!C65 + Lieri!C65 + Lycroa!C65 + Lydroa!C65 + Maalle!C65 + Mendereide!C65 + 'Merela Sta'!C65 + 'Mesjan Hyaa'!C65 + Metndria!C65 + Migoku!C65 + Myla!C65 + 'New Kizura'!C65 + 'New Misos'!C65 + 'Nheyes Si'!C65 + Nia!C65 + 'Niretui and Anulan'!C65 + 'Niul Spijan'!C65 + 'North Ayre'!C65 + Ocaun!C65 + Ohtina!C65 + Onphello!C65 + Oscairia!C65 + Othya!C65 + Otiiric!C65 + Oyreain!C65 + Ozinia!C65 + Palina!C65 + Peka!C65 + Pelan!C65 + Pelines!C65 + Pelugrotoa!C65 + 'Pha Hii'!C65 + Phuris!C65 + Praesyu!C65 + Prstreula!C65 + 'Pruim Fijan'!C65 + 'Prystr Hii'!C65 + Quidic!C65 + 'Raledria'!C65 + 'Reerica'!C65 + 'Rethern'!C65 + 'Rijan bu'!C65 + 'Rinew'!C65 + 'Rkmepuia'!C65 + 'Rtesania'!C65 + 'Ruylku'!C65 + Saa!C65 + Sadain!C65 + Sanagara!C65 + Sattle!C65 + Selaja!C65 + Seytinemas!C65 + Shinam!C65 + Shomjind!C65 + Siana!C65 + Sivoso!C65 + Slyiaduun!C65 + Stinebar!C65 + Suenan!C65 + Sunsokua!C65 + Taing!C65 + Taniduna!C65 + Taoisia!C65 + Taval!C65 + Terressin!C65 + Tomscilus!C65 + Tonder!C65 + Trevilla!C65 + Trian!C65 + Tvecoca!C65 + Ucrua!C65 + Ukhdari!C65 + Umarcia!C65 + Umendel!C65 + 'United Delet'!C65 + 'United Mihili'!C65 + Urbiqu!C65 + Uularin!C65 + Vayvele!C65 + Veelmit!C65 + Verste!C65 + Verusa!C65 + Vesozata!C65 + Viussi!C65 + Volver!C65 + Walporein!C65 + 'Welenu Fana'!C65 + 'Western Migoku'!C65 + Wundry!C65 + Yaxuto!C65 + Yihnurda!C65 + Yoprioq!C65 + Yutnitu!C65 + Zenashan!C65 + Zhanshe!C65 + Ztesh!C65 -> 2.6121848e+09 | D65: =((C65-C66)/C66) -> 0.019026534 | K65: =SUM(L65+250) -> 1952 | L65: 1702 | M65: =Eldavpir!C65 + Iquir!C65 + Viussi!C65 + Umendel!C65 + 'Reerica'!C65 + Saa!C65 + Sattle!C65 -> 19038479 | N65: =((M65-M66)/M66) -> 0.022285246 | O65: =SUM(M65/C65) -> 0.0072883353 | V65: =SUM(W65+250) -> 1952 | W65: 1702 | X65: ='Areoix Lie'!C65 + Jau!C65 + Terressin!C65 + Acetoa!C65 + 'Feio Lie'!C65 -> 2.7194694e+08 | Y65: =((X65-X66)/X66) -> 0.025549361 | Z65: =SUM(X65/C65) -> 0.10410708 | AG65: =SUM(AH65+250) -> 1952 | AH65: 1702 | AI65: =Taniduna!C65 + Jathua!C65 + Deschon!C65 + Pelines!C65 + 'Candenat'!C65 + Othya!C65 + Yoprioq!C65 + Jshain!C65 + 'Fire Coast'!C65 + 'Rijan bu'!C65 + 'Rinew'!C65 + Enina!C65 + Trevilla!C65 -> 50231467 | AJ65: =((AI65-AI66)/AI66) -> 0.021768755 | AK65: =SUM(AI65/C65) -> 0.019229676 | AR65: =SUM(AS65+250) -> 1952 | AS65: 1702 | AT65: =Gaeiya!C65 + 'Raledria'!C65 + Arbiya!C65 + Fincen!C65 + 'Curata'!C65 -> 1.2617458e+08 | AU65: =((AT65-AT66)/AT66) -> 0.02091482 | AV65: =SUM(AT65/C65) -> 0.048302319 | BC65: =SUM(BD65+250) -> 1952 | BD65: 1702 | BE65: =Etirha!C65 + Laselteh!C65 + Grazail!C65 + 'Disal Nila'!C65 + Pelan!C65 + Peka!C65 + Guise!C65 -> 49356347 | BF65: =((BE65-BE66)/BE66) -> 0.021342238 | BG65: =SUM(BE65/C65) -> 0.018894661 | BN65: =SUM(BO65+250) -> 1952 | BO65: 1702 | BP65: =Genaire!C65 + 'New Misos'!C65 + Phuris!C65 + Lasri!C65 + Slyiaduun!C65 + Aetintio!C65 + Metndria!C65 + Tomscilus!C65 -> 33651178 | BQ65: =((BP65-BP66)/BP66) -> 0.025678516 | BR65: =SUM(BP65/C65) -> 0.012882388 | BY65: =SUM(BZ65+250) -> 1952 | BZ65: 1702 | CA65: =Ealdorii!C65 + Ukhdari!C65 + Hkuqo!C65 + Acrana!C65 + Zenashan!C65 -> 1.2509825e+08 | CB65: =((CA65-CA66)/CA66) -> 0.011600016 | CC65: =SUM(CA65/C65) -> 0.047890277 | CJ65: =SUM(CK65+250) -> 1952 | CK65: 1702 | CL65: =Estijan!C65 + Ikzen!C65 + Urbiqu!C65 + Danocia!C65 + Koruch!C65 + 'New Kizura'!C65 + Lydroa!C65 + Fermori!C65 + Uularin!C65 + 'Niul Spijan'!C65 -> 1.44619e+08 | CM65: =((CL65-CL66)/CL66) -> 0.018819984 | CN65: =SUM(CL65/C65) -> 0.055363235 | CU65: =SUM(CV65+250) -> 1952 | CV65: 1702 | CW65: =Praesyu!C65 + Lycroa!C65 + Emara!C65 + Eldjo!C65 + Easuhura!C65 + Ilicuhe!C65 + Tonder!C65 -> 1.8369805e+08 | CX65: =((CW65-CW66)/CW66) -> 0.0058918983 | CY65: =SUM(CW65/C65) -> 0.070323527 | DF65: =SUM(DG65+250) -> 1952 | DG65: 1702 | DH65: =Verusa!C65 + Darewa!C65 + Siana!C65 + Yaxuto!C65 + 'Merela Sta'!C65 + Palina!C65 -> 1.2590938e+08 | DI65: =((DH65-DH66)/DH66) -> 0.011033894 | DJ65: =SUM(DH65/C65) -> 0.048200793 | DQ65: =SUM(DR65+250) -> 1952 | DR65: 1702 | DS65: =Sunsokua!C65 + Vayvele!C65 + Selaja!C65 + Sadain!C65 -> 57125099 | DT65: =((DS65-DS66)/DS66) -> 0.021871171 | DU65: =SUM(DS65/C65) -> 0.021868705 | EB65: =SUM(EC65+250) -> 1952 | EC65: 1702 | ED65: =Pelugrotoa!C65 + Lieri!C65 + 'Rtesania'!C65 + Ozinia!C65 -> 1.3800774e+08 | EE65: =((ED65-ED66)/ED66) -> 0.034351551 | EF65: =SUM(ED65/C65) -> 0.052832304 | EM65: =SUM(EN65+250) -> 1952 | EN65: 1702 | EO65: =Ocaun!C65 + 'Dual Cenryia'!C65 + Byllu!C65 + Exilium!C65 + Inrea!C65 + Amcha!C65 + Isnti!C65 + Galca!C65 + Otiiric!C65 + Taing!C65 + 'Cruthi Anoso'!C65 -> 68751222 | EP65: =((EO65-EO66)/EO66) -> 0.021357492 | EQ65: =SUM(EO65/C65) -> 0.026319433 | EX65: =SUM(EY65+250) -> 1952 | EY65: 1702 | EZ65: =Sivoso!C65 + Taoisia!C65 + Seytinemas!C65 + Trian!C65 + 'Chaenia'!C65 -> 42912594 | FA65: =((EZ65-EZ66)/EZ66) -> 0.026132687 | FB65: =SUM(EZ65/C65) -> 0.016427855 | FI65: =SUM(FJ65+250) -> 1952 | FJ65: 1702 | FK65: =Migoku!C65 + 'Welenu Fana'!C65 + Haiza!C65 + Ucrua!C65 + Ihner!C65 + Oscairia!C65 + Shinam!C65 + 'Ruylku'!C65 + Taval!C65 + 'Western Migoku'!C65 + 'Pruim Fijan'!C65 + 'Canldives'!C65 -> 55589153 | FL65: =((FK65-FK66)/FK66) -> 0.01606534 | FM65: =SUM(FK65/C65) -> 0.021280712 | FT65: =SUM(FU65+250) -> 1952 | FU65: 1702 | FV65: =Vesozata!C65 + Etretes!C65 + Kusierna!C65 + Eparia!C65 -> 33313515 | FW65: =((FV65-FV66)/FV66) -> 0.023384164 | FX65: =SUM(FV65/C65) -> 0.012753123 | GE65: =SUM(GF65+250) -> 1952 | GF65: 1702 | GG65: =Dahe!C65 + Kaastini!C65 + Suenan!C65 + Oyreain!C65 + Sanagara!C65 + 'North Ayre'!C65 + Stinebar!C65 + 'Cloja'!C65 + 'Pha Hii'!C65 + 'Prystr Hii'!C65 -> 5.7268858e+08 | GH65: =((GG65-GG66)/GG66) -> 0.015060339 | GI65: =SUM(GG65/C65) -> 0.21923739 | GP65: =SUM(GQ65+250) -> 1952 | GQ65: 1702 | GR65: =Maalle!C65 + 'United Delet'!C65 + Ohtina!C65 + Astye!C65 + Prstreula!C65 + Veelmit!C65 + Aplasia!C65 + 'Elja and Munusia'!C65 + Walporein!C65 + 'Crila Republic'!C65 + 'Niretui and Anulan'!C65 + 'Rethern'!C65 + Tvecoca!C65 -> 62377222 | GS65: =((GR65-GR66)/GR66) -> 0.018415522 | GT65: =SUM(GR65/C65) -> 0.023879329 | HA65: =SUM(HB65+250) -> 1952 | HB65: 1702 | HC65: =Andsaudare!C65 + Nia!C65 + Umarcia!C65 + Mendereide!C65 + Iainoa!C65 + Isari!C65 + 'Rkmepuia'!C65 + Hiwush!C65 + Isuibul!C65 + Yutnitu!C65 -> 19285750 | HD65: =((HC65-HC66)/HC66) -> 0.024065025 | HE65: =SUM(HC65/C65) -> 0.0073829959 | HL65: =SUM(HM65+250) -> 1952 | HM65: 1702 | HN65: =Zhanshe!C65 + Volver!C65 + Finae!C65 + Myla!C65 + 'Nheyes Si'!C65 + Onphello!C65 + Hyelen!C65 -> 34151816 | HO65: =((HN65-HN66)/HN66) -> 0.027839416 | HP65: =SUM(HN65/C65) -> 0.013074043 | HW65: =SUM(HX65+250) -> 1952 | HX65: 1702 | HY65: =Yihnurda!C65 + Ztesh!C65 + Wundry!C65 + Anymna!C65 + Shomjind!C65 + Baluyde!C65 + Letan!C65 -> 1.5693996e+08 | HZ65: =((HY65-HY66)/HY66) -> 0.016606126 | IA65: =SUM(HY65/C65) -> 0.060079961 | IH65: =SUM(II65+250) -> 1952 | II65: 1702 | IJ65: =Iareva!C65 + 'United Mihili'!C65 + 'Mesjan Hyaa'!C65 + Desaki!C65 + 'Far Lands'!C65 -> 18642300 | IK65: =((IJ65-IJ66)/IJ66) -> 0.018595051 | IL65: =SUM(IJ65/C65) -> 0.0071366696 | IS65: =SUM(IT65+250) -> 1952 | IT65: 1702 | IU65: =Verste!C65 + Quidic!C65 + Erkizil!C65 + Ashain!C65 + Ahokini!C65 -> 1.2018645e+08 | IV65: =((IU65-IU66)/IU66) -> 0.022246821 | IW65: =SUM(IU65/C65) -> 0.046009933
